Workbook
Name asdasd: #REF!
Name asdasd: #REF!
Name asdasdasdefasdf: #REF!
Name asdasdasdefasdf: #REF!
Name DFGDFG: #REF!
Name DFGDFG: #REF!
Name FDFSDFSD: #REF!
Name FDFSDFSD: #REF!
Name GHFHGF: #REF!
Name GHFHGF: #REF!
Name ghjghj: #REF!
Name ghjghj: #REF!
Name GRTG: #REF!
Name GRTG: #REF!
Name gyhfgh: #REF!
Name gyhfgh: #REF!
Name HGVG: #REF!
Name HGVG: #REF!
Name IND: #REF!
Name IND: #REF!
Name INDT: #REF!
Name INDT: #REF!
Name ORÇ: #REF!
Name ORÇ: #REF!
Name ORÇDET: #REF!
Name ORÇDET: #REF!
Name PF04.011: #REF!
Name PF04.011: #REF!
Name RES: #REF!
Name RES: #REF!
Name sadfsd: #REF!
Name sadfsd: #REF!
Name saswd: #REF!
Name saswd: #REF!
Name SDFSDF: #REF!
Name SDFSDF: #REF!
Name sdfsfd: #REF!
Name sdfsfd: #REF!

Sheet ORÇ#1
A1: Column1 | B1: Column2 | C1: Column3 | D1: Column4 | E1: Column5 | F1: Column6 | G1: Column7 | H1: Column8 | I1: Column9 | J1: Column10 | K1: Column11 | L1: Column12 | M1: Column13 | N1: Column14 | O1: Column15 | P1: Column16 | Q1: Column17 | R1: Column18 | S1: Column19 | T1: Column20 | U1: Column21 | V1: Column22 | W1: Column23 | X1: Column24 | Y1: Column25 | Z1: Column26 | AA1: Column27 | AB1: Column28 | AC1: Column29 | AD1: Column30 | AE1: Column31 | AF1: Column32 | AG1: Column33 | AH1: Column34 | AI1: Column35 | AJ1: Column36 | AK1: Column37
K6: a | W6: a | AA6: AAS | AC6: AAS
M7: ITEM | N7: CPU | O7: SINAPI | P7: DESCRIÇÃO DO SERVIÇO | Q7: QUANT. | R7: UNID. | S7: PREÇO UNITÁRIO | V7: PREÇO TOTAL | X7: PREÇO UNIT. M.O. | Y7: TOTAL MÃO DE OBRA | Z7: PREÇO UNIT. MAT. | AA7: TOTAL MATERIAL | AB7: PREÇO UNIT. EQUIP. | AC7: TOTAL EQUIPAMENTO | AE7: PREÇO TOTAL + BDI | AG7: INCIDÊNCIA (%) | AI7: OBSERVAÇÕES
AF8: 0 | AH8: 0
A9: n1 | F9: 1 | L9: 1 | M9: 1 | N9: CI | P9: CUSTOS INDIRETOS | V9: 224917,9 | Y9: 221273,5002 | AA9: 3644,3998 | AC9: 0 | AE9: 269901,48 | AF9: 0 | AG9: 0,036284423385 | AH9: 0 | AK9: 0
L10: 0
A11: n2 | B11: 1 | C11: 1 | G11: 1 | H11: CI | I11: CI.1 | M11: 1.1 | N11: CI.1 | P11: CUSTO ADMINISTRATIVO | V11: 224917,9 | Y11: 221273,5002 | AA11: 3644,3998 | AC11: 0 | AE11: 269901,48 | AF11: 0 | AG11: 0,036284423385 | AH11: 0 | AK11: 0
L12: 0
A13: n3 | B13: 1 | C13: 1 | D13: 1 | G13: 11 | M13: 1.1.1 | O13: 93567 | P13: ENGENHEIRO CIVIL DE OBRA PLENO COM ENCARGOS COMPLEMENTARES | Q13: 10 | R13: MES | S13: 22491,79 | V13: 224917,9 | X13: 22127,35 | Y13: 221273,5002 | Z13: 364,44 | AA13: 3644,3998 | AB13: 0 | AC13: 0 | AE13: 269901,48 | AF13: 0 | AG13: 0,036284423385 | AH13: 0 | AK13: 0
A14: n4 | B14: 1 | C14: 1 | D14: 1 | E14: 1 | G14: 111 | H14: 93567 | I14: 2 | J14: 93567-2 | L14: 0 | M14: 1.1.1.1 | O14: 40813 | P14: ENGENHEIRO CIVIL DE OBRA PLENO (MENSALISTA) | Q14: 1 | R14: MES | S14: 21872,32 | T14: 10 | U14: 10 | V14: 21872,32 | AE14: 26246,784 | AF14: 0 | AG14: 10 MES | AH14: 0 | AK14: 0
A15: n4 | B15: 1 | C15: 1 | D15: 1 | E15: 2 | G15: 111 | H15: 93567 | I15: 3 | J15: 93567-3 | L15: 0 | M15: 1.1.1.2 | O15: 40863 | P15: EXAMES - MENSALISTA (COLETADO CAIXA - ENCARGOS COMPLEMENTARES) | Q15: 1 | R15: MES | S15: 215,56 | T15: 10 | U15: 10 | V15: 215,56 | AE15: 258,672 | AF15: 0 | AG15: 10 MES | AH15: 0 | AK15: 0
A16: n4 | B16: 1 | C16: 1 | D16: 1 | E16: 3 | G16: 111 | H16: 93567 | I16: 4 | J16: 93567-4 | L16: 0 | M16: 1.1.1.3 | O16: 40864 | P16: SEGURO - MENSALISTA (COLETADO CAIXA - ENCARGOS COMPLEMENTARES) | Q16: 1 | R16: MES | S16: 12,89 | T16: 10 | U16: 10 | V16: 12,89 | AE16: 15,468 | AF16: 0 | AG16: 10 MES | AH16: 0 | AK16: 0
A17: n4 | B17: 1 | C17: 1 | D17: 1 | E17: 4 | G17: 111 | H17: 93567 | I17: 5 | J17: 93567-5 | L17: 0 | M17: 1.1.1.4 | O17: 43474 | P17: FERRAMENTAS - FAMILIA ENGENHEIRO CIVIL - MENSALISTA (ENCARGOS COMPLEMENTARES - COLETADO CAIXA) | Q17: 1 | R17: MES | S17: 2,54 | T17: 10 | U17: 10 | V17: 2,54 | AE17: 3,048 | AF17: 0 | AG17: 10 MES | AH17: 0 | AK17: 0
A18: n4 | B18: 1 | C18: 1 | D18: 1 | E18: 5 | G18: 111 | H18: 93567 | I18: 6 | J18: 93567-6 | L18: 0 | M18: 1.1.1.5 | O18: 43498 | P18: EPI - FAMILIA ENGENHEIRO CIVIL - MENSALISTA (ENCARGOS COMPLEMENTARES - COLETADO CAIXA) | Q18: 1 | R18: MES | S18: 133,45 | T18: 10 | U18: 10 | V18: 133,45 | AE18: 160,14 | AF18: 0 | AG18: 10 MES | AH18: 0 | AK18: 0
A19: n4 | B19: 1 | C19: 1 | D19: 1 | E19: 6 | G19: 111 | H19: 93567 | I19: 7 | J19: 93567-7 | L19: 0 | M19: 1.1.1.6 | O19: 95417 | P19: CURSO DE CAPACITAÇÃO PARA ENGENHEIRO CIVIL DE OBRA PLENO (ENCARGOS COMPLEMENTARES) - MENSALISTA | Q19: 1 | R19: MES | S19: 255,03 | T19: 10 | U19: 10 | V19: 255,03 | AE19: 306,036 | AF19: 0 | AG19: 10 MES | AH19: 0 | AK19: 0
A20: n4 | B20: 1 | C20: 1 | D20: 1 | E20: 7 | G20: 111 | H20: 93567 | I20: 8 | J20: 93567-8 | L20: 0 | T20: 10 | AF20: 0 | AH20: 0 | AK20: 0
A21: n4 | B21: 1 | C21: 1 | D21: 1 | E21: 8 | G21: 111 | H21: 93567 | I21: 9 | J21: 93567-9 | L21: 0 | T21: 10 | AF21: 0 | AH21: 0 | AK21: 0
A22: n4 | B22: 1 | C22: 1 | D22: 1 | E22: 9 | G22: 111 | H22: 93567 | I22: 10 | J22: 93567-10 | L22: 0 | T22: 10 | AF22: 0 | AH22: 0 | AK22: 0
A23: n4 | B23: 1 | C23: 1 | D23: 1 | E23: 10 | G23: 111 | H23: 93567 | I23: 11 | J23: 93567-11 | L23: 0 | T23: 10 | AF23: 0 | AH23: 0 | AK23: 0
A24: n4 | B24: 1 | C24: 1 | D24: 1 | E24: 11 | G24: 111 | H24: 93567 | I24: 12 | J24: 93567-12 | L24: 0 | T24: 10 | AF24: 0 | AH24: 0 | AK24: 0
A25: n4 | B25: 1 | C25: 1 | D25: 1 | E25: 12 | G25: 111 | H25: 93567 | I25: 13 | J25: 93567-13 | L25: 0 | T25: 10 | AF25: 0 | AH25: 0 | AK25: 0
A26: n4 | B26: 1 | C26: 1 | D26: 1 | E26: 13 | G26: 111 | H26: 93567 | I26: 14 | J26: 93567-14 | L26: 0 | T26: 10 | AF26: 0 | AH26: 0 | AK26: 0
A27: n4 | B27: 1 | C27: 1 | D27: 1 | E27: 14 | G27: 111 | H27: 93567 | I27: 15 | J27: 93567-15 | L27: 0 | T27: 10 | AF27: 0 | AH27: 0 | AK27: 0
A28: n4 | B28: 1 | C28: 1 | D28: 1 | E28: 15 | G28: 111 | H28: 93567 | I28: 16 | J28: 93567-16 | L28: 0 | T28: 10 | AF28: 0 | AH28: 0 | AK28: 0
L29: 0
A30: n3 | B30: 1 | C30: 1 | D30: 2 | G30: 11 | L30: 0 | S30: 0 | AF30: 0 | AH30: 0 | AK30: 0
A31: n4 | B31: 1 | C31: 1 | D31: 2 | E31: 1 | G31: 112 | H31: 0 | I31: 2 | J31: 0-2 | L31: 0 | T31: 0 | AF31: 0 | AH31: 0 | AK31: 0
A32: n4 | B32: 1 | C32: 1 | D32: 2 | E32: 2 | G32: 112 | H32: 0 | I32: 3 | J32: 0-3 | L32: 0 | T32: 0 | AF32: 0 | AH32: 0 | AK32: 0
A33: n4 | B33: 1 | C33: 1 | D33: 2 | E33: 3 | G33: 112 | H33: 0 | I33: 4 | J33: 0-4 | L33: 0 | T33: 0 | AF33: 0 | AH33: 0 | AK33: 0
A34: n4 | B34: 1 | C34: 1 | D34: 2 | E34: 4 | G34: 112 | H34: 0 | I34: 5 | J34: 0-5 | L34: 0 | T34: 0 | AF34: 0 | AH34: 0 | AK34: 0
A35: n4 | B35: 1 | C35: 1 | D35: 2 | E35: 5 | G35: 112 | H35: 0 | I35: 6 | J35: 0-6 | L35: 0 | T35: 0 | AF35: 0 | AH35: 0 | AK35: 0
A36: n4 | B36: 1 | C36: 1 | D36: 2 | E36: 6 | G36: 112 | H36: 0 | I36: 7 | J36: 0-7 | L36: 0 | T36: 0 | AF36: 0 | AH36: 0 | AK36: 0
A37: n4 | B37: 1 | C37: 1 | D37: 2 | E37: 7 | G37: 112 | H37: 0 | I37: 8 | J37: 0-8 | L37: 0 | T37: 0 | AF37: 0 | AH37: 0 | AK37: 0
A38: n4 | B38: 1 | C38: 1 | D38: 2 | E38: 8 | G38: 112 | H38: 0 | I38: 9 | J38: 0-9 | L38: 0 | T38: 0 | AF38: 0 | AH38: 0 | AK38: 0
A39: n4 | B39: 1 | C39: 1 | D39: 2 | E39: 9 | G39: 112 | H39: 0 | I39: 10 | J39: 0-10 | L39: 0 | T39: 0 | AF39: 0 | AH39: 0 | AK39: 0
A40: n4 | B40: 1 | C40: 1 | D40: 2 | E40: 10 | G40: 112 | H40: 0 | I40: 11 | J40: 0-11 | L40: 0 | T40: 0 | AF40: 0 | AH40: 0 | AK40: 0
A41: n4 | B41: 1 | C41: 1 | D41: 2 | E41: 11 | G41: 112 | H41: 0 | I41: 12 | J41: 0-12 | L41: 0 | T41: 0 | AF41: 0 | AH41: 0 | AK41: 0
A42: n4 | B42: 1 | C42: 1 | D42: 2 | E42: 12 | G42: 112 | H42: 0 | I42: 13 | J42: 0-13 | L42: 0 | T42: 0 | AF42: 0 | AH42: 0 | AK42: 0
... A45: n4 | B45: 1 | C45: 1 | D45: 2 | E45: 15 | G45: 112 | H45: 0 | I45: 16 | J45: 0-16 | L45: 0 | T45: 0 | AF45: 0 | AH45: 0 | AK45: 0
L46: 0
A47: n3 | B47: 1 | C47: 1 | D47: 3 | G47: 11 | L47: 0 | S47: 0 | AF47: 0 | AH47: 0 | AK47: 0
A48: n4 | B48: 1 | C48: 1 | D48: 3 | E48: 1 | G48: 113 | H48: 0 | I48: 2 | J48: 0-2 | L48: 0 | T48: 0 | AF48: 0 | AH48: 0 | AK48: 0
A49: n4 | B49: 1 | C49: 1 | D49: 3 | E49: 2 | G49: 113 | H49: 0 | I49: 3 | J49: 0-3 | L49: 0 | T49: 0 | AF49: 0 | AH49: 0 | AK49: 0
A50: n4 | B50: 1 | C50: 1 | D50: 3 | E50: 3 | G50: 113 | H50: 0 | I50: 4 | J50: 0-4 | L50: 0 | T50: 0 | AF50: 0 | AH50: 0 | AK50: 0
A51: n4 | B51: 1 | C51: 1 | D51: 3 | E51: 4 | G51: 113 | H51: 0 | I51: 5 | J51: 0-5 | L51: 0 | T51: 0 | AF51: 0 | AH51: 0 | AK51: 0
A52: n4 | B52: 1 | C52: 1 | D52: 3 | E52: 5 | G52: 113 | H52: 0 | I52: 6 | J52: 0-6 | L52: 0 | T52: 0 | AF52: 0 | AH52: 0 | AK52: 0
A53: n4 | B53: 1 | C53: 1 | D53: 3 | E53: 6 | G53: 113 | H53: 0 | I53: 7 | J53: 0-7 | L53: 0 | T53: 0 | AF53: 0 | AH53: 0 | AK53: 0
A54: n4 | B54: 1 | C54: 1 | D54: 3 | E54: 7 | G54: 113 | H54: 0 | I54: 8 | J54: 0-8 | L54: 0 | T54: 0 | AF54: 0 | AH54: 0 | AK54: 0
A55: n4 | B55: 1 | C55: 1 | D55: 3 | E55: 8 | G55: 113 | H55: 0 | I55: 9 | J55: 0-9 | L55: 0 | T55: 0 | AF55: 0 | AH55: 0 | AK55: 0
A56: n4 | B56: 1 | C56: 1 | D56: 3 | E56: 9 | G56: 113 | H56: 0 | I56: 10 | J56: 0-10 | L56: 0 | T56: 0 | AF56: 0 | AH56: 0 | AK56: 0
A57: n4 | B57: 1 | C57: 1 | D57: 3 | E57: 10 | G57: 113 | H57: 0 | I57: 11 | J57: 0-11 | L57: 0 | T57: 0 | AF57: 0 | AH57: 0 | AK57: 0
A58: n4 | B58: 1 | C58: 1 | D58: 3 | E58: 11 | G58: 113 | H58: 0 | I58: 12 | J58: 0-12 | L58: 0 | T58: 0 | AF58: 0 | AH58: 0 | AK58: 0
A59: n4 | B59: 1 | C59: 1 | D59: 3 | E59: 12 | G59: 113 | H59: 0 | I59: 13 | J59: 0-13 | L59: 0 | T59: 0 | AF59: 0 | AH59: 0 | AK59: 0
... A62: n4 | B62: 1 | C62: 1 | D62: 3 | E62: 15 | G62: 113 | H62: 0 | I62: 16 | J62: 0-16 | L62: 0 | T62: 0 | AF62: 0 | AH62: 0 | AK62: 0
L63: 0
A64: n3 | B64: 1 | C64: 1 | D64: 4 | G64: 11 | L64: 0 | S64: 0 | AF64: 0 | AH64: 0 | AK64: 0
A65: n4 | B65: 1 | C65: 1 | D65: 4 | E65: 1 | G65: 114 | H65: 0 | I65: 2 | J65: 0-2 | L65: 0 | T65: 0 | AF65: 0 | AH65: 0 | AK65: 0
A66: n4 | B66: 1 | C66: 1 | D66: 4 | E66: 2 | G66: 114 | H66: 0 | I66: 3 | J66: 0-3 | L66: 0 | T66: 0 | AF66: 0 | AH66: 0 | AK66: 0
A67: n4 | B67: 1 | C67: 1 | D67: 4 | E67: 3 | G67: 114 | H67: 0 | I67: 4 | J67: 0-4 | L67: 0 | T67: 0 | AF67: 0 | AH67: 0 | AK67: 0
A68: n4 | B68: 1 | C68: 1 | D68: 4 | E68: 4 | G68: 114 | H68: 0 | I68: 5 | J68: 0-5 | L68: 0 | T68: 0 | AF68: 0 | AH68: 0 | AK68: 0
A69: n4 | B69: 1 | C69: 1 | D69: 4 | E69: 5 | G69: 114 | H69: 0 | I69: 6 | J69: 0-6 | L69: 0 | T69: 0 | AF69: 0 | AH69: 0 | AK69: 0
A70: n4 | B70: 1 | C70: 1 | D70: 4 | E70: 6 | G70: 114 | H70: 0 | I70: 7 | J70: 0-7 | L70: 0 | T70: 0 | AF70: 0 | AH70: 0 | AK70: 0
A71: n4 | B71: 1 | C71: 1 | D71: 4 | E71: 7 | G71: 114 | H71: 0 | I71: 8 | J71: 0-8 | L71: 0 | T71: 0 | AF71: 0 | AH71: 0 | AK71: 0
A72: n4 | B72: 1 | C72: 1 | D72: 4 | E72: 8 | G72: 114 | H72: 0 | I72: 9 | J72: 0-9 | L72: 0 | T72: 0 | AF72: 0 | AH72: 0 | AK72: 0
A73: n4 | B73: 1 | C73: 1 | D73: 4 | E73: 9 | G73: 114 | H73: 0 | I73: 10 | J73: 0-10 | L73: 0 | T73: 0 | AF73: 0 | AH73: 0 | AK73: 0
A74: n4 | B74: 1 | C74: 1 | D74: 4 | E74: 10 | G74: 114 | H74: 0 | I74: 11 | J74: 0-11 | L74: 0 | T74: 0 | AF74: 0 | AH74: 0 | AK74: 0
A75: n4 | B75: 1 | C75: 1 | D75: 4 | E75: 11 | G75: 114 | H75: 0 | I75: 12 | J75: 0-12 | L75: 0 | T75: 0 | AF75: 0 | AH75: 0 | AK75: 0
A76: n4 | B76: 1 | C76: 1 | D76: 4 | E76: 12 | G76: 114 | H76: 0 | I76: 13 | J76: 0-13 | L76: 0 | T76: 0 | AF76: 0 | AH76: 0 | AK76: 0
... A79: n4 | B79: 1 | C79: 1 | D79: 4 | E79: 15 | G79: 114 | H79: 0 | I79: 16 | J79: 0-16 | L79: 0 | T79: 0 | AF79: 0 | AH79: 0 | AK79: 0
L80: 0
A81: n3 | B81: 1 | C81: 1 | D81: 5 | G81: 11 | L81: 0 | S81: 0 | AF81: 0 | AH81: 0 | AK81: 0
A82: n4 | B82: 1 | C82: 1 | D82: 5 | E82: 1 | G82: 115 | H82: 0 | I82: 2 | J82: 0-2 | L82: 0 | T82: 0 | AF82: 0 | AH82: 0 | AK82: 0
A83: n4 | B83: 1 | C83: 1 | D83: 5 | E83: 2 | G83: 115 | H83: 0 | I83: 3 | J83: 0-3 | L83: 0 | T83: 0 | AF83: 0 | AH83: 0 | AK83: 0
A84: n4 | B84: 1 | C84: 1 | D84: 5 | E84: 3 | G84: 115 | H84: 0 | I84: 4 | J84: 0-4 | L84: 0 | T84: 0 | AF84: 0 | AH84: 0 | AK84: 0
A85: n4 | B85: 1 | C85: 1 | D85: 5 | E85: 4 | G85: 115 | H85: 0 | I85: 5 | J85: 0-5 | L85: 0 | T85: 0 | AF85: 0 | AH85: 0 | AK85: 0
A86: n4 | B86: 1 | C86: 1 | D86: 5 | E86: 5 | G86: 115 | H86: 0 | I86: 6 | J86: 0-6 | L86: 0 | T86: 0 | AF86: 0 | AH86: 0 | AK86: 0
A87: n4 | B87: 1 | C87: 1 | D87: 5 | E87: 6 | G87: 115 | H87: 0 | I87: 7 | J87: 0-7 | L87: 0 | T87: 0 | AF87: 0 | AH87: 0 | AK87: 0
A88: n4 | B88: 1 | C88: 1 | D88: 5 | E88: 7 | G88: 115 | H88: 0 | I88: 8 | J88: 0-8 | L88: 0 | T88: 0 | AF88: 0 | AH88: 0 | AK88: 0
A89: n4 | B89: 1 | C89: 1 | D89: 5 | E89: 8 | G89: 115 | H89: 0 | I89: 9 | J89: 0-9 | L89: 0 | T89: 0 | AF89: 0 | AH89: 0 | AK89: 0
A90: n4 | B90: 1 | C90: 1 | D90: 5 | E90: 9 | G90: 115 | H90: 0 | I90: 10 | J90: 0-10 | L90: 0 | T90: 0 | AF90: 0 | AH90: 0 | AK90: 0
A91: n4 | B91: 1 | C91: 1 | D91: 5 | E91: 10 | G91: 115 | H91: 0 | I91: 11 | J91: 0-11 | L91: 0 | T91: 0 | AF91: 0 | AH91: 0 | AK91: 0
A92: n4 | B92: 1 | C92: 1 | D92: 5 | E92: 11 | G92: 115 | H92: 0 | I92: 12 | J92: 0-12 | L92: 0 | T92: 0 | AF92: 0 | AH92: 0 | AK92: 0
A93: n4 | B93: 1 | C93: 1 | D93: 5 | E93: 12 | G93: 115 | H93: 0 | I93: 13 | J93: 0-13 | L93: 0 | T93: 0 | AF93: 0 | AH93: 0 | AK93: 0
... A96: n4 | B96: 1 | C96: 1 | D96: 5 | E96: 15 | G96: 115 | H96: 0 | I96: 16 | J96: 0-16 | L96: 0 | T96: 0 | AF96: 0 | AH96: 0 | AK96: 0
L97: 0
L98: 0
A99: n2 | B99: 1 | C99: 2 | G99: 1 | H99: CI | I99: CI.2 | L99: 0 | V99: 0 | Y99: 0 | AA99: 0 | AC99: 0 | AE99: 0 | AF99: 0 | AG99: 0 | AH99: 0 | AK99: 0
L100: 0
A101: n3 | B101: 1 | C101: 2 | D101: 1 | G101: 12 | L101: 0 | S101: 0 | AF101: 0 | AH101: 0 | AK101: 0
A102: n4 | B102: 1 | C102: 2 | D102: 1 | E102: 1 | G102: 121 | H102: 0 | I102: 2 | J102: 0-2 | L102: 0 | T102: 0 | AF102: 0 | AH102: 0 | AK102: 0
A103: n4 | B103: 1 | C103: 2 | D103: 1 | E103: 2 | G103: 121 | H103: 0 | I103: 3 | J103: 0-3 | L103: 0 | T103: 0 | AF103: 0 | AH103: 0 | AK103: 0
A104: n4 | B104: 1 | C104: 2 | D104: 1 | E104: 3 | G104: 121 | H104: 0 | I104: 4 | J104: 0-4 | L104: 0 | T104: 0 | AF104: 0 | AH104: 0 | AK104: 0
A105: n4 | B105: 1 | C105: 2 | D105: 1 | E105: 4 | G105: 121 | H105: 0 | I105: 5 | J105: 0-5 | L105: 0 | T105: 0 | AF105: 0 | AH105: 0 | AK105: 0
A106: n4 | B106: 1 | C106: 2 | D106: 1 | E106: 5 | G106: 121 | H106: 0 | I106: 6 | J106: 0-6 | L106: 0 | T106: 0 | AF106: 0 | AH106: 0 | AK106: 0
A107: n4 | B107: 1 | C107: 2 | D107: 1 | E107: 6 | G107: 121 | H107: 0 | I107: 7 | J107: 0-7 | L107: 0 | T107: 0 | AF107: 0 | AH107: 0 | AK107: 0
A108: n4 | B108: 1 | C108: 2 | D108: 1 | E108: 7 | G108: 121 | H108: 0 | I108: 8 | J108: 0-8 | L108: 0 | T108: 0 | AF108: 0 | AH108: 0 | AK108: 0
A109: n4 | B109: 1 | C109: 2 | D109: 1 | E109: 8 | G109: 121 | H109: 0 | I109: 9 | J109: 0-9 | L109: 0 | T109: 0 | AF109: 0 | AH109: 0 | AK109: 0
A110: n4 | B110: 1 | C110: 2 | D110: 1 | E110: 9 | G110: 121 | H110: 0 | I110: 10 | J110: 0-10 | L110: 0 | T110: 0 | AF110: 0 | AH110: 0 | AK110: 0
A111: n4 | B111: 1 | C111: 2 | D111: 1 | E111: 10 | G111: 121 | H111: 0 | I111: 11 | J111: 0-11 | L111: 0 | T111: 0 | AF111: 0 | AH111: 0 | AK111: 0
A112: n4 | B112: 1 | C112: 2 | D112: 1 | E112: 11 | G112: 121 | H112: 0 | I112: 12 | J112: 0-12 | L112: 0 | T112: 0 | AF112: 0 | AH112: 0 | AK112: 0
...

Sheet Planilha1
B2: {=IFERROR(INDEX('ORÇ#1'!$A$1:$V$9999,SMALL(IF('ORÇ#1'!$A$1:$A$9999="n1",ROW('ORÇ#1'!$A$1:$A$9999)),ROW(A1)),6),"")} -> 1 | C2: {=IFERROR(INDEX('ORÇ#1'!$A$1:$V$9999,SMALL(IF('ORÇ#1'!$A$1:$A$9999="n1",ROW('ORÇ#1'!$A$1:$A$9999)),ROW(A1)),16),"")} -> CUSTOS INDIRETOS | D2: {=IFERROR(INDEX('ORÇ#1'!$A$1:$V$9999,SMALL(IF('ORÇ#1'!$A$1:$A$9999="n1",ROW('ORÇ#1'!$A$1:$A$9999)),ROW(A1)),22)*1,"")} -> 224917.9
B3: {=IFERROR(INDEX('ORÇ#1'!$A$1:$V$9999,SMALL(IF('ORÇ#1'!$A$1:$A$9999="n1",ROW('ORÇ#1'!$A$1:$A$9999)),ROW(A2)),6),"")} -> 2 | C3: {=IFERROR(INDEX('ORÇ#1'!$A$1:$V$9999,SMALL(IF('ORÇ#1'!$A$1:$A$9999="n1",ROW('ORÇ#1'!$A$1:$A$9999)),ROW(A2)),16),"")} -> SERVIÇOS PRELIMINARES | D3: {=IFERROR(INDEX('ORÇ#1'!$A$1:$V$9999,SMALL(IF('ORÇ#1'!$A$1:$A$9999="n1",ROW('ORÇ#1'!$A$1:$A$9999)),ROW(A2)),22)*1,"")} -> 79014.27
B4: {=IFERROR(INDEX('ORÇ#1'!$A$1:$V$9999,SMALL(IF('ORÇ#1'!$A$1:$A$9999="n1",ROW('ORÇ#1'!$A$1:$A$9999)),ROW(A3)),6),"")} -> 3 | C4: {=IFERROR(INDEX('ORÇ#1'!$A$1:$V$9999,SMALL(IF('ORÇ#1'!$A$1:$A$9999="n1",ROW('ORÇ#1'!$A$1:$A$9999)),ROW(A3)),16),"")} -> MOVIMENTAÇÃO DE TERRA | D4: {=IFERROR(INDEX('ORÇ#1'!$A$1:$V$9999,SMALL(IF('ORÇ#1'!$A$1:$A$9999="n1",ROW('ORÇ#1'!$A$1:$A$9999)),ROW(A3)),22)*1,"")} -> 3576.3
B5: {=IFERROR(INDEX('ORÇ#1'!$A$1:$V$9999,SMALL(IF('ORÇ#1'!$A$1:$A$9999="n1",ROW('ORÇ#1'!$A$1:$A$9999)),ROW(A4)),6),"")} -> 4 | C5: {=IFERROR(INDEX('ORÇ#1'!$A$1:$V$9999,SMALL(IF('ORÇ#1'!$A$1:$A$9999="n1",ROW('ORÇ#1'!$A$1:$A$9999)),ROW(A4)),16),"")} -> CONTENÇÕES | D5: {=IFERROR(INDEX('ORÇ#1'!$A$1:$V$9999,SMALL(IF('ORÇ#1'!$A$1:$A$9999="n1",ROW('ORÇ#1'!$A$1:$A$9999)),ROW(A4)),22)*1,"")} -> 18143.65
B6: {=IFERROR(INDEX('ORÇ#1'!$A$1:$V$9999,SMALL(IF('ORÇ#1'!$A$1:$A$9999="n1",ROW('ORÇ#1'!$A$1:$A$9999)),ROW(A5)),6),"")} -> 5 | C6: {=IFERROR(INDEX('ORÇ#1'!$A$1:$V$9999,SMALL(IF('ORÇ#1'!$A$1:$A$9999="n1",ROW('ORÇ#1'!$A$1:$A$9999)),ROW(A5)),16),"")} -> FUNDAÇÕES | D6: {=IFERROR(INDEX('ORÇ#1'!$A$1:$V$9999,SMALL(IF('ORÇ#1'!$A$1:$A$9999="n1",ROW('ORÇ#1'!$A$1:$A$9999)),ROW(A5)),22)*1,"")} -> 142139.33
B7: {=IFERROR(INDEX('ORÇ#1'!$A$1:$V$9999,SMALL(IF('ORÇ#1'!$A$1:$A$9999="n1",ROW('ORÇ#1'!$A$1:$A$9999)),ROW(A6)),6),"")} -> 6 | C7: {=IFERROR(INDEX('ORÇ#1'!$A$1:$V$9999,SMALL(IF('ORÇ#1'!$A$1:$A$9999="n1",ROW('ORÇ#1'!$A$1:$A$9999)),ROW(A6)),16),"")} -> ESTRUTURA | D7: {=IFERROR(INDEX('ORÇ#1'!$A$1:$V$9999,SMALL(IF('ORÇ#1'!$A$1:$A$9999="n1",ROW('ORÇ#1'!$A$1:$A$9999)),ROW(A6)),22)*1,"")} -> 1436404
B8: {=IFERROR(INDEX('ORÇ#1'!$A$1:$V$9999,SMALL(IF('ORÇ#1'!$A$1:$A$9999="n1",ROW('ORÇ#1'!$A$1:$A$9999)),ROW(A7)),6),"")} -> 7 | C8: {=IFERROR(INDEX('ORÇ#1'!$A$1:$V$9999,SMALL(IF('ORÇ#1'!$A$1:$A$9999="n1",ROW('ORÇ#1'!$A$1:$A$9999)),ROW(A7)),16),"")} -> ALVENARIAS | D8: {=IFERROR(INDEX('ORÇ#1'!$A$1:$V$9999,SMALL(IF('ORÇ#1'!$A$1:$A$9999="n1",ROW('ORÇ#1'!$A$1:$A$9999)),ROW(A7)),22)*1,"")} -> 324261.23
B9: {=IFERROR(INDEX('ORÇ#1'!$A$1:$V$9999,SMALL(IF('ORÇ#1'!$A$1:$A$9999="n1",ROW('ORÇ#1'!$A$1:$A$9999)),ROW(A8)),6),"")} -> 8 | C9: {=IFERROR(INDEX('ORÇ#1'!$A$1:$V$9999,SMALL(IF('ORÇ#1'!$A$1:$A$9999="n1",ROW('ORÇ#1'!$A$1:$A$9999)),ROW(A8)),16),"")} -> INSTALAÇÕES PREDIAIS | D9: {=IFERROR(INDEX('ORÇ#1'!$A$1:$V$9999,SMALL(IF('ORÇ#1'!$A$1:$A$9999="n1",ROW('ORÇ#1'!$A$1:$A$9999)),ROW(A8)),22)*1,"")} -> 2032618
B10: {=IFERROR(INDEX('ORÇ#1'!$A$1:$V$9999,SMALL(IF('ORÇ#1'!$A$1:$A$9999="n1",ROW('ORÇ#1'!$A$1:$A$9999)),ROW(A9)),6),"")} -> 9 | C10: {=IFERROR(INDEX('ORÇ#1'!$A$1:$V$9999,SMALL(IF('ORÇ#1'!$A$1:$A$9999="n1",ROW('ORÇ#1'!$A$1:$A$9999)),ROW(A9)),16),"")} -> PAVIMENTAÇÕES | D10: {=IFERROR(INDEX('ORÇ#1'!$A$1:$V$9999,SMALL(IF('ORÇ#1'!$A$1:$A$9999="n1",ROW('ORÇ#1'!$A$1:$A$9999)),ROW(A9)),22)*1,"")} -> 86827.514
B11: {=IFERROR(INDEX('ORÇ#1'!$A$1:$V$9999,SMALL(IF('ORÇ#1'!$A$1:$A$9999="n1",ROW('ORÇ#1'!$A$1:$A$9999)),ROW(A10)),6),"")} -> 10 | C11: {=IFERROR(INDEX('ORÇ#1'!$A$1:$V$9999,SMALL(IF('ORÇ#1'!$A$1:$A$9999="n1",ROW('ORÇ#1'!$A$1:$A$9999)),ROW(A10)),16),"")} -> REVESTIMENTOS | D11: {=IFERROR(INDEX('ORÇ#1'!$A$1:$V$9999,SMALL(IF('ORÇ#1'!$A$1:$A$9999="n1",ROW('ORÇ#1'!$A$1:$A$9999)),ROW(A10)),22)*1,"")} -> 826939.34
B12: {=IFERROR(INDEX('ORÇ#1'!$A$1:$V$9999,SMALL(IF('ORÇ#1'!$A$1:$A$9999="n1",ROW('ORÇ#1'!$A$1:$A$9999)),ROW(A11)),6),"")} -> 11 | C12: {=IFERROR(INDEX('ORÇ#1'!$A$1:$V$9999,SMALL(IF('ORÇ#1'!$A$1:$A$9999="n1",ROW('ORÇ#1'!$A$1:$A$9999)),ROW(A11)),16),"")} -> IMPERMEABILIZAÇÕES | D12: {=IFERROR(INDEX('ORÇ#1'!$A$1:$V$9999,SMALL(IF('ORÇ#1'!$A$1:$A$9999="n1",ROW('ORÇ#1'!$A$1:$A$9999)),ROW(A11)),22)*1,"")} -> 135014.29
B13: {=IFERROR(INDEX('ORÇ#1'!$A$1:$V$9999,SMALL(IF('ORÇ#1'!$A$1:$A$9999="n1",ROW('ORÇ#1'!$A$1:$A$9999)),ROW(A12)),6),"")} -> 12 | C13: {=IFERROR(INDEX('ORÇ#1'!$A$1:$V$9999,SMALL(IF('ORÇ#1'!$A$1:$A$9999="n1",ROW('ORÇ#1'!$A$1:$A$9999)),ROW(A12)),16),"")} -> GRANITOS | D13: {=IFERROR(INDEX('ORÇ#1'!$A$1:$V$9999,SMALL(IF('ORÇ#1'!$A$1:$A$9999="n1",ROW('ORÇ#1'!$A$1:$A$9999)),ROW(A12)),22)*1,"")} -> 107778.47
... B31: {=IFERROR(INDEX('ORÇ#1'!$A$1:$V$9999,SMALL(IF('ORÇ#1'!$A$1:$A$9999="n1",ROW('ORÇ#1'!$A$1:$A$9999)),ROW(A30)),6),"")} | C31: {=IFERROR(INDEX('ORÇ#1'!$A$1:$V$9999,SMALL(IF('ORÇ#1'!$A$1:$A$9999="n1",ROW('ORÇ#1'!$A$1:$A$9999)),ROW(A30)),16),"")} | D31: {=IFERROR(INDEX('ORÇ#1'!$A$1:$V$9999,SMALL(IF('ORÇ#1'!$A$1:$A$9999="n1",ROW('ORÇ#1'!$A$1:$A$9999)),ROW(A30)),22)*1,"")}

Sheet SIMULAÇÃO 01
B6: ANÁLISE DE VIABILIDADE FINANCEIRA PRELIMINAR | AR6: SIMULAÇÃO 01
B8: INFORMAÇÕES DO EMPREENDIMENTO
B10: OBRA | H10: Ed. Curupira | EW Esteves Construções | T10: CIDADE / UF | Z10: Ribeirão Preto / SP | AI10: PREÇO M² | AO10: 6682.9332
B12: MAPA DAS UNIDADES
B14: TIPOLOGIA | K14: ÁREA PRIVATIVA | T14: QUANT. | Z14: PREÇO M² | AI14: VALOR / UNIDADE | AR14: PERMUTA
B15: 1º Pav. Final 1 e 3 | K15: 73 | T15: 2 | Z15: =IF(B15<>"",$AO$10,"") -> 6682.9332 | AI15: =IF(K15=""," ",IF(Z15=""," ",Z15*K15)) -> 487854.12
B16: 1º Pav. Final 2 e 4 | K16: 70 | T16: 2 | Z16: =IF(B16<>"",$AO$10,"") -> 6682.9332 | AI16: =IF(K16=""," ",IF(Z16=""," ",Z16*K16)) -> 467805.32
B17: 2º Pav. Final 1 e 3 | K17: 73 | T17: 2 | Z17: =IF(B17<>"",$AO$10,"") -> 6682.9332 | AI17: =IF(K17=""," ",IF(Z17=""," ",Z17*K17)) -> 487854.12
B18: 2º Pav. Final 2 e 4 | K18: 70 | T18: 2 | Z18: =IF(B18<>"",$AO$10,"") -> 6682.9332 | AI18: =IF(K18=""," ",IF(Z18=""," ",Z18*K18)) -> 467805.32
B19: 3º Pav. Final 1 e 3 | K19: 73 | T19: 2 | Z19: =IF(B19<>"",$AO$10,"") -> 6682.9332 | AI19: =IF(K19=""," ",IF(Z19=""," ",Z19*K19)) -> 487854.12
B20: 3º Pav. Final 2 e 4 | K20: 70 | T20: 2 | Z20: =IF(B20<>"",$AO$10,"") -> 6682.9332 | AI20: =IF(K20=""," ",IF(Z20=""," ",Z20*K20)) -> 467805.32
B21: 4º Pav. Final 1 e 3 | K21: 73 | T21: 2 | Z21: =IF(B21<>"",$AO$10,"") -> 6682.9332 | AI21: =IF(K21=""," ",IF(Z21=""," ",Z21*K21)) -> 487854.12
B22: 4º Pav. Final 2 e 4 | K22: 70 | T22: 2 | Z22: =IF(B22<>"",$AO$10,"") -> 6682.9332 | AI22: =IF(K22=""," ",IF(Z22=""," ",Z22*K22)) -> 467805.32
B23: 5º Pav. Final 1 e 3 | K23: 73 | T23: 2 | Z23: =IF(B23<>"",$AO$10,"") -> 6682.9332 | AI23: =IF(K23=""," ",IF(Z23=""," ",Z23*K23)) -> 487854.12
B24: 5º Pav. Final 2 e 4 | K24: 70 | T24: 2 | Z24: =IF(B24<>"",$AO$10,"") -> 6682.9332 | AI24: =IF(K24=""," ",IF(Z24=""," ",Z24*K24)) -> 467805.32
Z25: =IF(B25<>"",$AO$10,"") | AI25: =IF(K25=""," ",IF(Z25=""," ",Z25*K25))
Z26: =IF(B26<>"",$AO$10,"") | AI26: =IF(K26=""," ",IF(Z26=""," ",Z26*K26))
B28: LINHA DO TEMPO | AI28: ESCALA: | AR28: MENSAL
B30: INÍCIO | F30: 45170 | J30: =IF(F30="","",F30) -> 45170 | K30: =IFERROR(DATE(YEAR(J30),IF($AR$28="MENSAL",MONTH(J30)+1,MONTH(J30)+2),1),"") -> 45200 | L30: =IFERROR(DATE(YEAR(K30),IF($AR$28="MENSAL",MONTH(K30)+1,MONTH(K30)+2),1),"") -> 45231 | M30: =IFERROR(DATE(YEAR(L30),IF($AR$28="MENSAL",MONTH(L30)+1,MONTH(L30)+2),1),"") -> 45261 | N30: =IFERROR(DATE(YEAR(M30),IF($AR$28="MENSAL",MONTH(M30)+1,MONTH(M30)+2),1),"") -> 45292 | O30: =IFERROR(DATE(YEAR(N30),IF($AR$28="MENSAL",MONTH(N30)+1,MONTH(N30)+2),1),"") -> 45323 | P30: =IFERROR(DATE(YEAR(O30),IF($AR$28="MENSAL",MONTH(O30)+1,MONTH(O30)+2),1),"") -> 45352 | Q30: =IFERROR(DATE(YEAR(P30),IF($AR$28="MENSAL",MONTH(P30)+1,MONTH(P30)+2),1),"") -> 45383 | R30: =IFERROR(DATE(YEAR(Q30),IF($AR$28="MENSAL",MONTH(Q30)+1,MONTH(Q30)+2),1),"") -> 45413 | ... AW30: =IFERROR(DATE(YEAR(AV30),IF($AR$28="MENSAL",MONTH(AV30)+1,MONTH(AV30)+2),1),"") -> 46357
B32: START VENDAS | F32: 6
B34: ETAPA | F34: MESES | AY34: I | AZ34: T
B35: Viabilidade | F35: 2 | J35: =IF(AND(J$30>=$AY35,J$30<=$AZ35),1,0) -> 1 | K35: =IF(AND(K$30>=$AY35,K$30<=$AZ35),1,0) -> 1 | L35: =IF(AND(L$30>=$AY35,L$30<=$AZ35),1,0) -> 0 | M35: =IF(AND(M$30>=$AY35,M$30<=$AZ35),1,0) -> 0 | N35: =IF(AND(N$30>=$AY35,N$30<=$AZ35),1,0) -> 0 | O35: =IF(AND(O$30>=$AY35,O$30<=$AZ35),1,0) -> 0 | P35: =IF(AND(P$30>=$AY35,P$30<=$AZ35),1,0) -> 0 | Q35: =IF(AND(Q$30>=$AY35,Q$30<=$AZ35),1,0) -> 0 | ... AW35: =IF(AND(AW$30>=$AY35,AW$30<=$AZ35),1,0) -> 0 | AY35: =F30 -> 45170 | AZ35: =DATE(YEAR(AY35),MONTH(AY35)+F35-1,1) -> 45200
B36: Aprovação | F36: 2 | J36: =IF(AND(J$30>=$AY36,J$30<=$AZ36),1,0) -> 0 | K36: =IF(AND(K$30>=$AY36,K$30<=$AZ36),1,0) -> 0 | L36: =IF(AND(L$30>=$AY36,L$30<=$AZ36),1,0) -> 1 | M36: =IF(AND(M$30>=$AY36,M$30<=$AZ36),1,0) -> 1 | N36: =IF(AND(N$30>=$AY36,N$30<=$AZ36),1,0) -> 0 | O36: =IF(AND(O$30>=$AY36,O$30<=$AZ36),1,0) -> 0 | P36: =IF(AND(P$30>=$AY36,P$30<=$AZ36),1,0) -> 0 | Q36: =IF(AND(Q$30>=$AY36,Q$30<=$AZ36),1,0) -> 0 | ... AW36: =IF(AND(AW$30>=$AY36,AW$30<=$AZ36),1,0) -> 0 | AY36: =DATE(YEAR(AZ35),MONTH(AZ35)+1,1) -> 45231 | AZ36: =DATE(YEAR(AY36),MONTH(AY36)+F36-1,1) -> 45261
B37: Vendas | F37: 30 | J37: =IF(AND(J$30>=$AY37,J$30<=$AZ37),1,0) -> 0 | K37: =IF(AND(K$30>=$AY37,K$30<=$AZ37),1,0) -> 0 | L37: =IF(AND(L$30>=$AY37,L$30<=$AZ37),1,0) -> 0 | M37: =IF(AND(M$30>=$AY37,M$30<=$AZ37),1,0) -> 0 | N37: =IF(AND(N$30>=$AY37,N$30<=$AZ37),1,0) -> 1 | O37: =IF(AND(O$30>=$AY37,O$30<=$AZ37),1,0) -> 1 | P37: =IF(AND(P$30>=$AY37,P$30<=$AZ37),1,0) -> 1 | Q37: =IF(AND(Q$30>=$AY37,Q$30<=$AZ37),1,0) -> 1 | ... AW37: =IF(AND(AW$30>=$AY37,AW$30<=$AZ37),1,0) -> 0 | AY37: =DATE(YEAR(AZ36),MONTH(AZ36)+1,1) -> 45292 | AZ37: =DATE(YEAR(AY37),MONTH(AY37)+F37-1,1) -> 46174
B38: Obras | F38: 24 | J38: =IF(AND(J$30>=$AY38,J$30<=$AZ38),1,0) -> 0 | K38: =IF(AND(K$30>=$AY38,K$30<=$AZ38),1,0) -> 0 | L38: =IF(AND(L$30>=$AY38,L$30<=$AZ38),1,0) -> 0 | M38: =IF(AND(M$30>=$AY38,M$30<=$AZ38),1,0) -> 0 | N38: =IF(AND(N$30>=$AY38,N$30<=$AZ38),1,0) -> 0 | O38: =IF(AND(O$30>=$AY38,O$30<=$AZ38),1,0) -> 0 | P38: =IF(AND(P$30>=$AY38,P$30<=$AZ38),1,0) -> 0 | Q38: =IF(AND(Q$30>=$AY38,Q$30<=$AZ38),1,0) -> 0 | ... AW38: =IF(AND(AW$30>=$AY38,AW$30<=$AZ38),1,0) -> 0 | AY38: =DATE(YEAR(AY37),MONTH(AY37)+F32,1) -> 45474 | AZ38: =DATE(YEAR(AY38),MONTH(AY38)+F38-1,1) -> 46174
B39: Legalização | F39: 2 | J39: =IF(AND(J$30>=$AY39,J$30<=$AZ39),1,0) -> 0 | K39: =IF(AND(K$30>=$AY39,K$30<=$AZ39),1,0) -> 0 | L39: =IF(AND(L$30>=$AY39,L$30<=$AZ39),1,0) -> 0 | M39: =IF(AND(M$30>=$AY39,M$30<=$AZ39),1,0) -> 0 | N39: =IF(AND(N$30>=$AY39,N$30<=$AZ39),1,0) -> 0 | O39: =IF(AND(O$30>=$AY39,O$30<=$AZ39),1,0) -> 0 | P39: =IF(AND(P$30>=$AY39,P$30<=$AZ39),1,0) -> 0 | Q39: =IF(AND(Q$30>=$AY39,Q$30<=$AZ39),1,0) -> 0 | ... AW39: =IF(AND(AW$30>=$AY39,AW$30<=$AZ39),1,0) -> 0 | AY39: =DATE(YEAR(AZ38),MONTH(AZ38)+1,1) -> 46204 | AZ39: =DATE(YEAR(AY39),MONTH(AY39)+F39-1,1) -> 46235
B41: QUADRO RESUMO
J43: UNIDADES | R43: ÁREA PRIVATIVA | AH43: VALOR GERAL DE VENDA (VGV)
B44: Vendável | J44: =J46-J45 -> 20 | R44: =R46-R45 -> 1430 | AB44: =IFERROR(R44/R46,"") -> 1 | AH44: =AH46-AH45 -> 9556594.4 | AR44: =IFERROR(AH44/AH46,"") -> 1
B45: Permuta | J45: =SUM(AR15:AW26) -> 0 | R45: =SUMPRODUCT(K15:K26,AR15:AR26) -> 0 | AB45: =IFERROR(R45/R46,"") -> 0 | AH45: =SUMPRODUCT(K15:K26,AR15:AR26,Z15:Z26) -> 0 | AR45: =IFERROR(AH45/AH46,"") -> 0
B46: TOTAL | J46: =SUM(T15:Y26) -> 20 | R46: =SUMPRODUCT(K15:K26,T15:T26) -> 1430 | AH46: =SUMPRODUCT(K15:K26,T15:T26,Z15:Z26) -> 9556594.4
B48: ÁREA DO LOTE | J48: 500 | Z48: EFICIÊNCIA | AH48: C.A.
B49: ÁREA TOTAL CONSTRUÍDA | J49: 2399.77 | Z49: =IFERROR(R46/J49,"") -> 0.59589044 | AH49: =IFERROR(J50/J48,"") -> 2.955
B50: ÁREA COMPUTÁVEL | J50: 1477.5
B52: LOTE
B54: PERMUTA | J54: =AH45 -> 0
B55: PAGAMENTO | J55: 800000 | Z55: CUSTO BASE
B56: PERMUTA FINANCEIRA | J56: 0 | Z56: =SUM(J54:Q57) -> 800000
B57: PERMUTA FÍSICA FORA | J57: 0 | Z57: =IFERROR(Z56/J48,"") -> 1600
B58: COMISSÃO | J58: 0 | N58: =(SUM(J54:K57))*J58 -> 0
B60: VALOR VENAL | J60: 400 | N60: =J60*J48 -> 200000
B61: ITBI / REGISTRO | J61: 0.02 | N61: =N60*J61 -> 4000 | Z61: CUSTO TOTAL
Z62: =SUM(J54:Q57,N58,N61,J63:Q64) -> 804000
B63: OUTORGA ONEROSA | J63: 0 | Z63: =IFERROR(Z62/J48,"") -> 1608
B64: CEPAC | J64: 0
B66: CUSTO OBRA
B68: REFERÊNCIA PROJETO PADRÃO (NBR 12.721) | R68: R8 – A
B69: MÊS DE REFERÊNCIA | R69: 45108
B70: CUSTO / M² | R70: 1825.1
B72: CUSTO HISTÓRICO / M² (ÁREA TOTAL CONSTRUÍDA)
B74: LOCAL | M74: ÁREA | R74: COEF. EQUIV. | W74: COEFICIENTE | AB74: ÁREA EQUIV. | AG74: OBSERVAÇÕES
B75: Garagem (Subsolo 1) | M75: 469.52 | R75: 0,50 a 0,75 | W75: 0.75 | AB75: =IF(M75="","",IF(W75="","",W75*M75)) -> 352.14
B76: Garagem (Subsolo 2) - Térreo | M76: 296.18 | R76: 0,50 a 0,75 | W76: 0.75 | AB76: =IF(M76="","",IF(W76="","",W76*M76)) -> 222.135
B77: Garagem (Subsolo 3) | R77: 0,50 a 0,75 | AB77: =IF(M77="","",IF(W77="","",W77*M77))
B78: Garagem (Subsolo 4) | R78: 0,50 a 0,75 | AB78: =IF(M78="","",IF(W78="","",W78*M78))
B79: Garagem (Subsolo 5) | R79: 0,50 a 0,75 | AB79: =IF(M79="","",IF(W79="","",W79*M79))
B80: Salas sem acabamento | R80: 0,75 a 0,90 | AB80: =IF(M80="","",IF(W80="","",W80*M80))
B81: Lojas sem acabamento | R81: 0,40 a 0,60 | AB81: =IF(M81="","",IF(W81="","",W81*M81))
B82: Varandas | R82: 0,75 a 1,00 | AB82: =IF(M82="","",IF(W82="","",W82*M82))
B83: Terraço ou áreas descobertas sobre lajes | M83: 155.87 | R83: 0,30 a 0,60 | W83: 0.6 | AB83: =IF(M83="","",IF(W83="","",W83*M83)) -> 93.522 | AG83: Esta área está considerada como área construída no projeto arquitetônico.
B84: Estacionamento sobre terreno | M84: 61.5 | R84: 0,05 a 0,10 | W84: 0.1 | AB84: =IF(M84="","",IF(W84="","",W84*M84)) -> 6.15
B85: Barrilhete | M85: 21.6 | R85: 0,50 a 0,75 | W85: 0.75 | AB85: =IF(M85="","",IF(W85="","",W85*M85)) -> 16.2
B86: Caixa d´água | R86: 0,50 a 0,75 | AB86: =IF(M86="","",IF(W86="","",W86*M86))
B87: Casa de máquinas | R87: 0,50 a 0,75 | AB87: =IF(M87="","",IF(W87="","",W87*M87))
B88: Piscinas, quintais, etc | R88: 0,50 a 0,75 | AB88: =IF(M88="","",IF(W88="","",W88*M88))
R90: ÁREA EQUIVALENTE | AB90: =SUM(AB75:AF88) -> 690.147
R91: ÁREA RESIDUAL | AB91: =J49-(SUM(M75:Q88)-M84-M88) -> 1456.6
R92: ÁREA EQUIVALENTE TOTAL | AB92: =AB90+AB91 -> 2146.747
B94: ITENS NÃO CONSIDERADOS NO CUB | R94: QUANTIDADE | W94: UNIDADE | AB94: VALOR UNITÁRIO | AG94: VALOR TOTAL | AL94: OBSERVAÇÕES
B95: Fundações especiais (CUB = fundações diretas até 2,50m) | R95: 1 | W95: vb | AB95: 216283.9 | AG95: =IF(R95="","",IF(AB95="","",AB95*R95)) -> 216283.9
B96: Elevadores | R96: 1 | W96: vb | AB96: 210000 | AG96: =IF(R96="","",IF(AB96="","",AB96*R96)) -> 210000
B97: Fogões | AG97: =IF(R97="","",IF(AB97="","",AB97*R97))
B98: Aquecedores | AG98: =IF(R98="","",IF(AB98="","",AB98*R98))
B99: Bombas de recalque | R99: 1 | W99: vb | AB99: 6000 | AG99: =IF(R99="","",IF(AB99="","",AB99*R99)) -> 6000
B100: Incineração | AG100: =IF(R100="","",IF(AB100="","",AB100*R100))
B101: Ar condicionado | R101: 63 | W101: vb | AB101: 1000 | AG101: =IF(R101="","",IF(AB101="","",AB101*R101)) -> 63000
B102: Calefação | AG102: =IF(R102="","",IF(AB102="","",AB102*R102))
B103: Ventilação e exaustão | R103: 10 | W103: vb | AB103: 500 | AG103: =IF(R103="","",IF(AB103="","",AB103*R103)) -> 5000
B104: Playground (quando fora da área construída) | AG104: =IF(R104="","",IF(AB104="","",AB104*R104))
B105: Urbanização | AG105: =IF(R105="","",IF(AB105="","",AB105*R105))
B106: Recreação (piscina, campos de esportes) | AG106: =IF(R106="","",IF(AB106="","",AB106*R106))
B107: Ajardinamento | R107: 1 | W107: vb | AB107: 5000 | AG107: =IF(R107="","",IF(AB107="","",AB107*R107)) -> 5000
B108: Instalação e regulamentação do condomínio | R108: 1 | W108: vb | AB108: 10000 | AG108: =IF(R108="","",IF(AB108="","",AB108*R108)) -> 10000
B109: Outros | AG109: =IF(R109="","",IF(AB109="","",AB109*R109))
AB111: TOTAL | AG111: =SUM(AG95:AK109) -> 515283.9
H113: CUSTO TOTAL DA OBRA | AC113: TAXA DE ADMINISTRAÇÃO DE OBRA
H114: CUB Ajustado | M114: {=IFERROR(_xlfn.IFS(H114="Selecione","",H114="Custo Histórico",R72,H114="CUB Ajustado",(AG111/AB92)+R70),"")} -> 2065.1301 | R114: {=IFERROR(_xlfn.IFS(H114="Selecione","",H114="Custo Histórico",M114*J49,H114="CUB Ajustado",M114*AB92),"")} -> 4433311.8 | AC114: Índice | AH114: Mensal | AM114: Valor Total
AC115: 0.1 | AH115: =IFERROR(AM115/F38,"") -> 18472.133 | AM115: =IFERROR(R114*AC115,"") -> 443331.18
B117: CUSTOS E DESPESAS EXTRAS
B119: VALOR TERRENO | L119: VALOR TERRENO GERAL | U119: CUSTO OBRA | AE119: VGV NOMINAL | AN119: VGV GERAL
B120: =Z56 -> 800000 | L120: =Z62 -> 804000 | U120: =R114 -> 4433311.8 | AE120: =AH44 -> 9556594.4 | AN120: =AH46 -> 9556594.4
B122: DESCRIÇÃO | L122: BASE | U122: ÍNDICE | Z122: VALOR
B123: Projetos | L123: Custo Obra | U123: 0.01398503 | Z123: =IF(U123="","",_xlfn.XLOOKUP(L123,$B$119:$AW$119,$B$120:$AW$120)*U123) -> 62000 | AI123: GESTÃO DO PROJETO
B124: Despesas Legais | L124: Custo Obra | U124: 0.00180452 | Z124: =IF(U124="","",_xlfn.XLOOKUP(L124,$B$119:$AW$119,$B$120:$AW$120)*U124) -> 8000 | AI124: Base | AN124: Valor Terreno
B125: Aprovação CEF | L125: Custo Obra | Z125: =IF(U125="","",_xlfn.XLOOKUP(L125,$B$119:$AW$119,$B$120:$AW$120)*U125) | AI125: Índice | AN125: 0
B126: Demolições | L126: Custo Obra | Z126: =IF(U126="","",_xlfn.XLOOKUP(L126,$B$119:$AW$119,$B$120:$AW$120)*U126) | AI126: Folha Pagamento | AN126: =IFERROR(AN127/F38,"") -> 0
B127: Canteiro | L127: Custo Obra | Z127: =IF(U127="","",_xlfn.XLOOKUP(L127,$B$119:$AW$119,$B$120:$AW$120)*U127) | AI127: Valor Total | AN127: =IF(AN125="","",_xlfn.XLOOKUP(AN124,$B$119:$AW$119,$B$120:$AW$120)*AN125) -> 0
B128: Máquinas e Equipamentos | L128: Custo Obra | Z128: =IF(U128="","",_xlfn.XLOOKUP(L128,$B$119:$AW$119,$B$120:$AW$120)*U128)
B129: Regularização | L129: VGV Geral | U129: 0.03 | Z129: =IF(U129="","",_xlfn.XLOOKUP(L129,$B$119:$AW$119,$B$120:$AW$120)*U129) -> 286697.83 | AI129: IPTU
B130: Infraestrutura não Incidente | L130: Custo Obra | Z130: =IF(U130="","",_xlfn.XLOOKUP(L130,$B$119:$AW$119,$B$120:$AW$120)*U130) | AI130: Base | AN130: =N60 -> 200000
...

Sheet SIMULAÇÃO 02
B6: ANÁLISE DE VIABILIDADE FINANCEIRA PRELIMINAR | AR6: SIMULAÇÃO 02
B8: INFORMAÇÕES DO EMPREENDIMENTO
B10: OBRA | H10: ='SIMULAÇÃO 01'!H10 -> Ed. Curupira | EW Esteves Construções | T10: CIDADE / UF | Z10: ='SIMULAÇÃO 01'!Z10 -> Ribeirão Preto / SP | AI10: PREÇO M² | AO10: ='SIMULAÇÃO 01'!AO10 -> 6682.9332
B12: MAPA DAS UNIDADES
B14: TIPOLOGIA | K14: ÁREA PRIVATIVA | T14: QUANT. | Z14: PREÇO M² | AI14: VALOR / UNIDADE | AR14: PERMUTA
Z15: =IF(B15<>"",$AO$10,"") | AI15: =IF(K15=""," ",IF(Z15=""," ",Z15*K15))
Z16: =IF(B16<>"",$AO$10,"") | AI16: =IF(K16=""," ",IF(Z16=""," ",Z16*K16))
Z17: =IF(B17<>"",$AO$10,"") | AI17: =IF(K17=""," ",IF(Z17=""," ",Z17*K17))
Z18: =IF(B18<>"",$AO$10,"") | AI18: =IF(K18=""," ",IF(Z18=""," ",Z18*K18))
Z19: =IF(B19<>"",$AO$10,"") | AI19: =IF(K19=""," ",IF(Z19=""," ",Z19*K19))
Z20: =IF(B20<>"",$AO$10,"") | AI20: =IF(K20=""," ",IF(Z20=""," ",Z20*K20))
Z21: =IF(B21<>"",$AO$10,"") | AI21: =IF(K21=""," ",IF(Z21=""," ",Z21*K21))
Z22: =IF(B22<>"",$AO$10,"") | AI22: =IF(K22=""," ",IF(Z22=""," ",Z22*K22))
Z23: =IF(B23<>"",$AO$10,"") | AI23: =IF(K23=""," ",IF(Z23=""," ",Z23*K23))
Z24: =IF(B24<>"",$AO$10,"") | AI24: =IF(K24=""," ",IF(Z24=""," ",Z24*K24))
Z25: =IF(B25<>"",$AO$10,"") | AI25: =IF(K25=""," ",IF(Z25=""," ",Z25*K25))
Z26: =IF(B26<>"",$AO$10,"") | AI26: =IF(K26=""," ",IF(Z26=""," ",Z26*K26))
B28: LINHA DO TEMPO | AI28: ESCALA: | AR28: MENSAL
B30: INÍCIO | J30: =IF(F30="","",F30) | K30: =IFERROR(DATE(YEAR(J30),IF($AR$28="MENSAL",MONTH(J30)+1,MONTH(J30)+2),1),"") | L30: =IFERROR(DATE(YEAR(K30),IF($AR$28="MENSAL",MONTH(K30)+1,MONTH(K30)+2),1),"") | M30: =IFERROR(DATE(YEAR(L30),IF($AR$28="MENSAL",MONTH(L30)+1,MONTH(L30)+2),1),"") | N30: =IFERROR(DATE(YEAR(M30),IF($AR$28="MENSAL",MONTH(M30)+1,MONTH(M30)+2),1),"") | O30: =IFERROR(DATE(YEAR(N30),IF($AR$28="MENSAL",MONTH(N30)+1,MONTH(N30)+2),1),"") | P30: =IFERROR(DATE(YEAR(O30),IF($AR$28="MENSAL",MONTH(O30)+1,MONTH(O30)+2),1),"") | Q30: =IFERROR(DATE(YEAR(P30),IF($AR$28="MENSAL",MONTH(P30)+1,MONTH(P30)+2),1),"") | R30: =IFERROR(DATE(YEAR(Q30),IF($AR$28="MENSAL",MONTH(Q30)+1,MONTH(Q30)+2),1),"") | ... AW30: =IFERROR(DATE(YEAR(AV30),IF($AR$28="MENSAL",MONTH(AV30)+1,MONTH(AV30)+2),1),"")
B32: START VENDAS
B34: ETAPA | F34: MESES | AY34: I | AZ34: T
B35: Viabilidade | J35: =IF(AND(J$30>=$AY35,J$30<=$AZ35),1,0) -> 0 | K35: =IF(AND(K$30>=$AY35,K$30<=$AZ35),1,0) -> 0 | L35: =IF(AND(L$30>=$AY35,L$30<=$AZ35),1,0) -> 0 | M35: =IF(AND(M$30>=$AY35,M$30<=$AZ35),1,0) -> 0 | N35: =IF(AND(N$30>=$AY35,N$30<=$AZ35),1,0) -> 0 | O35: =IF(AND(O$30>=$AY35,O$30<=$AZ35),1,0) -> 0 | P35: =IF(AND(P$30>=$AY35,P$30<=$AZ35),1,0) -> 0 | Q35: =IF(AND(Q$30>=$AY35,Q$30<=$AZ35),1,0) -> 0 | ... AW35: =IF(AND(AW$30>=$AY35,AW$30<=$AZ35),1,0) -> 0 | AY35: =F30 -> 0 | AZ35: =DATE(YEAR(AY35),MONTH(AY35)+F35,1) -> 1
B36: Aprovação | J36: =IF(AND(J$30>=$AY36,J$30<=$AZ36),1,0) -> 0 | K36: =IF(AND(K$30>=$AY36,K$30<=$AZ36),1,0) -> 0 | L36: =IF(AND(L$30>=$AY36,L$30<=$AZ36),1,0) -> 0 | M36: =IF(AND(M$30>=$AY36,M$30<=$AZ36),1,0) -> 0 | N36: =IF(AND(N$30>=$AY36,N$30<=$AZ36),1,0) -> 0 | O36: =IF(AND(O$30>=$AY36,O$30<=$AZ36),1,0) -> 0 | P36: =IF(AND(P$30>=$AY36,P$30<=$AZ36),1,0) -> 0 | Q36: =IF(AND(Q$30>=$AY36,Q$30<=$AZ36),1,0) -> 0 | ... AW36: =IF(AND(AW$30>=$AY36,AW$30<=$AZ36),1,0) -> 0 | AY36: =AZ35 -> 1 | AZ36: =DATE(YEAR(AY36),MONTH(AY36)+F36,1) -> 1
B37: Vendas | J37: =IF(AND(J$30>=$AY37,J$30<=$AZ37),1,0) -> 0 | K37: =IF(AND(K$30>=$AY37,K$30<=$AZ37),1,0) -> 0 | L37: =IF(AND(L$30>=$AY37,L$30<=$AZ37),1,0) -> 0 | M37: =IF(AND(M$30>=$AY37,M$30<=$AZ37),1,0) -> 0 | N37: =IF(AND(N$30>=$AY37,N$30<=$AZ37),1,0) -> 0 | O37: =IF(AND(O$30>=$AY37,O$30<=$AZ37),1,0) -> 0 | P37: =IF(AND(P$30>=$AY37,P$30<=$AZ37),1,0) -> 0 | Q37: =IF(AND(Q$30>=$AY37,Q$30<=$AZ37),1,0) -> 0 | ... AW37: =IF(AND(AW$30>=$AY37,AW$30<=$AZ37),1,0) -> 0 | AY37: =AZ36 -> 1 | AZ37: =DATE(YEAR(AY37),MONTH(AY37)+F37,1) -> 1
B38: Obras | J38: =IF(AND(J$30>=$AY38,J$30<=$AZ38),1,0) -> 0 | K38: =IF(AND(K$30>=$AY38,K$30<=$AZ38),1,0) -> 0 | L38: =IF(AND(L$30>=$AY38,L$30<=$AZ38),1,0) -> 0 | M38: =IF(AND(M$30>=$AY38,M$30<=$AZ38),1,0) -> 0 | N38: =IF(AND(N$30>=$AY38,N$30<=$AZ38),1,0) -> 0 | O38: =IF(AND(O$30>=$AY38,O$30<=$AZ38),1,0) -> 0 | P38: =IF(AND(P$30>=$AY38,P$30<=$AZ38),1,0) -> 0 | Q38: =IF(AND(Q$30>=$AY38,Q$30<=$AZ38),1,0) -> 0 | ... AW38: =IF(AND(AW$30>=$AY38,AW$30<=$AZ38),1,0) -> 0 | AY38: =DATE(YEAR(AY37),MONTH(AY37)+F32,1) -> 1 | AZ38: =DATE(YEAR(AY38),MONTH(AY38)+F38,1) -> 1
B39: Legalização | J39: =IF(AND(J$30>=$AY39,J$30<=$AZ39),1,0) -> 0 | K39: =IF(AND(K$30>=$AY39,K$30<=$AZ39),1,0) -> 0 | L39: =IF(AND(L$30>=$AY39,L$30<=$AZ39),1,0) -> 0 | M39: =IF(AND(M$30>=$AY39,M$30<=$AZ39),1,0) -> 0 | N39: =IF(AND(N$30>=$AY39,N$30<=$AZ39),1,0) -> 0 | O39: =IF(AND(O$30>=$AY39,O$30<=$AZ39),1,0) -> 0 | P39: =IF(AND(P$30>=$AY39,P$30<=$AZ39),1,0) -> 0 | Q39: =IF(AND(Q$30>=$AY39,Q$30<=$AZ39),1,0) -> 0 | ... AW39: =IF(AND(AW$30>=$AY39,AW$30<=$AZ39),1,0) -> 0 | AY39: =AZ38 -> 1 | AZ39: =DATE(YEAR(AY39),MONTH(AY39)+F39,1) -> 1
B41: QUADRO RESUMO
J43: UNIDADES | R43: ÁREA PRIVATIVA | AH43: VALOR GERAL DE VENDA (VGV)
B44: Vendável | J44: =J46-J45 -> 0 | R44: =R46-R45 -> 0 | AB44: =IFERROR(R44/R46,"") | AH44: =AH46-AH45 -> 0 | AR44: =IFERROR(AH44/AH46,"")
B45: Permuta | J45: =SUM(AR15:AW26) -> 0 | R45: =SUMPRODUCT(K15:K26,AR15:AR26) -> 0 | AB45: =IFERROR(R45/R46,"") | AH45: =SUMPRODUCT(K15:K26,AR15:AR26,Z15:Z26) -> 0 | AR45: =IFERROR(AH45/AH46,"")
B46: TOTAL | J46: =SUM(T15:Y26) -> 0 | R46: =SUMPRODUCT(K15:K26,T15:T26) -> 0 | AH46: =SUMPRODUCT(K15:K26,T15:T26,Z15:Z26) -> 0
B48: ÁREA DO LOTE | Z48: EFICIÊNCIA | AH48: C.A.
B49: ÁREA TOTAL CONSTRUÍDA | Z49: =IFERROR(R46/J49,"") | AH49: =IFERROR(J50/J48,"")
B50: ÁREA COMPUTÁVEL
B52: LOTE
B54: PERMUTA | J54: =AH45 -> 0
B55: PAGAMENTO | Z55: CUSTO BASE
B56: PERMUTA FINANCEIRA | Z56: =SUM(J54:Q57) -> 0
B57: PERMUTA FÍSICA FORA | Z57: =IFERROR(Z56/J48,"")
B58: COMISSÃO | N58: =(SUM(J54:K57))*J58 -> 0
B60: VALOR VENAL | N60: =J60*J48 -> 0
B61: ITBI / REGISTRO | N61: =N60*J61 -> 0 | Z61: CUSTO TOTAL
Z62: =SUM(J54:Q57,N58,N61,J63:Q64) -> 0
B63: OUTORGA ONEROSA | Z63: =IFERROR(Z62/J48,"")
B64: CEPAC
B66: CUSTO OBRA
B68: REFERÊNCIA PROJETO PADRÃO (NBR 12.721) | R68: Selecione
B69: MÊS DE REFERÊNCIA
B70: CUSTO / M²
B72: CUSTO HISTÓRICO / M² (ÁREA TOTAL CONSTRUÍDA)
B74: LOCAL | M74: ÁREA | R74: COEF. EQUIV. | W74: COEFICIENTE | AB74: ÁREA EQUIV. | AG74: OBSERVAÇÕES
B75: Garagem (Subsolo 1) | R75: 0,50 a 0,75 | AB75: =IF(M75="","",IF(W75="","",W75*M75))
B76: Garagem (Subsolo 2) - Térreo | R76: 0,50 a 0,75 | AB76: =IF(M76="","",IF(W76="","",W76*M76))
B77: Garagem (Subsolo 3) | R77: 0,50 a 0,75 | AB77: =IF(M77="","",IF(W77="","",W77*M77))
B78: Garagem (Subsolo 4) | R78: 0,50 a 0,75 | AB78: =IF(M78="","",IF(W78="","",W78*M78))
B79: Garagem (Subsolo 5) | R79: 0,50 a 0,75 | AB79: =IF(M79="","",IF(W79="","",W79*M79))
B80: Salas sem acabamento | R80: 0,75 a 0,90 | AB80: =IF(M80="","",IF(W80="","",W80*M80))
B81: Lojas sem acabamento | R81: 0,40 a 0,60 | AB81: =IF(M81="","",IF(W81="","",W81*M81))
B82: Varandas | R82: 0,75 a 1,00 | AB82: =IF(M82="","",IF(W82="","",W82*M82))
B83: Terraço ou áreas descobertas sobre lajes | R83: 0,30 a 0,60 | AB83: =IF(M83="","",IF(W83="","",W83*M83))
B84: Estacionamento sobre terreno | R84: 0,05 a 0,10 | AB84: =IF(M84="","",IF(W84="","",W84*M84))
B85: Barrilhete | R85: 0,50 a 0,75 | AB85: =IF(M85="","",IF(W85="","",W85*M85))
B86: Caixa d´água | R86: 0,50 a 0,75 | AB86: =IF(M86="","",IF(W86="","",W86*M86))
... B88: Piscinas, quintais, etc | R88: 0,50 a 0,75 | AB88: =IF(M88="","",IF(W88="","",W88*M88))
R90: ÁREA EQUIVALENTE | AB90: =SUM(AB75:AF88) -> 0
R91: ÁREA RESIDUAL | AB91: =J49-(SUM(M75:Q88)-M84-M88) -> 0
R92: ÁREA EQUIVALENTE TOTAL | AB92: =AB90+AB91 -> 0
B94: ITENS NÃO CONSIDERADOS NO CUB | R94: QUANTIDADE | W94: UNIDADE | AB94: VALOR UNITÁRIO | AG94: VALOR TOTAL | AL94: OBSERVAÇÕES
B95: Fundações especiais (CUB = fundações diretas até 2,50m) | AG95: =IF(R95="","",IF(AB95="","",AB95*R95))
B96: Elevadores | AG96: =IF(R96="","",IF(AB96="","",AB96*R96))
B97: Fogões | AG97: =IF(R97="","",IF(AB97="","",AB97*R97))
B98: Aquecedores | AG98: =IF(R98="","",IF(AB98="","",AB98*R98))
B99: Bombas de recalque | AG99: =IF(R99="","",IF(AB99="","",AB99*R99))
B100: Incineração | AG100: =IF(R100="","",IF(AB100="","",AB100*R100))
B101: Ar condicionado | AG101: =IF(R101="","",IF(AB101="","",AB101*R101))
B102: Calefação | AG102: =IF(R102="","",IF(AB102="","",AB102*R102))
B103: Ventilação e exaustão | AG103: =IF(R103="","",IF(AB103="","",AB103*R103))
B104: Playground (quando fora da área construída) | AG104: =IF(R104="","",IF(AB104="","",AB104*R104))
B105: Urbanização | AG105: =IF(R105="","",IF(AB105="","",AB105*R105))
B106: Recreação (piscina, campos de esportes) | AG106: =IF(R106="","",IF(AB106="","",AB106*R106))
... B109: Outros | AG109: =IF(R109="","",IF(AB109="","",AB109*R109))
AB111: TOTAL | AG111: =SUM(AG95:AK109) -> 0
H113: CUSTO TOTAL DA OBRA | AC113: TAXA DE ADMINISTRAÇÃO DE OBRA
H114: Selecione | M114: {=IFERROR(_xlfn.IFS(H114="Selecione","",H114="Custo Histórico",R72,H114="CUB Ajustado",(AG111/AB92)+R70),"")} | R114: {=IFERROR(_xlfn.IFS(H114="Selecione","",H114="Custo Histórico",M114*J49,H114="CUB Ajustado",M114*AB92),"")} | AC114: Índice | AH114: Mensal | AM114: Valor Total
AH115: =IFERROR(AM115/F38,"") | AM115: =IFERROR(R114*AC115,"")
B117: CUSTOS E DESPESAS EXTRAS
B119: VALOR TERRENO | L119: VALOR TERRENO GERAL | U119: CUSTO OBRA | AE119: VGV NOMINAL | AN119: VGV GERAL
B120: =Z56 -> 0 | L120: =Z62 -> 0 | U120: =R114 | AE120: =AH44 -> 0 | AN120: =AH46 -> 0
B122: DESCRIÇÃO | L122: BASE | U122: ÍNDICE | Z122: VALOR
B123: Projetos | L123: Custo Obra | Z123: =IF(U123="","",_xlfn.XLOOKUP(L123,$B$119:$AW$119,$B$120:$AW$120)*U123) | AI123: GESTÃO DO PROJETO
B124: Despesas Legais | L124: Custo Obra | Z124: =IF(U124="","",_xlfn.XLOOKUP(L124,$B$119:$AW$119,$B$120:$AW$120)*U124) | AI124: Base | AN124: Valor Terreno
B125: Aprovação CEF | L125: Custo Obra | Z125: =IF(U125="","",_xlfn.XLOOKUP(L125,$B$119:$AW$119,$B$120:$AW$120)*U125) | AI125: Índice
B126: Demolições | L126: Custo Obra | Z126: =IF(U126="","",_xlfn.XLOOKUP(L126,$B$119:$AW$119,$B$120:$AW$120)*U126) | AI126: Folha Pagamento | AN126: =IFERROR(AN127/F38,"")
B127: Canteiro | L127: Custo Obra | Z127: =IF(U127="","",_xlfn.XLOOKUP(L127,$B$119:$AW$119,$B$120:$AW$120)*U127) | AI127: Valor Total | AN127: =IF(AN125="","",_xlfn.XLOOKUP(AN124,$B$119:$AW$119,$B$120:$AW$120)*AN125)
B128: Máquinas e Equipamentos | L128: Custo Obra | Z128: =IF(U128="","",_xlfn.XLOOKUP(L128,$B$119:$AW$119,$B$120:$AW$120)*U128)
B129: Regularização | L129: VGV Geral | Z129: =IF(U129="","",_xlfn.XLOOKUP(L129,$B$119:$AW$119,$B$120:$AW$120)*U129) | AI129: IPTU
B130: Infraestrutura não Incidente | L130: Custo Obra | Z130: =IF(U130="","",_xlfn.XLOOKUP(L130,$B$119:$AW$119,$B$120:$AW$120)*U130) | AI130: Base | AN130: =N60 -> 0
B131: Assistência Técnica | L131: Custo Obra | Z131: =IF(U131="","",_xlfn.XLOOKUP(L131,$B$119:$AW$119,$B$120:$AW$120)*U131) | AI131: Índice
B132: Custo Contábil | L132: Custo Obra | Z132: =IF(U132="","",_xlfn.XLOOKUP(L132,$B$119:$AW$119,$B$120:$AW$120)*U132) | AI132: Valor Mensal | AN132: =(POWER(1+AN131,1/12)-1)*AN130 -> 0
B133: Outros (reembolso entrada 4 aptos) | L133: Custo Obra | Z133: =IF(U133="","",_xlfn.XLOOKUP(L133,$B$119:$AW$119,$B$120:$AW$120)*U133) | AI133: Valor Total | AN133: =AN132*(F32+F38+F39) -> 0
...

Sheet SIMULAÇÃO 03
B6: ANÁLISE DE VIABILIDADE FINANCEIRA PRELIMINAR | AR6: SIMULAÇÃO 03
B8: INFORMAÇÕES DO EMPREENDIMENTO
B10: OBRA | H10: ='SIMULAÇÃO 01'!H10 -> Ed. Curupira | EW Esteves Construções | T10: CIDADE / UF | Z10: ='SIMULAÇÃO 01'!Z10 -> Ribeirão Preto / SP | AI10: PREÇO M² | AO10: ='SIMULAÇÃO 01'!AO10 -> 6682.9332
B12: MAPA DAS UNIDADES
B14: TIPOLOGIA | K14: ÁREA PRIVATIVA | T14: QUANT. | Z14: PREÇO M² | AI14: VALOR / UNIDADE | AR14: PERMUTA
Z15: =IF(B15<>"",$AO$10,"") | AI15: =IF(K15=""," ",IF(Z15=""," ",Z15*K15))
Z16: =IF(B16<>"",$AO$10,"") | AI16: =IF(K16=""," ",IF(Z16=""," ",Z16*K16))
Z17: =IF(B17<>"",$AO$10,"") | AI17: =IF(K17=""," ",IF(Z17=""," ",Z17*K17))
Z18: =IF(B18<>"",$AO$10,"") | AI18: =IF(K18=""," ",IF(Z18=""," ",Z18*K18))
Z19: =IF(B19<>"",$AO$10,"") | AI19: =IF(K19=""," ",IF(Z19=""," ",Z19*K19))
Z20: =IF(B20<>"",$AO$10,"") | AI20: =IF(K20=""," ",IF(Z20=""," ",Z20*K20))
Z21: =IF(B21<>"",$AO$10,"") | AI21: =IF(K21=""," ",IF(Z21=""," ",Z21*K21))
Z22: =IF(B22<>"",$AO$10,"") | AI22: =IF(K22=""," ",IF(Z22=""," ",Z22*K22))
Z23: =IF(B23<>"",$AO$10,"") | AI23: =IF(K23=""," ",IF(Z23=""," ",Z23*K23))
Z24: =IF(B24<>"",$AO$10,"") | AI24: =IF(K24=""," ",IF(Z24=""," ",Z24*K24))
Z25: =IF(B25<>"",$AO$10,"") | AI25: =IF(K25=""," ",IF(Z25=""," ",Z25*K25))
Z26: =IF(B26<>"",$AO$10,"") | AI26: =IF(K26=""," ",IF(Z26=""," ",Z26*K26))
B28: LINHA DO TEMPO | AI28: ESCALA: | AR28: MENSAL
B30: INÍCIO | J30: =IF(F30="","",F30) | K30: =IFERROR(DATE(YEAR(J30),IF($AR$28="MENSAL",MONTH(J30)+1,MONTH(J30)+2),1),"") | L30: =IFERROR(DATE(YEAR(K30),IF($AR$28="MENSAL",MONTH(K30)+1,MONTH(K30)+2),1),"") | M30: =IFERROR(DATE(YEAR(L30),IF($AR$28="MENSAL",MONTH(L30)+1,MONTH(L30)+2),1),"") | N30: =IFERROR(DATE(YEAR(M30),IF($AR$28="MENSAL",MONTH(M30)+1,MONTH(M30)+2),1),"") | O30: =IFERROR(DATE(YEAR(N30),IF($AR$28="MENSAL",MONTH(N30)+1,MONTH(N30)+2),1),"") | P30: =IFERROR(DATE(YEAR(O30),IF($AR$28="MENSAL",MONTH(O30)+1,MONTH(O30)+2),1),"") | Q30: =IFERROR(DATE(YEAR(P30),IF($AR$28="MENSAL",MONTH(P30)+1,MONTH(P30)+2),1),"") | R30: =IFERROR(DATE(YEAR(Q30),IF($AR$28="MENSAL",MONTH(Q30)+1,MONTH(Q30)+2),1),"") | ... AW30: =IFERROR(DATE(YEAR(AV30),IF($AR$28="MENSAL",MONTH(AV30)+1,MONTH(AV30)+2),1),"")
B32: START VENDAS
B34: ETAPA | F34: MESES | AY34: I | AZ34: T
B35: Viabilidade | J35: =IF(AND(J$30>=$AY35,J$30<=$AZ35),1,0) -> 0 | K35: =IF(AND(K$30>=$AY35,K$30<=$AZ35),1,0) -> 0 | L35: =IF(AND(L$30>=$AY35,L$30<=$AZ35),1,0) -> 0 | M35: =IF(AND(M$30>=$AY35,M$30<=$AZ35),1,0) -> 0 | N35: =IF(AND(N$30>=$AY35,N$30<=$AZ35),1,0) -> 0 | O35: =IF(AND(O$30>=$AY35,O$30<=$AZ35),1,0) -> 0 | P35: =IF(AND(P$30>=$AY35,P$30<=$AZ35),1,0) -> 0 | Q35: =IF(AND(Q$30>=$AY35,Q$30<=$AZ35),1,0) -> 0 | ... AW35: =IF(AND(AW$30>=$AY35,AW$30<=$AZ35),1,0) -> 0 | AY35: =F30 -> 0 | AZ35: =DATE(YEAR(AY35),MONTH(AY35)+F35,1) -> 1
B36: Aprovação | J36: =IF(AND(J$30>=$AY36,J$30<=$AZ36),1,0) -> 0 | K36: =IF(AND(K$30>=$AY36,K$30<=$AZ36),1,0) -> 0 | L36: =IF(AND(L$30>=$AY36,L$30<=$AZ36),1,0) -> 0 | M36: =IF(AND(M$30>=$AY36,M$30<=$AZ36),1,0) -> 0 | N36: =IF(AND(N$30>=$AY36,N$30<=$AZ36),1,0) -> 0 | O36: =IF(AND(O$30>=$AY36,O$30<=$AZ36),1,0) -> 0 | P36: =IF(AND(P$30>=$AY36,P$30<=$AZ36),1,0) -> 0 | Q36: =IF(AND(Q$30>=$AY36,Q$30<=$AZ36),1,0) -> 0 | ... AW36: =IF(AND(AW$30>=$AY36,AW$30<=$AZ36),1,0) -> 0 | AY36: =AZ35 -> 1 | AZ36: =DATE(YEAR(AY36),MONTH(AY36)+F36,1) -> 1
B37: Vendas | J37: =IF(AND(J$30>=$AY37,J$30<=$AZ37),1,0) -> 0 | K37: =IF(AND(K$30>=$AY37,K$30<=$AZ37),1,0) -> 0 | L37: =IF(AND(L$30>=$AY37,L$30<=$AZ37),1,0) -> 0 | M37: =IF(AND(M$30>=$AY37,M$30<=$AZ37),1,0) -> 0 | N37: =IF(AND(N$30>=$AY37,N$30<=$AZ37),1,0) -> 0 | O37: =IF(AND(O$30>=$AY37,O$30<=$AZ37),1,0) -> 0 | P37: =IF(AND(P$30>=$AY37,P$30<=$AZ37),1,0) -> 0 | Q37: =IF(AND(Q$30>=$AY37,Q$30<=$AZ37),1,0) -> 0 | ... AW37: =IF(AND(AW$30>=$AY37,AW$30<=$AZ37),1,0) -> 0 | AY37: =AZ36 -> 1 | AZ37: =DATE(YEAR(AY37),MONTH(AY37)+F37,1) -> 1
B38: Obras | J38: =IF(AND(J$30>=$AY38,J$30<=$AZ38),1,0) -> 0 | K38: =IF(AND(K$30>=$AY38,K$30<=$AZ38),1,0) -> 0 | L38: =IF(AND(L$30>=$AY38,L$30<=$AZ38),1,0) -> 0 | M38: =IF(AND(M$30>=$AY38,M$30<=$AZ38),1,0) -> 0 | N38: =IF(AND(N$30>=$AY38,N$30<=$AZ38),1,0) -> 0 | O38: =IF(AND(O$30>=$AY38,O$30<=$AZ38),1,0) -> 0 | P38: =IF(AND(P$30>=$AY38,P$30<=$AZ38),1,0) -> 0 | Q38: =IF(AND(Q$30>=$AY38,Q$30<=$AZ38),1,0) -> 0 | ... AW38: =IF(AND(AW$30>=$AY38,AW$30<=$AZ38),1,0) -> 0 | AY38: =DATE(YEAR(AY37),MONTH(AY37)+F32,1) -> 1 | AZ38: =DATE(YEAR(AY38),MONTH(AY38)+F38,1) -> 1
B39: Legalização | J39: =IF(AND(J$30>=$AY39,J$30<=$AZ39),1,0) -> 0 | K39: =IF(AND(K$30>=$AY39,K$30<=$AZ39),1,0) -> 0 | L39: =IF(AND(L$30>=$AY39,L$30<=$AZ39),1,0) -> 0 | M39: =IF(AND(M$30>=$AY39,M$30<=$AZ39),1,0) -> 0 | N39: =IF(AND(N$30>=$AY39,N$30<=$AZ39),1,0) -> 0 | O39: =IF(AND(O$30>=$AY39,O$30<=$AZ39),1,0) -> 0 | P39: =IF(AND(P$30>=$AY39,P$30<=$AZ39),1,0) -> 0 | Q39: =IF(AND(Q$30>=$AY39,Q$30<=$AZ39),1,0) -> 0 | ... AW39: =IF(AND(AW$30>=$AY39,AW$30<=$AZ39),1,0) -> 0 | AY39: =AZ38 -> 1 | AZ39: =DATE(YEAR(AY39),MONTH(AY39)+F39,1) -> 1
B41: QUADRO RESUMO
J43: UNIDADES | R43: ÁREA PRIVATIVA | AH43: VALOR GERAL DE VENDA (VGV)
B44: Vendável | J44: =J46-J45 -> 0 | R44: =R46-R45 -> 0 | AB44: =IFERROR(R44/R46,"") | AH44: =AH46-AH45 -> 0 | AR44: =IFERROR(AH44/AH46,"")
B45: Permuta | J45: =SUM(AR15:AW26) -> 0 | R45: =SUMPRODUCT(K15:K26,AR15:AR26) -> 0 | AB45: =IFERROR(R45/R46,"") | AH45: =SUMPRODUCT(K15:K26,AR15:AR26,Z15:Z26) -> 0 | AR45: =IFERROR(AH45/AH46,"")
B46: TOTAL | J46: =SUM(T15:Y26) -> 0 | R46: =SUMPRODUCT(K15:K26,T15:T26) -> 0 | AH46: =SUMPRODUCT(K15:K26,T15:T26,Z15:Z26) -> 0
B48: ÁREA DO LOTE | Z48: EFICIÊNCIA | AH48: C.A.
B49: ÁREA TOTAL CONSTRUÍDA | Z49: =IFERROR(R46/J49,"") | AH49: =IFERROR(J50/J48,"")
B50: ÁREA COMPUTÁVEL
B52: LOTE
B54: PERMUTA | J54: =AH45 -> 0
B55: PAGAMENTO | Z55: CUSTO BASE
B56: PERMUTA FINANCEIRA | Z56: =SUM(J54:Q57) -> 0
B57: PERMUTA FÍSICA FORA | Z57: =IFERROR(Z56/J48,"")
B58: COMISSÃO | N58: =(SUM(J54:K57))*J58 -> 0
B60: VALOR VENAL | N60: =J60*J48 -> 0
B61: ITBI / REGISTRO | N61: =N60*J61 -> 0 | Z61: CUSTO TOTAL
Z62: =SUM(J54:Q57,N58,N61,J63:Q64) -> 0
B63: OUTORGA ONEROSA | Z63: =IFERROR(Z62/J48,"")
B64: CEPAC
B66: CUSTO OBRA
B68: REFERÊNCIA PROJETO PADRÃO (NBR 12.721) | R68: Selecione
B69: MÊS DE REFERÊNCIA
B70: CUSTO / M²
B72: CUSTO HISTÓRICO / M² (ÁREA TOTAL CONSTRUÍDA)
B74: LOCAL | M74: ÁREA | R74: COEF. EQUIV. | W74: COEFICIENTE | AB74: ÁREA EQUIV. | AG74: OBSERVAÇÕES
B75: Garagem (Subsolo 1) | R75: 0,50 a 0,75 | AB75: =IF(M75="","",IF(W75="","",W75*M75))
B76: Garagem (Subsolo 2) - Térreo | R76: 0,50 a 0,75 | AB76: =IF(M76="","",IF(W76="","",W76*M76))
B77: Garagem (Subsolo 3) | R77: 0,50 a 0,75 | AB77: =IF(M77="","",IF(W77="","",W77*M77))
B78: Garagem (Subsolo 4) | R78: 0,50 a 0,75 | AB78: =IF(M78="","",IF(W78="","",W78*M78))
B79: Garagem (Subsolo 5) | R79: 0,50 a 0,75 | AB79: =IF(M79="","",IF(W79="","",W79*M79))
B80: Salas sem acabamento | R80: 0,75 a 0,90 | AB80: =IF(M80="","",IF(W80="","",W80*M80))
B81: Lojas sem acabamento | R81: 0,40 a 0,60 | AB81: =IF(M81="","",IF(W81="","",W81*M81))
B82: Varandas | R82: 0,75 a 1,00 | AB82: =IF(M82="","",IF(W82="","",W82*M82))
B83: Terraço ou áreas descobertas sobre lajes | R83: 0,30 a 0,60 | AB83: =IF(M83="","",IF(W83="","",W83*M83))
B84: Estacionamento sobre terreno | R84: 0,05 a 0,10 | AB84: =IF(M84="","",IF(W84="","",W84*M84))
B85: Barrilhete | R85: 0,50 a 0,75 | AB85: =IF(M85="","",IF(W85="","",W85*M85))
B86: Caixa d´água | R86: 0,50 a 0,75 | AB86: =IF(M86="","",IF(W86="","",W86*M86))
... B88: Piscinas, quintais, etc | R88: 0,50 a 0,75 | AB88: =IF(M88="","",IF(W88="","",W88*M88))
R90: ÁREA EQUIVALENTE | AB90: =SUM(AB75:AF88) -> 0
R91: ÁREA RESIDUAL | AB91: =J49-(SUM(M75:Q88)-M84-M88) -> 0
R92: ÁREA EQUIVALENTE TOTAL | AB92: =AB90+AB91 -> 0
B94: ITENS NÃO CONSIDERADOS NO CUB | R94: QUANTIDADE | W94: UNIDADE | AB94: VALOR UNITÁRIO | AG94: VALOR TOTAL | AL94: OBSERVAÇÕES
B95: Fundações especiais (CUB = fundações diretas até 2,50m) | AG95: =IF(R95="","",IF(AB95="","",AB95*R95))
B96: Elevadores | AG96: =IF(R96="","",IF(AB96="","",AB96*R96))
B97: Fogões | AG97: =IF(R97="","",IF(AB97="","",AB97*R97))
B98: Aquecedores | AG98: =IF(R98="","",IF(AB98="","",AB98*R98))
B99: Bombas de recalque | AG99: =IF(R99="","",IF(AB99="","",AB99*R99))
B100: Incineração | AG100: =IF(R100="","",IF(AB100="","",AB100*R100))
B101: Ar condicionado | AG101: =IF(R101="","",IF(AB101="","",AB101*R101))
B102: Calefação | AG102: =IF(R102="","",IF(AB102="","",AB102*R102))
B103: Ventilação e exaustão | AG103: =IF(R103="","",IF(AB103="","",AB103*R103))
B104: Playground (quando fora da área construída) | AG104: =IF(R104="","",IF(AB104="","",AB104*R104))
B105: Urbanização | AG105: =IF(R105="","",IF(AB105="","",AB105*R105))
B106: Recreação (piscina, campos de esportes) | AG106: =IF(R106="","",IF(AB106="","",AB106*R106))
... B109: Outros | AG109: =IF(R109="","",IF(AB109="","",AB109*R109))
AB111: TOTAL | AG111: =SUM(AG95:AK109) -> 0
H113: CUSTO TOTAL DA OBRA | AC113: TAXA DE ADMINISTRAÇÃO DE OBRA
H114: Selecione | M114: {=IFERROR(_xlfn.IFS(H114="Selecione","",H114="Custo Histórico",R72,H114="CUB Ajustado",(AG111/AB92)+R70),"")} | R114: {=IFERROR(_xlfn.IFS(H114="Selecione","",H114="Custo Histórico",M114*J49,H114="CUB Ajustado",M114*AB92),"")} | AC114: Índice | AH114: Mensal | AM114: Valor Total
AH115: =IFERROR(AM115/F38,"") | AM115: =IFERROR(R114*AC115,"")
B117: CUSTOS E DESPESAS EXTRAS
B119: VALOR TERRENO | L119: VALOR TERRENO GERAL | U119: CUSTO OBRA | AE119: VGV NOMINAL | AN119: VGV GERAL
B120: =Z56 -> 0 | L120: =Z62 -> 0 | U120: =R114 | AE120: =AH44 -> 0 | AN120: =AH46 -> 0
B122: DESCRIÇÃO | L122: BASE | U122: ÍNDICE | Z122: VALOR
B123: Projetos | L123: Custo Obra | Z123: =IF(U123="","",_xlfn.XLOOKUP(L123,$B$119:$AW$119,$B$120:$AW$120)*U123) | AI123: GESTÃO DO PROJETO
B124: Despesas Legais | L124: Custo Obra | Z124: =IF(U124="","",_xlfn.XLOOKUP(L124,$B$119:$AW$119,$B$120:$AW$120)*U124) | AI124: Base | AN124: Valor Terreno
B125: Aprovação CEF | L125: Custo Obra | Z125: =IF(U125="","",_xlfn.XLOOKUP(L125,$B$119:$AW$119,$B$120:$AW$120)*U125) | AI125: Índice
B126: Demolições | L126: Custo Obra | Z126: =IF(U126="","",_xlfn.XLOOKUP(L126,$B$119:$AW$119,$B$120:$AW$120)*U126) | AI126: Folha Pagamento | AN126: =IFERROR(AN127/F38,"")
B127: Canteiro | L127: Custo Obra | Z127: =IF(U127="","",_xlfn.XLOOKUP(L127,$B$119:$AW$119,$B$120:$AW$120)*U127) | AI127: Valor Total | AN127: =IF(AN125="","",_xlfn.XLOOKUP(AN124,$B$119:$AW$119,$B$120:$AW$120)*AN125)
B128: Máquinas e Equipamentos | L128: Custo Obra | Z128: =IF(U128="","",_xlfn.XLOOKUP(L128,$B$119:$AW$119,$B$120:$AW$120)*U128)
B129: Regularização | L129: VGV Geral | Z129: =IF(U129="","",_xlfn.XLOOKUP(L129,$B$119:$AW$119,$B$120:$AW$120)*U129) | AI129: IPTU
B130: Infraestrutura não Incidente | L130: Custo Obra | Z130: =IF(U130="","",_xlfn.XLOOKUP(L130,$B$119:$AW$119,$B$120:$AW$120)*U130) | AI130: Base | AN130: =N60 -> 0
B131: Assistência Técnica | L131: Custo Obra | Z131: =IF(U131="","",_xlfn.XLOOKUP(L131,$B$119:$AW$119,$B$120:$AW$120)*U131) | AI131: Índice
B132: Custo Contábil | L132: Custo Obra | Z132: =IF(U132="","",_xlfn.XLOOKUP(L132,$B$119:$AW$119,$B$120:$AW$120)*U132) | AI132: Valor Mensal | AN132: =(POWER(1+AN131,1/12)-1)*AN130 -> 0
B133: Outros (reembolso entrada 4 aptos) | L133: Custo Obra | Z133: =IF(U133="","",_xlfn.XLOOKUP(L133,$B$119:$AW$119,$B$120:$AW$120)*U133) | AI133: Valor Total | AN133: =AN132*(F32+F38+F39) -> 0
...

Sheet SIMULAÇÃO 04
B6: ANÁLISE DE VIABILIDADE FINANCEIRA PRELIMINAR | AR6: SIMULAÇÃO 04
B8: INFORMAÇÕES DO EMPREENDIMENTO
B10: OBRA | H10: ='SIMULAÇÃO 01'!H10 -> Ed. Curupira | EW Esteves Construções | T10: CIDADE / UF | Z10: ='SIMULAÇÃO 01'!Z10 -> Ribeirão Preto / SP | AI10: PREÇO M² | AO10: ='SIMULAÇÃO 01'!AO10 -> 6682.9332
B12: MAPA DAS UNIDADES
B14: TIPOLOGIA | K14: ÁREA PRIVATIVA | T14: QUANT. | Z14: PREÇO M² | AI14: VALOR / UNIDADE | AR14: PERMUTA
Z15: =IF(B15<>"",$AO$10,"") | AI15: =IF(K15=""," ",IF(Z15=""," ",Z15*K15))
Z16: =IF(B16<>"",$AO$10,"") | AI16: =IF(K16=""," ",IF(Z16=""," ",Z16*K16))
Z17: =IF(B17<>"",$AO$10,"") | AI17: =IF(K17=""," ",IF(Z17=""," ",Z17*K17))
Z18: =IF(B18<>"",$AO$10,"") | AI18: =IF(K18=""," ",IF(Z18=""," ",Z18*K18))
Z19: =IF(B19<>"",$AO$10,"") | AI19: =IF(K19=""," ",IF(Z19=""," ",Z19*K19))
Z20: =IF(B20<>"",$AO$10,"") | AI20: =IF(K20=""," ",IF(Z20=""," ",Z20*K20))
Z21: =IF(B21<>"",$AO$10,"") | AI21: =IF(K21=""," ",IF(Z21=""," ",Z21*K21))
Z22: =IF(B22<>"",$AO$10,"") | AI22: =IF(K22=""," ",IF(Z22=""," ",Z22*K22))
Z23: =IF(B23<>"",$AO$10,"") | AI23: =IF(K23=""," ",IF(Z23=""," ",Z23*K23))
Z24: =IF(B24<>"",$AO$10,"") | AI24: =IF(K24=""," ",IF(Z24=""," ",Z24*K24))
Z25: =IF(B25<>"",$AO$10,"") | AI25: =IF(K25=""," ",IF(Z25=""," ",Z25*K25))
Z26: =IF(B26<>"",$AO$10,"") | AI26: =IF(K26=""," ",IF(Z26=""," ",Z26*K26))
B28: LINHA DO TEMPO | AI28: ESCALA: | AR28: MENSAL
B30: INÍCIO | J30: =IF(F30="","",F30) | K30: =IFERROR(DATE(YEAR(J30),IF($AR$28="MENSAL",MONTH(J30)+1,MONTH(J30)+2),1),"") | L30: =IFERROR(DATE(YEAR(K30),IF($AR$28="MENSAL",MONTH(K30)+1,MONTH(K30)+2),1),"") | M30: =IFERROR(DATE(YEAR(L30),IF($AR$28="MENSAL",MONTH(L30)+1,MONTH(L30)+2),1),"") | N30: =IFERROR(DATE(YEAR(M30),IF($AR$28="MENSAL",MONTH(M30)+1,MONTH(M30)+2),1),"") | O30: =IFERROR(DATE(YEAR(N30),IF($AR$28="MENSAL",MONTH(N30)+1,MONTH(N30)+2),1),"") | P30: =IFERROR(DATE(YEAR(O30),IF($AR$28="MENSAL",MONTH(O30)+1,MONTH(O30)+2),1),"") | Q30: =IFERROR(DATE(YEAR(P30),IF($AR$28="MENSAL",MONTH(P30)+1,MONTH(P30)+2),1),"") | R30: =IFERROR(DATE(YEAR(Q30),IF($AR$28="MENSAL",MONTH(Q30)+1,MONTH(Q30)+2),1),"") | ... AW30: =IFERROR(DATE(YEAR(AV30),IF($AR$28="MENSAL",MONTH(AV30)+1,MONTH(AV30)+2),1),"")
B32: START VENDAS
B34: ETAPA | F34: MESES | AY34: I | AZ34: T
B35: Viabilidade | J35: =IF(AND(J$30>=$AY35,J$30<=$AZ35),1,0) -> 0 | K35: =IF(AND(K$30>=$AY35,K$30<=$AZ35),1,0) -> 0 | L35: =IF(AND(L$30>=$AY35,L$30<=$AZ35),1,0) -> 0 | M35: =IF(AND(M$30>=$AY35,M$30<=$AZ35),1,0) -> 0 | N35: =IF(AND(N$30>=$AY35,N$30<=$AZ35),1,0) -> 0 | O35: =IF(AND(O$30>=$AY35,O$30<=$AZ35),1,0) -> 0 | P35: =IF(AND(P$30>=$AY35,P$30<=$AZ35),1,0) -> 0 | Q35: =IF(AND(Q$30>=$AY35,Q$30<=$AZ35),1,0) -> 0 | ... AW35: =IF(AND(AW$30>=$AY35,AW$30<=$AZ35),1,0) -> 0 | AY35: =F30 -> 0 | AZ35: =DATE(YEAR(AY35),MONTH(AY35)+F35,1) -> 1
B36: Aprovação | J36: =IF(AND(J$30>=$AY36,J$30<=$AZ36),1,0) -> 0 | K36: =IF(AND(K$30>=$AY36,K$30<=$AZ36),1,0) -> 0 | L36: =IF(AND(L$30>=$AY36,L$30<=$AZ36),1,0) -> 0 | M36: =IF(AND(M$30>=$AY36,M$30<=$AZ36),1,0) -> 0 | N36: =IF(AND(N$30>=$AY36,N$30<=$AZ36),1,0) -> 0 | O36: =IF(AND(O$30>=$AY36,O$30<=$AZ36),1,0) -> 0 | P36: =IF(AND(P$30>=$AY36,P$30<=$AZ36),1,0) -> 0 | Q36: =IF(AND(Q$30>=$AY36,Q$30<=$AZ36),1,0) -> 0 | ... AW36: =IF(AND(AW$30>=$AY36,AW$30<=$AZ36),1,0) -> 0 | AY36: =AZ35 -> 1 | AZ36: =DATE(YEAR(AY36),MONTH(AY36)+F36,1) -> 1
B37: Vendas | J37: =IF(AND(J$30>=$AY37,J$30<=$AZ37),1,0) -> 0 | K37: =IF(AND(K$30>=$AY37,K$30<=$AZ37),1,0) -> 0 | L37: =IF(AND(L$30>=$AY37,L$30<=$AZ37),1,0) -> 0 | M37: =IF(AND(M$30>=$AY37,M$30<=$AZ37),1,0) -> 0 | N37: =IF(AND(N$30>=$AY37,N$30<=$AZ37),1,0) -> 0 | O37: =IF(AND(O$30>=$AY37,O$30<=$AZ37),1,0) -> 0 | P37: =IF(AND(P$30>=$AY37,P$30<=$AZ37),1,0) -> 0 | Q37: =IF(AND(Q$30>=$AY37,Q$30<=$AZ37),1,0) -> 0 | ... AW37: =IF(AND(AW$30>=$AY37,AW$30<=$AZ37),1,0) -> 0 | AY37: =AZ36 -> 1 | AZ37: =DATE(YEAR(AY37),MONTH(AY37)+F37,1) -> 1
B38: Obras | J38: =IF(AND(J$30>=$AY38,J$30<=$AZ38),1,0) -> 0 | K38: =IF(AND(K$30>=$AY38,K$30<=$AZ38),1,0) -> 0 | L38: =IF(AND(L$30>=$AY38,L$30<=$AZ38),1,0) -> 0 | M38: =IF(AND(M$30>=$AY38,M$30<=$AZ38),1,0) -> 0 | N38: =IF(AND(N$30>=$AY38,N$30<=$AZ38),1,0) -> 0 | O38: =IF(AND(O$30>=$AY38,O$30<=$AZ38),1,0) -> 0 | P38: =IF(AND(P$30>=$AY38,P$30<=$AZ38),1,0) -> 0 | Q38: =IF(AND(Q$30>=$AY38,Q$30<=$AZ38),1,0) -> 0 | ... AW38: =IF(AND(AW$30>=$AY38,AW$30<=$AZ38),1,0) -> 0 | AY38: =DATE(YEAR(AY37),MONTH(AY37)+F32,1) -> 1 | AZ38: =DATE(YEAR(AY38),MONTH(AY38)+F38,1) -> 1
B39: Legalização | J39: =IF(AND(J$30>=$AY39,J$30<=$AZ39),1,0) -> 0 | K39: =IF(AND(K$30>=$AY39,K$30<=$AZ39),1,0) -> 0 | L39: =IF(AND(L$30>=$AY39,L$30<=$AZ39),1,0) -> 0 | M39: =IF(AND(M$30>=$AY39,M$30<=$AZ39),1,0) -> 0 | N39: =IF(AND(N$30>=$AY39,N$30<=$AZ39),1,0) -> 0 | O39: =IF(AND(O$30>=$AY39,O$30<=$AZ39),1,0) -> 0 | P39: =IF(AND(P$30>=$AY39,P$30<=$AZ39),1,0) -> 0 | Q39: =IF(AND(Q$30>=$AY39,Q$30<=$AZ39),1,0) -> 0 | ... AW39: =IF(AND(AW$30>=$AY39,AW$30<=$AZ39),1,0) -> 0 | AY39: =AZ38 -> 1 | AZ39: =DATE(YEAR(AY39),MONTH(AY39)+F39,1) -> 1
B41: QUADRO RESUMO
J43: UNIDADES | R43: ÁREA PRIVATIVA | AH43: VALOR GERAL DE VENDA (VGV)
B44: Vendável | J44: =J46-J45 -> 0 | R44: =R46-R45 -> 0 | AB44: =IFERROR(R44/R46,"") | AH44: =AH46-AH45 -> 0 | AR44: =IFERROR(AH44/AH46,"")
B45: Permuta | J45: =SUM(AR15:AW26) -> 0 | R45: =SUMPRODUCT(K15:K26,AR15:AR26) -> 0 | AB45: =IFERROR(R45/R46,"") | AH45: =SUMPRODUCT(K15:K26,AR15:AR26,Z15:Z26) -> 0 | AR45: =IFERROR(AH45/AH46,"")
B46: TOTAL | J46: =SUM(T15:Y26) -> 0 | R46: =SUMPRODUCT(K15:K26,T15:T26) -> 0 | AH46: =SUMPRODUCT(K15:K26,T15:T26,Z15:Z26) -> 0
B48: ÁREA DO LOTE | Z48: EFICIÊNCIA | AH48: C.A.
B49: ÁREA TOTAL CONSTRUÍDA | Z49: =IFERROR(R46/J49,"") | AH49: =IFERROR(J50/J48,"")
B50: ÁREA COMPUTÁVEL
B52: LOTE
B54: PERMUTA | J54: =AH45 -> 0
B55: PAGAMENTO | Z55: CUSTO BASE
B56: PERMUTA FINANCEIRA | Z56: =SUM(J54:Q57) -> 0
B57: PERMUTA FÍSICA FORA | Z57: =IFERROR(Z56/J48,"")
B58: COMISSÃO | N58: =(SUM(J54:K57))*J58 -> 0
B60: VALOR VENAL | N60: =J60*J48 -> 0
B61: ITBI / REGISTRO | N61: =N60*J61 -> 0 | Z61: CUSTO TOTAL
Z62: =SUM(J54:Q57,N58,N61,J63:Q64) -> 0
B63: OUTORGA ONEROSA | Z63: =IFERROR(Z62/J48,"")
B64: CEPAC
B66: CUSTO OBRA
B68: REFERÊNCIA PROJETO PADRÃO (NBR 12.721) | R68: Selecione
B69: MÊS DE REFERÊNCIA
B70: CUSTO / M²
B72: CUSTO HISTÓRICO / M² (ÁREA TOTAL CONSTRUÍDA)
B74: LOCAL | M74: ÁREA | R74: COEF. EQUIV. | W74: COEFICIENTE | AB74: ÁREA EQUIV. | AG74: OBSERVAÇÕES
B75: Garagem (Subsolo 1) | R75: 0,50 a 0,75 | AB75: =IF(M75="","",IF(W75="","",W75*M75))
B76: Garagem (Subsolo 2) - Térreo | R76: 0,50 a 0,75 | AB76: =IF(M76="","",IF(W76="","",W76*M76))
B77: Garagem (Subsolo 3) | R77: 0,50 a 0,75 | AB77: =IF(M77="","",IF(W77="","",W77*M77))
B78: Garagem (Subsolo 4) | R78: 0,50 a 0,75 | AB78: =IF(M78="","",IF(W78="","",W78*M78))
B79: Garagem (Subsolo 5) | R79: 0,50 a 0,75 | AB79: =IF(M79="","",IF(W79="","",W79*M79))
B80: Salas sem acabamento | R80: 0,75 a 0,90 | AB80: =IF(M80="","",IF(W80="","",W80*M80))
B81: Lojas sem acabamento | R81: 0,40 a 0,60 | AB81: =IF(M81="","",IF(W81="","",W81*M81))
B82: Varandas | R82: 0,75 a 1,00 | AB82: =IF(M82="","",IF(W82="","",W82*M82))
B83: Terraço ou áreas descobertas sobre lajes | R83: 0,30 a 0,60 | AB83: =IF(M83="","",IF(W83="","",W83*M83))
B84: Estacionamento sobre terreno | R84: 0,05 a 0,10 | AB84: =IF(M84="","",IF(W84="","",W84*M84))
B85: Barrilhete | R85: 0,50 a 0,75 | AB85: =IF(M85="","",IF(W85="","",W85*M85))
B86: Caixa d´água | R86: 0,50 a 0,75 | AB86: =IF(M86="","",IF(W86="","",W86*M86))
... B88: Piscinas, quintais, etc | R88: 0,50 a 0,75 | AB88: =IF(M88="","",IF(W88="","",W88*M88))
R90: ÁREA EQUIVALENTE | AB90: =SUM(AB75:AF88) -> 0
R91: ÁREA RESIDUAL | AB91: =J49-(SUM(M75:Q88)-M84-M88) -> 0
R92: ÁREA EQUIVALENTE TOTAL | AB92: =AB90+AB91 -> 0
B94: ITENS NÃO CONSIDERADOS NO CUB | R94: QUANTIDADE | W94: UNIDADE | AB94: VALOR UNITÁRIO | AG94: VALOR TOTAL | AL94: OBSERVAÇÕES
B95: Fundações especiais (CUB = fundações diretas até 2,50m) | AG95: =IF(R95="","",IF(AB95="","",AB95*R95))
B96: Elevadores | AG96: =IF(R96="","",IF(AB96="","",AB96*R96))
B97: Fogões | AG97: =IF(R97="","",IF(AB97="","",AB97*R97))
B98: Aquecedores | AG98: =IF(R98="","",IF(AB98="","",AB98*R98))
B99: Bombas de recalque | AG99: =IF(R99="","",IF(AB99="","",AB99*R99))
B100: Incineração | AG100: =IF(R100="","",IF(AB100="","",AB100*R100))
B101: Ar condicionado | AG101: =IF(R101="","",IF(AB101="","",AB101*R101))
B102: Calefação | AG102: =IF(R102="","",IF(AB102="","",AB102*R102))
B103: Ventilação e exaustão | AG103: =IF(R103="","",IF(AB103="","",AB103*R103))
B104: Playground (quando fora da área construída) | AG104: =IF(R104="","",IF(AB104="","",AB104*R104))
B105: Urbanização | AG105: =IF(R105="","",IF(AB105="","",AB105*R105))
B106: Recreação (piscina, campos de esportes) | AG106: =IF(R106="","",IF(AB106="","",AB106*R106))
... B109: Outros | AG109: =IF(R109="","",IF(AB109="","",AB109*R109))
AB111: TOTAL | AG111: =SUM(AG95:AK109) -> 0
H113: CUSTO TOTAL DA OBRA | AC113: TAXA DE ADMINISTRAÇÃO DE OBRA
H114: Selecione | M114: {=IFERROR(_xlfn.IFS(H114="Selecione","",H114="Custo Histórico",R72,H114="CUB Ajustado",(AG111/AB92)+R70),"")} | R114: {=IFERROR(_xlfn.IFS(H114="Selecione","",H114="Custo Histórico",M114*J49,H114="CUB Ajustado",M114*AB92),"")} | AC114: Índice | AH114: Mensal | AM114: Valor Total
AH115: =IFERROR(AM115/F38,"") | AM115: =IFERROR(R114*AC115,"")
B117: CUSTOS E DESPESAS EXTRAS
B119: VALOR TERRENO | L119: VALOR TERRENO GERAL | U119: CUSTO OBRA | AE119: VGV NOMINAL | AN119: VGV GERAL
B120: =Z56 -> 0 | L120: =Z62 -> 0 | U120: =R114 | AE120: =AH44 -> 0 | AN120: =AH46 -> 0
B122: DESCRIÇÃO | L122: BASE | U122: ÍNDICE | Z122: VALOR
B123: Projetos | L123: Custo Obra | Z123: =IF(U123="","",_xlfn.XLOOKUP(L123,$B$119:$AW$119,$B$120:$AW$120)*U123) | AI123: GESTÃO DO PROJETO
B124: Despesas Legais | L124: Custo Obra | Z124: =IF(U124="","",_xlfn.XLOOKUP(L124,$B$119:$AW$119,$B$120:$AW$120)*U124) | AI124: Base | AN124: Valor Terreno
B125: Aprovação CEF | L125: Custo Obra | Z125: =IF(U125="","",_xlfn.XLOOKUP(L125,$B$119:$AW$119,$B$120:$AW$120)*U125) | AI125: Índice
B126: Demolições | L126: Custo Obra | Z126: =IF(U126="","",_xlfn.XLOOKUP(L126,$B$119:$AW$119,$B$120:$AW$120)*U126) | AI126: Folha Pagamento | AN126: =IFERROR(AN127/F38,"")
B127: Canteiro | L127: Custo Obra | Z127: =IF(U127="","",_xlfn.XLOOKUP(L127,$B$119:$AW$119,$B$120:$AW$120)*U127) | AI127: Valor Total | AN127: =IF(AN125="","",_xlfn.XLOOKUP(AN124,$B$119:$AW$119,$B$120:$AW$120)*AN125)
B128: Máquinas e Equipamentos | L128: Custo Obra | Z128: =IF(U128="","",_xlfn.XLOOKUP(L128,$B$119:$AW$119,$B$120:$AW$120)*U128)
B129: Regularização | L129: VGV Geral | Z129: =IF(U129="","",_xlfn.XLOOKUP(L129,$B$119:$AW$119,$B$120:$AW$120)*U129) | AI129: IPTU
B130: Infraestrutura não Incidente | L130: Custo Obra | Z130: =IF(U130="","",_xlfn.XLOOKUP(L130,$B$119:$AW$119,$B$120:$AW$120)*U130) | AI130: Base | AN130: =N60 -> 0
B131: Assistência Técnica | L131: Custo Obra | Z131: =IF(U131="","",_xlfn.XLOOKUP(L131,$B$119:$AW$119,$B$120:$AW$120)*U131) | AI131: Índice
B132: Custo Contábil | L132: Custo Obra | Z132: =IF(U132="","",_xlfn.XLOOKUP(L132,$B$119:$AW$119,$B$120:$AW$120)*U132) | AI132: Valor Mensal | AN132: =(POWER(1+AN131,1/12)-1)*AN130 -> 0
B133: Outros (reembolso entrada 4 aptos) | L133: Custo Obra | Z133: =IF(U133="","",_xlfn.XLOOKUP(L133,$B$119:$AW$119,$B$120:$AW$120)*U133) | AI133: Valor Total | AN133: =AN132*(F32+F38+F39) -> 0
...

Sheet COMPARATIVO
B6: ANÁLISE COMPARATIVA DE SIMULAÇÕES | AJ6: VALOR: | AQ6: GLOBAL
V8: SIMULAÇÃO 01 | AC8: SIMULAÇÃO 02 | AJ8: SIMULAÇÃO 03 | AQ8: SIMULAÇÃO 04
D10: RECEITA DE VENDAS | V10: {=_xlfn.IFS($AQ$6="GLOBAL",'SIMULAÇÃO 01'!AH181,$AQ$6="POR UNIDADE",'SIMULAÇÃO 01'!AN181)} -> 9556594.4 | AC10: {=_xlfn.IFS($AQ$6="GLOBAL",'SIMULAÇÃO 02'!AO181,$AQ$6="POR UNIDADE",'SIMULAÇÃO 02'!AU181)} -> 0 | AJ10: {=_xlfn.IFS($AQ$6="GLOBAL",'SIMULAÇÃO 03'!AV181,$AQ$6="POR UNIDADE",'SIMULAÇÃO 03'!BB181)} -> 0 | AQ10: {=_xlfn.IFS($AQ$6="GLOBAL",'SIMULAÇÃO 04'!BC181,$AQ$6="POR UNIDADE",'SIMULAÇÃO 04'!BI181)} -> 0
B11: Terreno | D11: Negociação do Lote | V11: {=_xlfn.IFS($AQ$6="GLOBAL",'SIMULAÇÃO 01'!AH182,$AQ$6="POR UNIDADE",'SIMULAÇÃO 01'!AN182)} -> -800000 | AC11: {=_xlfn.IFS($AQ$6="GLOBAL",'SIMULAÇÃO 02'!AO182,$AQ$6="POR UNIDADE",'SIMULAÇÃO 02'!AU182)} -> 0 | AJ11: {=_xlfn.IFS($AQ$6="GLOBAL",'SIMULAÇÃO 03'!AV182,$AQ$6="POR UNIDADE",'SIMULAÇÃO 03'!BB182)} -> 0 | AQ11: {=_xlfn.IFS($AQ$6="GLOBAL",'SIMULAÇÃO 04'!BC182,$AQ$6="POR UNIDADE",'SIMULAÇÃO 04'!BI182)} -> 0
D12: Comissão, ITBI e Registro | V12: {=_xlfn.IFS($AQ$6="GLOBAL",'SIMULAÇÃO 01'!AH183,$AQ$6="POR UNIDADE",'SIMULAÇÃO 01'!AN183)} -> -4000 | AC12: {=_xlfn.IFS($AQ$6="GLOBAL",'SIMULAÇÃO 02'!AO183,$AQ$6="POR UNIDADE",'SIMULAÇÃO 02'!AU183)} -> 0 | AJ12: {=_xlfn.IFS($AQ$6="GLOBAL",'SIMULAÇÃO 03'!AV183,$AQ$6="POR UNIDADE",'SIMULAÇÃO 03'!BB183)} -> 0 | AQ12: {=_xlfn.IFS($AQ$6="GLOBAL",'SIMULAÇÃO 04'!BC183,$AQ$6="POR UNIDADE",'SIMULAÇÃO 04'!BI183)} -> 0
D13: Outorga Onerosa | V13: {=_xlfn.IFS($AQ$6="GLOBAL",'SIMULAÇÃO 01'!AH184,$AQ$6="POR UNIDADE",'SIMULAÇÃO 01'!AN184)} -> 0 | AC13: {=_xlfn.IFS($AQ$6="GLOBAL",'SIMULAÇÃO 02'!AO184,$AQ$6="POR UNIDADE",'SIMULAÇÃO 02'!AU184)} -> 0 | AJ13: {=_xlfn.IFS($AQ$6="GLOBAL",'SIMULAÇÃO 03'!AV184,$AQ$6="POR UNIDADE",'SIMULAÇÃO 03'!BB184)} -> 0 | AQ13: {=_xlfn.IFS($AQ$6="GLOBAL",'SIMULAÇÃO 04'!BC184,$AQ$6="POR UNIDADE",'SIMULAÇÃO 04'!BI184)} -> 0
D14: CEPAC | V14: {=_xlfn.IFS($AQ$6="GLOBAL",'SIMULAÇÃO 01'!AH185,$AQ$6="POR UNIDADE",'SIMULAÇÃO 01'!AN185)} -> 0 | AC14: {=_xlfn.IFS($AQ$6="GLOBAL",'SIMULAÇÃO 02'!AO185,$AQ$6="POR UNIDADE",'SIMULAÇÃO 02'!AU185)} -> 0 | AJ14: {=_xlfn.IFS($AQ$6="GLOBAL",'SIMULAÇÃO 03'!AV185,$AQ$6="POR UNIDADE",'SIMULAÇÃO 03'!BB185)} -> 0 | AQ14: {=_xlfn.IFS($AQ$6="GLOBAL",'SIMULAÇÃO 04'!BC185,$AQ$6="POR UNIDADE",'SIMULAÇÃO 04'!BI185)} -> 0
B15: Obra | D15: Custo Obra | V15: {=_xlfn.IFS($AQ$6="GLOBAL",'SIMULAÇÃO 01'!AH186,$AQ$6="POR UNIDADE",'SIMULAÇÃO 01'!AN186)} -> -4433311.8 | AC15: {=_xlfn.IFS($AQ$6="GLOBAL",'SIMULAÇÃO 02'!AO186,$AQ$6="POR UNIDADE",'SIMULAÇÃO 02'!AU186)} -> 0 | AJ15: {=_xlfn.IFS($AQ$6="GLOBAL",'SIMULAÇÃO 03'!AV186,$AQ$6="POR UNIDADE",'SIMULAÇÃO 03'!BB186)} -> 0 | AQ15: {=_xlfn.IFS($AQ$6="GLOBAL",'SIMULAÇÃO 04'!BC186,$AQ$6="POR UNIDADE",'SIMULAÇÃO 04'!BI186)} -> 0
D16: Taxa de Administração de Obra | V16: {=_xlfn.IFS($AQ$6="GLOBAL",'SIMULAÇÃO 01'!AH187,$AQ$6="POR UNIDADE",'SIMULAÇÃO 01'!AN187)} -> -443331.18 | AC16: {=_xlfn.IFS($AQ$6="GLOBAL",'SIMULAÇÃO 02'!AO187,$AQ$6="POR UNIDADE",'SIMULAÇÃO 02'!AU187)} -> 0 | AJ16: {=_xlfn.IFS($AQ$6="GLOBAL",'SIMULAÇÃO 03'!AV187,$AQ$6="POR UNIDADE",'SIMULAÇÃO 03'!BB187)} -> 0 | AQ16: {=_xlfn.IFS($AQ$6="GLOBAL",'SIMULAÇÃO 04'!BC187,$AQ$6="POR UNIDADE",'SIMULAÇÃO 04'!BI187)} -> 0
B17: Taxas, Custos e Despesas Extras | D17: Projetos | V17: {=_xlfn.IFS($AQ$6="GLOBAL",'SIMULAÇÃO 01'!AH188,$AQ$6="POR UNIDADE",'SIMULAÇÃO 01'!AN188)} -> -62000 | AC17: {=_xlfn.IFS($AQ$6="GLOBAL",'SIMULAÇÃO 02'!AO188,$AQ$6="POR UNIDADE",'SIMULAÇÃO 02'!AU188)} -> 0 | AJ17: {=_xlfn.IFS($AQ$6="GLOBAL",'SIMULAÇÃO 03'!AV188,$AQ$6="POR UNIDADE",'SIMULAÇÃO 03'!BB188)} -> 0 | AQ17: {=_xlfn.IFS($AQ$6="GLOBAL",'SIMULAÇÃO 04'!BC188,$AQ$6="POR UNIDADE",'SIMULAÇÃO 04'!BI188)} -> 0
D18: Despesas Legais | V18: {=_xlfn.IFS($AQ$6="GLOBAL",'SIMULAÇÃO 01'!AH189,$AQ$6="POR UNIDADE",'SIMULAÇÃO 01'!AN189)} -> -8000 | AC18: {=_xlfn.IFS($AQ$6="GLOBAL",'SIMULAÇÃO 02'!AO189,$AQ$6="POR UNIDADE",'SIMULAÇÃO 02'!AU189)} -> 0 | AJ18: {=_xlfn.IFS($AQ$6="GLOBAL",'SIMULAÇÃO 03'!AV189,$AQ$6="POR UNIDADE",'SIMULAÇÃO 03'!BB189)} -> 0 | AQ18: {=_xlfn.IFS($AQ$6="GLOBAL",'SIMULAÇÃO 04'!BC189,$AQ$6="POR UNIDADE",'SIMULAÇÃO 04'!BI189)} -> 0
D19: Aprovação CEF | V19: {=_xlfn.IFS($AQ$6="GLOBAL",'SIMULAÇÃO 01'!AH190,$AQ$6="POR UNIDADE",'SIMULAÇÃO 01'!AN190)} -> 0 | AC19: {=_xlfn.IFS($AQ$6="GLOBAL",'SIMULAÇÃO 02'!AO190,$AQ$6="POR UNIDADE",'SIMULAÇÃO 02'!AU190)} -> 0 | AJ19: {=_xlfn.IFS($AQ$6="GLOBAL",'SIMULAÇÃO 03'!AV190,$AQ$6="POR UNIDADE",'SIMULAÇÃO 03'!BB190)} -> 0 | AQ19: {=_xlfn.IFS($AQ$6="GLOBAL",'SIMULAÇÃO 04'!BC190,$AQ$6="POR UNIDADE",'SIMULAÇÃO 04'!BI190)} -> 0
D20: Demolições | V20: {=_xlfn.IFS($AQ$6="GLOBAL",'SIMULAÇÃO 01'!AH191,$AQ$6="POR UNIDADE",'SIMULAÇÃO 01'!AN191)} -> 0 | AC20: {=_xlfn.IFS($AQ$6="GLOBAL",'SIMULAÇÃO 02'!AO191,$AQ$6="POR UNIDADE",'SIMULAÇÃO 02'!AU191)} -> 0 | AJ20: {=_xlfn.IFS($AQ$6="GLOBAL",'SIMULAÇÃO 03'!AV191,$AQ$6="POR UNIDADE",'SIMULAÇÃO 03'!BB191)} -> 0 | AQ20: {=_xlfn.IFS($AQ$6="GLOBAL",'SIMULAÇÃO 04'!BC191,$AQ$6="POR UNIDADE",'SIMULAÇÃO 04'!BI191)} -> 0
D21: Canteiro | V21: {=_xlfn.IFS($AQ$6="GLOBAL",'SIMULAÇÃO 01'!AH192,$AQ$6="POR UNIDADE",'SIMULAÇÃO 01'!AN192)} -> 0 | AC21: {=_xlfn.IFS($AQ$6="GLOBAL",'SIMULAÇÃO 02'!AO192,$AQ$6="POR UNIDADE",'SIMULAÇÃO 02'!AU192)} -> 0 | AJ21: {=_xlfn.IFS($AQ$6="GLOBAL",'SIMULAÇÃO 03'!AV192,$AQ$6="POR UNIDADE",'SIMULAÇÃO 03'!BB192)} -> 0 | AQ21: {=_xlfn.IFS($AQ$6="GLOBAL",'SIMULAÇÃO 04'!BC192,$AQ$6="POR UNIDADE",'SIMULAÇÃO 04'!BI192)} -> 0
D22: Máquinas e Equipamentos | V22: {=_xlfn.IFS($AQ$6="GLOBAL",'SIMULAÇÃO 01'!AH193,$AQ$6="POR UNIDADE",'SIMULAÇÃO 01'!AN193)} -> 0 | AC22: {=_xlfn.IFS($AQ$6="GLOBAL",'SIMULAÇÃO 02'!AO193,$AQ$6="POR UNIDADE",'SIMULAÇÃO 02'!AU193)} -> 0 | AJ22: {=_xlfn.IFS($AQ$6="GLOBAL",'SIMULAÇÃO 03'!AV193,$AQ$6="POR UNIDADE",'SIMULAÇÃO 03'!BB193)} -> 0 | AQ22: {=_xlfn.IFS($AQ$6="GLOBAL",'SIMULAÇÃO 04'!BC193,$AQ$6="POR UNIDADE",'SIMULAÇÃO 04'!BI193)} -> 0
D23: Regularização | V23: {=_xlfn.IFS($AQ$6="GLOBAL",'SIMULAÇÃO 01'!AH194,$AQ$6="POR UNIDADE",'SIMULAÇÃO 01'!AN194)} -> -286697.83 | AC23: {=_xlfn.IFS($AQ$6="GLOBAL",'SIMULAÇÃO 02'!AO194,$AQ$6="POR UNIDADE",'SIMULAÇÃO 02'!AU194)} -> 0 | AJ23: {=_xlfn.IFS($AQ$6="GLOBAL",'SIMULAÇÃO 03'!AV194,$AQ$6="POR UNIDADE",'SIMULAÇÃO 03'!BB194)} -> 0 | AQ23: {=_xlfn.IFS($AQ$6="GLOBAL",'SIMULAÇÃO 04'!BC194,$AQ$6="POR UNIDADE",'SIMULAÇÃO 04'!BI194)} -> 0
D24: Infraestrutura não Incidente | V24: {=_xlfn.IFS($AQ$6="GLOBAL",'SIMULAÇÃO 01'!AH195,$AQ$6="POR UNIDADE",'SIMULAÇÃO 01'!AN195)} -> 0 | AC24: {=_xlfn.IFS($AQ$6="GLOBAL",'SIMULAÇÃO 02'!AO195,$AQ$6="POR UNIDADE",'SIMULAÇÃO 02'!AU195)} -> 0 | AJ24: {=_xlfn.IFS($AQ$6="GLOBAL",'SIMULAÇÃO 03'!AV195,$AQ$6="POR UNIDADE",'SIMULAÇÃO 03'!BB195)} -> 0 | AQ24: {=_xlfn.IFS($AQ$6="GLOBAL",'SIMULAÇÃO 04'!BC195,$AQ$6="POR UNIDADE",'SIMULAÇÃO 04'!BI195)} -> 0
D25: Assistência Técnica | V25: {=_xlfn.IFS($AQ$6="GLOBAL",'SIMULAÇÃO 01'!AH196,$AQ$6="POR UNIDADE",'SIMULAÇÃO 01'!AN196)} -> -44333.118 | AC25: {=_xlfn.IFS($AQ$6="GLOBAL",'SIMULAÇÃO 02'!AO196,$AQ$6="POR UNIDADE",'SIMULAÇÃO 02'!AU196)} -> 0 | AJ25: {=_xlfn.IFS($AQ$6="GLOBAL",'SIMULAÇÃO 03'!AV196,$AQ$6="POR UNIDADE",'SIMULAÇÃO 03'!BB196)} -> 0 | AQ25: {=_xlfn.IFS($AQ$6="GLOBAL",'SIMULAÇÃO 04'!BC196,$AQ$6="POR UNIDADE",'SIMULAÇÃO 04'!BI196)} -> 0
D26: Gestão do Projeto | V26: {=_xlfn.IFS($AQ$6="GLOBAL",'SIMULAÇÃO 01'!AH197,$AQ$6="POR UNIDADE",'SIMULAÇÃO 01'!AN197)} -> 0 | AC26: {=_xlfn.IFS($AQ$6="GLOBAL",'SIMULAÇÃO 02'!AO197,$AQ$6="POR UNIDADE",'SIMULAÇÃO 02'!AU197)} -> 0 | AJ26: {=_xlfn.IFS($AQ$6="GLOBAL",'SIMULAÇÃO 03'!AV197,$AQ$6="POR UNIDADE",'SIMULAÇÃO 03'!BB197)} -> 0 | AQ26: {=_xlfn.IFS($AQ$6="GLOBAL",'SIMULAÇÃO 04'!BC197,$AQ$6="POR UNIDADE",'SIMULAÇÃO 04'!BI197)} -> 0
D27: IPTU | V27: {=_xlfn.IFS($AQ$6="GLOBAL",'SIMULAÇÃO 01'!AH198,$AQ$6="POR UNIDADE",'SIMULAÇÃO 01'!AN198)} -> 0 | AC27: {=_xlfn.IFS($AQ$6="GLOBAL",'SIMULAÇÃO 02'!AO198,$AQ$6="POR UNIDADE",'SIMULAÇÃO 02'!AU198)} -> 0 | AJ27: {=_xlfn.IFS($AQ$6="GLOBAL",'SIMULAÇÃO 03'!AV198,$AQ$6="POR UNIDADE",'SIMULAÇÃO 03'!BB198)} -> 0 | AQ27: {=_xlfn.IFS($AQ$6="GLOBAL",'SIMULAÇÃO 04'!BC198,$AQ$6="POR UNIDADE",'SIMULAÇÃO 04'!BI198)} -> 0
D28: Outros | V28: {=_xlfn.IFS($AQ$6="GLOBAL",'SIMULAÇÃO 01'!AH199,$AQ$6="POR UNIDADE",'SIMULAÇÃO 01'!AN199)} -> -260000 | AC28: {=_xlfn.IFS($AQ$6="GLOBAL",'SIMULAÇÃO 02'!AO199,$AQ$6="POR UNIDADE",'SIMULAÇÃO 02'!AU199)} -> 0 | AJ28: {=_xlfn.IFS($AQ$6="GLOBAL",'SIMULAÇÃO 03'!AV199,$AQ$6="POR UNIDADE",'SIMULAÇÃO 03'!BB199)} -> 0 | AQ28: {=_xlfn.IFS($AQ$6="GLOBAL",'SIMULAÇÃO 04'!BC199,$AQ$6="POR UNIDADE",'SIMULAÇÃO 04'!BI199)} -> 0
D29: Incorporação | V29: {=_xlfn.IFS($AQ$6="GLOBAL",'SIMULAÇÃO 01'!AH200,$AQ$6="POR UNIDADE",'SIMULAÇÃO 01'!AN200)} -> -34796.45 | AC29: {=_xlfn.IFS($AQ$6="GLOBAL",'SIMULAÇÃO 02'!AO200,$AQ$6="POR UNIDADE",'SIMULAÇÃO 02'!AU200)} -> 0 | AJ29: {=_xlfn.IFS($AQ$6="GLOBAL",'SIMULAÇÃO 03'!AV200,$AQ$6="POR UNIDADE",'SIMULAÇÃO 03'!BB200)} -> 0 | AQ29: {=_xlfn.IFS($AQ$6="GLOBAL",'SIMULAÇÃO 04'!BC200,$AQ$6="POR UNIDADE",'SIMULAÇÃO 04'!BI200)} -> 0
B30: Comercialização | D30: Corretagem | V30: {=_xlfn.IFS($AQ$6="GLOBAL",'SIMULAÇÃO 01'!AH201,$AQ$6="POR UNIDADE",'SIMULAÇÃO 01'!AN201)} -> -477829.72 | AC30: {=_xlfn.IFS($AQ$6="GLOBAL",'SIMULAÇÃO 02'!AO201,$AQ$6="POR UNIDADE",'SIMULAÇÃO 02'!AU201)} -> 0 | AJ30: {=_xlfn.IFS($AQ$6="GLOBAL",'SIMULAÇÃO 03'!AV201,$AQ$6="POR UNIDADE",'SIMULAÇÃO 03'!BB201)} -> 0 | AQ30: {=_xlfn.IFS($AQ$6="GLOBAL",'SIMULAÇÃO 04'!BC201,$AQ$6="POR UNIDADE",'SIMULAÇÃO 04'!BI201)} -> 0
D31: Administração de Vendas | V31: {=_xlfn.IFS($AQ$6="GLOBAL",'SIMULAÇÃO 01'!AH202,$AQ$6="POR UNIDADE",'SIMULAÇÃO 01'!AN202)} -> -95565.944 | AC31: {=_xlfn.IFS($AQ$6="GLOBAL",'SIMULAÇÃO 02'!AO202,$AQ$6="POR UNIDADE",'SIMULAÇÃO 02'!AU202)} -> 0 | AJ31: {=_xlfn.IFS($AQ$6="GLOBAL",'SIMULAÇÃO 03'!AV202,$AQ$6="POR UNIDADE",'SIMULAÇÃO 03'!BB202)} -> 0 | AQ31: {=_xlfn.IFS($AQ$6="GLOBAL",'SIMULAÇÃO 04'!BC202,$AQ$6="POR UNIDADE",'SIMULAÇÃO 04'!BI202)} -> 0
D32: Marketing e Publicidade | V32: {=_xlfn.IFS($AQ$6="GLOBAL",'SIMULAÇÃO 01'!AH203,$AQ$6="POR UNIDADE",'SIMULAÇÃO 01'!AN203)} -> -47782.972 | AC32: {=_xlfn.IFS($AQ$6="GLOBAL",'SIMULAÇÃO 02'!AO203,$AQ$6="POR UNIDADE",'SIMULAÇÃO 02'!AU203)} -> 0 | AJ32: {=_xlfn.IFS($AQ$6="GLOBAL",'SIMULAÇÃO 03'!AV203,$AQ$6="POR UNIDADE",'SIMULAÇÃO 03'!BB203)} -> 0 | AQ32: {=_xlfn.IFS($AQ$6="GLOBAL",'SIMULAÇÃO 04'!BC203,$AQ$6="POR UNIDADE",'SIMULAÇÃO 04'!BI203)} -> 0
D33: Stand de Vendas | V33: {=_xlfn.IFS($AQ$6="GLOBAL",'SIMULAÇÃO 01'!AH204,$AQ$6="POR UNIDADE",'SIMULAÇÃO 01'!AN204)} -> 0 | AC33: {=_xlfn.IFS($AQ$6="GLOBAL",'SIMULAÇÃO 02'!AO204,$AQ$6="POR UNIDADE",'SIMULAÇÃO 02'!AU204)} -> 0 | AJ33: {=_xlfn.IFS($AQ$6="GLOBAL",'SIMULAÇÃO 03'!AV204,$AQ$6="POR UNIDADE",'SIMULAÇÃO 03'!BB204)} -> 0 | AQ33: {=_xlfn.IFS($AQ$6="GLOBAL",'SIMULAÇÃO 04'!BC204,$AQ$6="POR UNIDADE",'SIMULAÇÃO 04'!BI204)} -> 0
D34: Apartamento Decorado | V34: {=_xlfn.IFS($AQ$6="GLOBAL",'SIMULAÇÃO 01'!AH205,$AQ$6="POR UNIDADE",'SIMULAÇÃO 01'!AN205)} -> 0 | AC34: {=_xlfn.IFS($AQ$6="GLOBAL",'SIMULAÇÃO 02'!AO205,$AQ$6="POR UNIDADE",'SIMULAÇÃO 02'!AU205)} -> 0 | AJ34: {=_xlfn.IFS($AQ$6="GLOBAL",'SIMULAÇÃO 03'!AV205,$AQ$6="POR UNIDADE",'SIMULAÇÃO 03'!BB205)} -> 0 | AQ34: {=_xlfn.IFS($AQ$6="GLOBAL",'SIMULAÇÃO 04'!BC205,$AQ$6="POR UNIDADE",'SIMULAÇÃO 04'!BI205)} -> 0
D35: Recebimento em Imóveis | V35: {=_xlfn.IFS($AQ$6="GLOBAL",'SIMULAÇÃO 01'!AH206,$AQ$6="POR UNIDADE",'SIMULAÇÃO 01'!AN206)} -> 0 | AC35: {=_xlfn.IFS($AQ$6="GLOBAL",'SIMULAÇÃO 02'!AO206,$AQ$6="POR UNIDADE",'SIMULAÇÃO 02'!AU206)} -> 0 | AJ35: {=_xlfn.IFS($AQ$6="GLOBAL",'SIMULAÇÃO 03'!AV206,$AQ$6="POR UNIDADE",'SIMULAÇÃO 03'!BB206)} -> 0 | AQ35: {=_xlfn.IFS($AQ$6="GLOBAL",'SIMULAÇÃO 04'!BC206,$AQ$6="POR UNIDADE",'SIMULAÇÃO 04'!BI206)} -> 0
D36: Outros | V36: {=_xlfn.IFS($AQ$6="GLOBAL",'SIMULAÇÃO 01'!AH207,$AQ$6="POR UNIDADE",'SIMULAÇÃO 01'!AN207)} -> 0 | AC36: {=_xlfn.IFS($AQ$6="GLOBAL",'SIMULAÇÃO 02'!AO207,$AQ$6="POR UNIDADE",'SIMULAÇÃO 02'!AU207)} -> 0 | AJ36: {=_xlfn.IFS($AQ$6="GLOBAL",'SIMULAÇÃO 03'!AV207,$AQ$6="POR UNIDADE",'SIMULAÇÃO 03'!BB207)} -> 0 | AQ36: {=_xlfn.IFS($AQ$6="GLOBAL",'SIMULAÇÃO 04'!BC207,$AQ$6="POR UNIDADE",'SIMULAÇÃO 04'!BI207)} -> 0
B37: Seguros | D37: Risco de Engenhairia | V37: {=_xlfn.IFS($AQ$6="GLOBAL",'SIMULAÇÃO 01'!AH208,$AQ$6="POR UNIDADE",'SIMULAÇÃO 01'!AN208)} -> -3546.6495 | AC37: {=_xlfn.IFS($AQ$6="GLOBAL",'SIMULAÇÃO 02'!AO208,$AQ$6="POR UNIDADE",'SIMULAÇÃO 02'!AU208)} -> 0 | AJ37: {=_xlfn.IFS($AQ$6="GLOBAL",'SIMULAÇÃO 03'!AV208,$AQ$6="POR UNIDADE",'SIMULAÇÃO 03'!BB208)} -> 0 | AQ37: {=_xlfn.IFS($AQ$6="GLOBAL",'SIMULAÇÃO 04'!BC208,$AQ$6="POR UNIDADE",'SIMULAÇÃO 04'!BI208)} -> 0
D38: Assistência Técnica | V38: {=_xlfn.IFS($AQ$6="GLOBAL",'SIMULAÇÃO 01'!AH209,$AQ$6="POR UNIDADE",'SIMULAÇÃO 01'!AN209)} -> -3546.6495 | AC38: {=_xlfn.IFS($AQ$6="GLOBAL",'SIMULAÇÃO 02'!AO209,$AQ$6="POR UNIDADE",'SIMULAÇÃO 02'!AU209)} -> 0 | AJ38: {=_xlfn.IFS($AQ$6="GLOBAL",'SIMULAÇÃO 03'!AV209,$AQ$6="POR UNIDADE",'SIMULAÇÃO 03'!BB209)} -> 0 | AQ38: {=_xlfn.IFS($AQ$6="GLOBAL",'SIMULAÇÃO 04'!BC209,$AQ$6="POR UNIDADE",'SIMULAÇÃO 04'!BI209)} -> 0
D39: Conclusão de Obra | V39: {=_xlfn.IFS($AQ$6="GLOBAL",'SIMULAÇÃO 01'!AH210,$AQ$6="POR UNIDADE",'SIMULAÇÃO 01'!AN210)} -> -3546.6495 | AC39: {=_xlfn.IFS($AQ$6="GLOBAL",'SIMULAÇÃO 02'!AO210,$AQ$6="POR UNIDADE",'SIMULAÇÃO 02'!AU210)} -> 0 | AJ39: {=_xlfn.IFS($AQ$6="GLOBAL",'SIMULAÇÃO 03'!AV210,$AQ$6="POR UNIDADE",'SIMULAÇÃO 03'!BB210)} -> 0 | AQ39: {=_xlfn.IFS($AQ$6="GLOBAL",'SIMULAÇÃO 04'!BC210,$AQ$6="POR UNIDADE",'SIMULAÇÃO 04'!BI210)} -> 0
D40: Outros | V40: {=_xlfn.IFS($AQ$6="GLOBAL",'SIMULAÇÃO 01'!AH211,$AQ$6="POR UNIDADE",'SIMULAÇÃO 01'!AN211)} -> 0 | AC40: {=_xlfn.IFS($AQ$6="GLOBAL",'SIMULAÇÃO 02'!AO211,$AQ$6="POR UNIDADE",'SIMULAÇÃO 02'!AU211)} -> 0 | AJ40: {=_xlfn.IFS($AQ$6="GLOBAL",'SIMULAÇÃO 03'!AV211,$AQ$6="POR UNIDADE",'SIMULAÇÃO 03'!BB211)} -> 0 | AQ40: {=_xlfn.IFS($AQ$6="GLOBAL",'SIMULAÇÃO 04'!BC211,$AQ$6="POR UNIDADE",'SIMULAÇÃO 04'!BI211)} -> 0
D41: Impostos | V41: {=_xlfn.IFS($AQ$6="GLOBAL",'SIMULAÇÃO 01'!AH212,$AQ$6="POR UNIDADE",'SIMULAÇÃO 01'!AN212)} -> -359327.95 | AC41: {=_xlfn.IFS($AQ$6="GLOBAL",'SIMULAÇÃO 02'!AO212,$AQ$6="POR UNIDADE",'SIMULAÇÃO 02'!AU212)} -> 0 | AJ41: {=_xlfn.IFS($AQ$6="GLOBAL",'SIMULAÇÃO 03'!AV212,$AQ$6="POR UNIDADE",'SIMULAÇÃO 03'!BB212)} -> 0 | AQ41: {=_xlfn.IFS($AQ$6="GLOBAL",'SIMULAÇÃO 04'!BC212,$AQ$6="POR UNIDADE",'SIMULAÇÃO 04'!BI212)} -> 0
D42: Custo de Capital | V42: {=_xlfn.IFS($AQ$6="GLOBAL",'SIMULAÇÃO 01'!AH213,$AQ$6="POR UNIDADE",'SIMULAÇÃO 01'!AN213)} -> -466979.47 | AC42: {=_xlfn.IFS($AQ$6="GLOBAL",'SIMULAÇÃO 02'!AO213,$AQ$6="POR UNIDADE",'SIMULAÇÃO 02'!AU213)} -> 0 | AJ42: {=_xlfn.IFS($AQ$6="GLOBAL",'SIMULAÇÃO 03'!AV213,$AQ$6="POR UNIDADE",'SIMULAÇÃO 03'!BB213)} -> 0 | AQ42: {=_xlfn.IFS($AQ$6="GLOBAL",'SIMULAÇÃO 04'!BC213,$AQ$6="POR UNIDADE",'SIMULAÇÃO 04'!BI213)} -> 0
D43: RESULTADO | V43: {=_xlfn.IFS($AQ$6="GLOBAL",'SIMULAÇÃO 01'!AH214,$AQ$6="POR UNIDADE",'SIMULAÇÃO 01'!AN214)} -> 1721998 | AC43: {=_xlfn.IFS($AQ$6="GLOBAL",'SIMULAÇÃO 02'!AO214,$AQ$6="POR UNIDADE",'SIMULAÇÃO 02'!AU214)} -> 0 | AJ43: {=_xlfn.IFS($AQ$6="GLOBAL",'SIMULAÇÃO 03'!AV214,$AQ$6="POR UNIDADE",'SIMULAÇÃO 03'!BB214)} -> 0 | AQ43: {=_xlfn.IFS($AQ$6="GLOBAL",'SIMULAÇÃO 04'!BC214,$AQ$6="POR UNIDADE",'SIMULAÇÃO 04'!BI214)} -> 0
V44: =IFERROR(V43/V10,0) -> 0.1801895 | AC44: =IFERROR(AC43/AC10,0) -> 0 | AJ44: =IFERROR(AJ43/AJ10,0) -> 0 | AQ44: =IFERROR(AQ43/AQ10,0) -> 0
B46: ANÁLISE GRÁFICA | AQ46: SIMULAÇÃO 01
C49: =AQ46 -> SIMULAÇÃO 01 | E49: SIMULAÇÃO 01 | F49: SIMULAÇÃO 02 | G49: SIMULAÇÃO 03 | H49: SIMULAÇÃO 04
B50: Receita de Vendas | C50: {=_xlfn.IFS($AQ$46="SIMULAÇÃO 01",E50,$AQ$46="SIMULAÇÃO 02",F50,$AQ$46="SIMULAÇÃO 03",G50,$AQ$46="SIMULAÇÃO 04",H50)} -> 9556594.4 | E50: =V10 -> 9556594.4 | F50: =AC10 -> 0 | G50: =AJ10 -> 0 | H50: =AQ10 -> 0
B51: Terreno | C51: {=_xlfn.IFS($AQ$46="SIMULAÇÃO 01",E51,$AQ$46="SIMULAÇÃO 02",F51,$AQ$46="SIMULAÇÃO 03",G51,$AQ$46="SIMULAÇÃO 04",H51)} -> -804000 | E51: =SUM(V11:AB14) -> -804000 | F51: =SUM(AC11:AI14) -> 0 | G51: =SUM(AJ11:AP14) -> 0 | H51: =SUM(AQ11:AW14) -> 0
B52: Obra | C52: {=_xlfn.IFS($AQ$46="SIMULAÇÃO 01",E52,$AQ$46="SIMULAÇÃO 02",F52,$AQ$46="SIMULAÇÃO 03",G52,$AQ$46="SIMULAÇÃO 04",H52)} -> -4876643 | E52: =SUM(V15:AB16) -> -4876643 | F52: =SUM(AC15:AI16) -> 0 | G52: =SUM(AJ15:AP16) -> 0 | H52: =SUM(AQ15:AW16) -> 0
B53: Despesas Extras | C53: {=_xlfn.IFS($AQ$46="SIMULAÇÃO 01",E53,$AQ$46="SIMULAÇÃO 02",F53,$AQ$46="SIMULAÇÃO 03",G53,$AQ$46="SIMULAÇÃO 04",H53)} -> -661030.95 | E53: =SUM(V17:AB28) -> -661030.95 | F53: =SUM(AC17:AI28) -> 0 | G53: =SUM(AJ17:AP28) -> 0 | H53: =SUM(AQ17:AW28) -> 0
B54: Incorporação | C54: {=_xlfn.IFS($AQ$46="SIMULAÇÃO 01",E54,$AQ$46="SIMULAÇÃO 02",F54,$AQ$46="SIMULAÇÃO 03",G54,$AQ$46="SIMULAÇÃO 04",H54)} -> -34796.45 | E54: =SUM(V29) -> -34796.45 | F54: =SUM(AC29) -> 0 | G54: =SUM(AJ29) -> 0 | H54: =SUM(AQ29) -> 0
B55: Comercialização | C55: {=_xlfn.IFS($AQ$46="SIMULAÇÃO 01",E55,$AQ$46="SIMULAÇÃO 02",F55,$AQ$46="SIMULAÇÃO 03",G55,$AQ$46="SIMULAÇÃO 04",H55)} -> -621178.64 | E55: =SUM(V30:AB36) -> -621178.64 | F55: =SUM(AC30:AI36) -> 0 | G55: =SUM(AJ30:AP36) -> 0 | H55: =SUM(AQ30:AW36) -> 0
B56: Seguros | C56: {=_xlfn.IFS($AQ$46="SIMULAÇÃO 01",E56,$AQ$46="SIMULAÇÃO 02",F56,$AQ$46="SIMULAÇÃO 03",G56,$AQ$46="SIMULAÇÃO 04",H56)} -> -10639.948 | E56: =SUM(V37:AB40) -> -10639.948 | F56: =SUM(AC37:AI40) -> 0 | G56: =SUM(AJ37:AP40) -> 0 | H56: =SUM(AQ37:AW40) -> 0
B57: Impostos | C57: {=_xlfn.IFS($AQ$46="SIMULAÇÃO 01",E57,$AQ$46="SIMULAÇÃO 02",F57,$AQ$46="SIMULAÇÃO 03",G57,$AQ$46="SIMULAÇÃO 04",H57)} -> -826307.42 | E57: =SUM(V41:AB42) -> -826307.42 | F57: =SUM(AC41:AI42) -> 0 | G57: =SUM(AJ41:AP42) -> 0 | H57: =SUM(AQ41:AW42) -> 0
B58: Resultado | C58: {=_xlfn.IFS($AQ$46="SIMULAÇÃO 01",E58,$AQ$46="SIMULAÇÃO 02",F58,$AQ$46="SIMULAÇÃO 03",G58,$AQ$46="SIMULAÇÃO 04",H58)} -> 1721998 | E58: =V43 -> 1721998 | F58: =AC43 -> 0 | G58: =AJ43 -> 0 | H58: =AQ43 -> 0

Sheet RELATÓRIO
C3: RELATÓRIO DE EQUALIZAÇÃO DE ORÇAMENTO PARA PLANILHA PCI | P3: RELATÓRIO DE EQUALIZAÇÃO DE ORÇAMENTO PARA PLANILHA PCI | AI3: RELATÓRIO DE EQUALIZAÇÃO DE ORÇAMENTO PARA PLANILHA PCI | BB3: RELATÓRIO DE EQUALIZAÇÃO DE ORÇAMENTO PARA PLANILHA PCI
B7: OBRA | C7: ='SIMULAÇÃO 01'!$S$10 -> 0 | F7: DATA | G7: ='SIMULAÇÃO 01'!#REF! -> #REF! | I7: LOCAL | J7: ='SIMULAÇÃO 01'!$Z$10 -> Ribeirão Preto / SP | N7: OBRA | O7: ='SIMULAÇÃO 01'!$S$10 -> 0 | S7: DATA | U7: ='SIMULAÇÃO 01'!#REF! -> #REF! | Y7: LOCAL | AA7: ='SIMULAÇÃO 01'!$Z$10 -> Ribeirão Preto / SP | AG7: OBRA | AH7: ='SIMULAÇÃO 01'!$S$10 -> 0 | AL7: DATA | AN7: ='SIMULAÇÃO 01'!#REF! -> #REF! | AR7: LOCAL | AT7: ='SIMULAÇÃO 01'!$Z$10 -> Ribeirão Preto / SP
B9: ITEM | C9: ETAPA | D9: ORÇAMENTO | F9: EQUALIZAÇÃO | G9: DIFERENÇA | I9: PCI ADOTADO (C/ BDI) | K9: % | N9: ITEM | O9: ETAPA | P9: TOTAL | Q9: PESO | S9: =#REF! -> #REF! | T9: =#REF! -> #REF! | U9: =#REF! -> #REF! | V9: =#REF! -> #REF! | W9: =#REF! -> #REF! | X9: =#REF! -> #REF! | Y9: =#REF! -> #REF! | Z9: =#REF! -> #REF! | ... AD9: =#REF! -> #REF! | AG9: ITEM | AH9: ETAPA | AI9: TOTAL | AJ9: PESO | AL9: =#REF! -> #REF! | AM9: =#REF! -> #REF! | AN9: =#REF! -> #REF! | AO9: =#REF! -> #REF! | AP9: =#REF! -> #REF! | AQ9: =#REF! -> #REF! | AR9: =#REF! -> #REF! | AS9: =#REF! -> #REF! | ... AW9: =#REF! -> #REF!
B11: 1 | C11: =VLOOKUP(B11,#REF!,2,0) -> #REF! | D11: =VLOOKUP(B11,#REF!,10,0) -> #REF! | F11: =VLOOKUP(B11,#REF!,15,0) -> #REF! | G11: =D11-F11 -> #REF! | I11: =VLOOKUP(B11,#REF!,11,0) -> #REF! | K11: =I11/SUM($I$11:$J$50) -> #REF! | N11: 1 | O11: =C11 -> #REF! | P11: =I11 -> #REF! | Q11: =K11 -> #REF! | S11: =#REF! -> #REF! | T11: =#REF! -> #REF! | U11: =#REF! -> #REF! | V11: =#REF! -> #REF! | W11: =#REF! -> #REF! | X11: =#REF! -> #REF! | Y11: =#REF! -> #REF! | Z11: =#REF! -> #REF! | ... AD11: =#REF! -> #REF! | AG11: 1 | AH11: =O11 -> #REF! | AI11: =P11 -> #REF! | AJ11: =Q11 -> #REF! | AL11: =#REF! -> #REF! | AM11: =#REF! -> #REF! | AN11: =#REF! -> #REF! | AO11: =#REF! -> #REF! | AP11: =#REF! -> #REF! | AQ11: =#REF! -> #REF! | AR11: =#REF! -> #REF! | AS11: =#REF! -> #REF! | ... AW11: =#REF! -> #REF!
S12: =#REF! -> #REF! | T12: =#REF! -> #REF! | U12: =#REF! -> #REF! | V12: =#REF! -> #REF! | W12: =#REF! -> #REF! | X12: =#REF! -> #REF! | Y12: =#REF! -> #REF! | Z12: =#REF! -> #REF! | ... AD12: =#REF! -> #REF! | AL12: =#REF! -> #REF! | AM12: =#REF! -> #REF! | AN12: =#REF! -> #REF! | AO12: =#REF! -> #REF! | AP12: =#REF! -> #REF! | AQ12: =#REF! -> #REF! | AR12: =#REF! -> #REF! | AS12: =#REF! -> #REF! | ... AW12: =#REF! -> #REF!
B13: 2 | C13: =VLOOKUP(B13,#REF!,2,0) -> #REF! | D13: =VLOOKUP(B13,#REF!,10,0) -> #REF! | F13: =VLOOKUP(B13,#REF!,15,0) -> #REF! | G13: =D13-F13 -> #REF! | I13: =VLOOKUP(B13,#REF!,11,0) -> #REF! | K13: =I13/SUM($I$11:$J$50) -> #REF! | N13: 2 | O13: =C13 -> #REF! | P13: =I13 -> #REF! | Q13: =K13 -> #REF! | S13: =#REF! -> #REF! | T13: =#REF! -> #REF! | U13: =#REF! -> #REF! | V13: =#REF! -> #REF! | W13: =#REF! -> #REF! | X13: =#REF! -> #REF! | Y13: =#REF! -> #REF! | Z13: =#REF! -> #REF! | ... AD13: =#REF! -> #REF! | AG13: 2 | AH13: =O13 -> #REF! | AI13: =P13 -> #REF! | AJ13: =Q13 -> #REF! | AL13: =#REF! -> #REF! | AM13: =#REF! -> #REF! | AN13: =#REF! -> #REF! | AO13: =#REF! -> #REF! | AP13: =#REF! -> #REF! | AQ13: =#REF! -> #REF! | AR13: =#REF! -> #REF! | AS13: =#REF! -> #REF! | ... AW13: =#REF! -> #REF!
S14: =#REF! -> #REF! | T14: =#REF! -> #REF! | U14: =#REF! -> #REF! | V14: =#REF! -> #REF! | W14: =#REF! -> #REF! | X14: =#REF! -> #REF! | Y14: =#REF! -> #REF! | Z14: =#REF! -> #REF! | ... AD14: =#REF! -> #REF! | AL14: =#REF! -> #REF! | AM14: =#REF! -> #REF! | AN14: =#REF! -> #REF! | AO14: =#REF! -> #REF! | AP14: =#REF! -> #REF! | AQ14: =#REF! -> #REF! | AR14: =#REF! -> #REF! | AS14: =#REF! -> #REF! | ... AW14: =#REF! -> #REF!
B15: 3 | C15: =VLOOKUP(B15,#REF!,2,0) -> #REF! | D15: =VLOOKUP(B15,#REF!,10,0) -> #REF! | F15: =VLOOKUP(B15,#REF!,15,0) -> #REF! | G15: =D15-F15 -> #REF! | I15: =VLOOKUP(B15,#REF!,11,0) -> #REF! | K15: =I15/SUM($I$11:$J$50) -> #REF! | N15: 3 | O15: =C15 -> #REF! | P15: =I15 -> #REF! | Q15: =K15 -> #REF! | S15: =#REF! -> #REF! | T15: =#REF! -> #REF! | U15: =#REF! -> #REF! | V15: =#REF! -> #REF! | W15: =#REF! -> #REF! | X15: =#REF! -> #REF! | Y15: =#REF! -> #REF! | Z15: =#REF! -> #REF! | ... AD15: =#REF! -> #REF! | AG15: 3 | AH15: =O15 -> #REF! | AI15: =P15 -> #REF! | AJ15: =Q15 -> #REF! | AL15: =#REF! -> #REF! | AM15: =#REF! -> #REF! | AN15: =#REF! -> #REF! | AO15: =#REF! -> #REF! | AP15: =#REF! -> #REF! | AQ15: =#REF! -> #REF! | AR15: =#REF! -> #REF! | AS15: =#REF! -> #REF! | ... AW15: =#REF! -> #REF!
S16: =#REF! -> #REF! | T16: =#REF! -> #REF! | U16: =#REF! -> #REF! | V16: =#REF! -> #REF! | W16: =#REF! -> #REF! | X16: =#REF! -> #REF! | Y16: =#REF! -> #REF! | Z16: =#REF! -> #REF! | ... AD16: =#REF! -> #REF! | AL16: =#REF! -> #REF! | AM16: =#REF! -> #REF! | AN16: =#REF! -> #REF! | AO16: =#REF! -> #REF! | AP16: =#REF! -> #REF! | AQ16: =#REF! -> #REF! | AR16: =#REF! -> #REF! | AS16: =#REF! -> #REF! | ... AW16: =#REF! -> #REF!
B17: 4 | C17: =VLOOKUP(B17,#REF!,2,0) -> #REF! | D17: =VLOOKUP(B17,#REF!,10,0) -> #REF! | F17: =VLOOKUP(B17,#REF!,15,0) -> #REF! | G17: =D17-F17 -> #REF! | I17: =VLOOKUP(B17,#REF!,11,0) -> #REF! | K17: =I17/SUM($I$11:$J$50) -> #REF! | N17: 4 | O17: =C17 -> #REF! | P17: =I17 -> #REF! | Q17: =K17 -> #REF! | S17: =#REF! -> #REF! | T17: =#REF! -> #REF! | U17: =#REF! -> #REF! | V17: =#REF! -> #REF! | W17: =#REF! -> #REF! | X17: =#REF! -> #REF! | Y17: =#REF! -> #REF! | Z17: =#REF! -> #REF! | ... AD17: =#REF! -> #REF! | AG17: 4 | AH17: =O17 -> #REF! | AI17: =P17 -> #REF! | AJ17: =Q17 -> #REF! | AL17: =#REF! -> #REF! | AM17: =#REF! -> #REF! | AN17: =#REF! -> #REF! | AO17: =#REF! -> #REF! | AP17: =#REF! -> #REF! | AQ17: =#REF! -> #REF! | AR17: =#REF! -> #REF! | AS17: =#REF! -> #REF! | ... AW17: =#REF! -> #REF!
S18: =#REF! -> #REF! | T18: =#REF! -> #REF! | U18: =#REF! -> #REF! | V18: =#REF! -> #REF! | W18: =#REF! -> #REF! | X18: =#REF! -> #REF! | Y18: =#REF! -> #REF! | Z18: =#REF! -> #REF! | ... AD18: =#REF! -> #REF! | AL18: =#REF! -> #REF! | AM18: =#REF! -> #REF! | AN18: =#REF! -> #REF! | AO18: =#REF! -> #REF! | AP18: =#REF! -> #REF! | AQ18: =#REF! -> #REF! | AR18: =#REF! -> #REF! | AS18: =#REF! -> #REF! | ... AW18: =#REF! -> #REF!
B19: 5 | C19: =VLOOKUP(B19,#REF!,2,0) -> #REF! | D19: =VLOOKUP(B19,#REF!,10,0) -> #REF! | F19: =VLOOKUP(B19,#REF!,15,0) -> #REF! | G19: =D19-F19 -> #REF! | I19: =VLOOKUP(B19,#REF!,11,0) -> #REF! | K19: =I19/SUM($I$11:$J$50) -> #REF! | N19: 5 | O19: =C19 -> #REF! | P19: =I19 -> #REF! | Q19: =K19 -> #REF! | S19: =#REF! -> #REF! | T19: =#REF! -> #REF! | U19: =#REF! -> #REF! | V19: =#REF! -> #REF! | W19: =#REF! -> #REF! | X19: =#REF! -> #REF! | Y19: =#REF! -> #REF! | Z19: =#REF! -> #REF! | ... AD19: =#REF! -> #REF! | AG19: 5 | AH19: =O19 -> #REF! | AI19: =P19 -> #REF! | AJ19: =Q19 -> #REF! | AL19: =#REF! -> #REF! | AM19: =#REF! -> #REF! | AN19: =#REF! -> #REF! | AO19: =#REF! -> #REF! | AP19: =#REF! -> #REF! | AQ19: =#REF! -> #REF! | AR19: =#REF! -> #REF! | AS19: =#REF! -> #REF! | ... AW19: =#REF! -> #REF!
S20: =#REF! -> #REF! | T20: =#REF! -> #REF! | U20: =#REF! -> #REF! | V20: =#REF! -> #REF! | W20: =#REF! -> #REF! | X20: =#REF! -> #REF! | Y20: =#REF! -> #REF! | Z20: =#REF! -> #REF! | ... AD20: =#REF! -> #REF! | AL20: =#REF! -> #REF! | AM20: =#REF! -> #REF! | AN20: =#REF! -> #REF! | AO20: =#REF! -> #REF! | AP20: =#REF! -> #REF! | AQ20: =#REF! -> #REF! | AR20: =#REF! -> #REF! | AS20: =#REF! -> #REF! | ... AW20: =#REF! -> #REF!
B21: 6 | C21: =VLOOKUP(B21,#REF!,2,0) -> #REF! | D21: =VLOOKUP(B21,#REF!,10,0) -> #REF! | F21: =VLOOKUP(B21,#REF!,15,0) -> #REF! | G21: =D21-F21 -> #REF! | I21: =VLOOKUP(B21,#REF!,11,0) -> #REF! | K21: =I21/SUM($I$11:$J$50) -> #REF! | N21: 6 | O21: =C21 -> #REF! | P21: =I21 -> #REF! | Q21: =K21 -> #REF! | S21: =#REF! -> #REF! | T21: =#REF! -> #REF! | U21: =#REF! -> #REF! | V21: =#REF! -> #REF! | W21: =#REF! -> #REF! | X21: =#REF! -> #REF! | Y21: =#REF! -> #REF! | Z21: =#REF! -> #REF! | ... AD21: =#REF! -> #REF! | AG21: 6 | AH21: =O21 -> #REF! | AI21: =P21 -> #REF! | AJ21: =Q21 -> #REF! | AL21: =#REF! -> #REF! | AM21: =#REF! -> #REF! | AN21: =#REF! -> #REF! | AO21: =#REF! -> #REF! | AP21: =#REF! -> #REF! | AQ21: =#REF! -> #REF! | AR21: =#REF! -> #REF! | AS21: =#REF! -> #REF! | ... AW21: =#REF! -> #REF!
S22: =#REF! -> #REF! | T22: =#REF! -> #REF! | U22: =#REF! -> #REF! | V22: =#REF! -> #REF! | W22: =#REF! -> #REF! | X22: =#REF! -> #REF! | Y22: =#REF! -> #REF! | Z22: =#REF! -> #REF! | ... AD22: =#REF! -> #REF! | AL22: =#REF! -> #REF! | AM22: =#REF! -> #REF! | AN22: =#REF! -> #REF! | AO22: =#REF! -> #REF! | AP22: =#REF! -> #REF! | AQ22: =#REF! -> #REF! | AR22: =#REF! -> #REF! | AS22: =#REF! -> #REF! | ... AW22: =#REF! -> #REF!
B23: 7 | C23: =VLOOKUP(B23,#REF!,2,0) -> #REF! | D23: =VLOOKUP(B23,#REF!,10,0) -> #REF! | F23: =VLOOKUP(B23,#REF!,15,0) -> #REF! | G23: =D23-F23 -> #REF! | I23: =VLOOKUP(B23,#REF!,11,0) -> #REF! | K23: =I23/SUM($I$11:$J$50) -> #REF! | N23: 7 | O23: =C23 -> #REF! | P23: =I23 -> #REF! | Q23: =K23 -> #REF! | S23: =#REF! -> #REF! | T23: =#REF! -> #REF! | U23: =#REF! -> #REF! | V23: =#REF! -> #REF! | W23: =#REF! -> #REF! | X23: =#REF! -> #REF! | Y23: =#REF! -> #REF! | Z23: =#REF! -> #REF! | ... AD23: =#REF! -> #REF! | AG23: 7 | AH23: =O23 -> #REF! | AI23: =P23 -> #REF! | AJ23: =Q23 -> #REF! | AL23: =#REF! -> #REF! | AM23: =#REF! -> #REF! | AN23: =#REF! -> #REF! | AO23: =#REF! -> #REF! | AP23: =#REF! -> #REF! | AQ23: =#REF! -> #REF! | AR23: =#REF! -> #REF! | AS23: =#REF! -> #REF! | ... AW23: =#REF! -> #REF!
S24: =#REF! -> #REF! | T24: =#REF! -> #REF! | U24: =#REF! -> #REF! | V24: =#REF! -> #REF! | W24: =#REF! -> #REF! | X24: =#REF! -> #REF! | Y24: =#REF! -> #REF! | Z24: =#REF! -> #REF! | ... AD24: =#REF! -> #REF! | AL24: =#REF! -> #REF! | AM24: =#REF! -> #REF! | AN24: =#REF! -> #REF! | AO24: =#REF! -> #REF! | AP24: =#REF! -> #REF! | AQ24: =#REF! -> #REF! | AR24: =#REF! -> #REF! | AS24: =#REF! -> #REF! | ... AW24: =#REF! -> #REF!
B25: 8 | C25: =VLOOKUP(B25,#REF!,2,0) -> #REF! | D25: =VLOOKUP(B25,#REF!,10,0) -> #REF! | F25: =VLOOKUP(B25,#REF!,15,0) -> #REF! | G25: =D25-F25 -> #REF! | I25: =VLOOKUP(B25,#REF!,11,0) -> #REF! | K25: =I25/SUM($I$11:$J$50) -> #REF! | N25: 8 | O25: =C25 -> #REF! | P25: =I25 -> #REF! | Q25: =K25 -> #REF! | S25: =#REF! -> #REF! | T25: =#REF! -> #REF! | U25: =#REF! -> #REF! | V25: =#REF! -> #REF! | W25: =#REF! -> #REF! | X25: =#REF! -> #REF! | Y25: =#REF! -> #REF! | Z25: =#REF! -> #REF! | ... AD25: =#REF! -> #REF! | AG25: 8 | AH25: =O25 -> #REF! | AI25: =P25 -> #REF! | AJ25: =Q25 -> #REF! | AL25: =#REF! -> #REF! | AM25: =#REF! -> #REF! | AN25: =#REF! -> #REF! | AO25: =#REF! -> #REF! | AP25: =#REF! -> #REF! | AQ25: =#REF! -> #REF! | AR25: =#REF! -> #REF! | AS25: =#REF! -> #REF! | ... AW25: =#REF! -> #REF!
S26: =#REF! -> #REF! | T26: =#REF! -> #REF! | U26: =#REF! -> #REF! | V26: =#REF! -> #REF! | W26: =#REF! -> #REF! | X26: =#REF! -> #REF! | Y26: =#REF! -> #REF! | Z26: =#REF! -> #REF! | ... AD26: =#REF! -> #REF! | AL26: =#REF! -> #REF! | AM26: =#REF! -> #REF! | AN26: =#REF! -> #REF! | AO26: =#REF! -> #REF! | AP26: =#REF! -> #REF! | AQ26: =#REF! -> #REF! | AR26: =#REF! -> #REF! | AS26: =#REF! -> #REF! | ... AW26: =#REF! -> #REF!
B27: 9 | C27: =VLOOKUP(B27,#REF!,2,0) -> #REF! | D27: =VLOOKUP(B27,#REF!,10,0) -> #REF! | F27: =VLOOKUP(B27,#REF!,15,0) -> #REF! | G27: =D27-F27 -> #REF! | I27: =VLOOKUP(B27,#REF!,11,0) -> #REF! | K27: =I27/SUM($I$11:$J$50) -> #REF! | N27: 9 | O27: =C27 -> #REF! | P27: =I27 -> #REF! | Q27: =K27 -> #REF! | S27: =#REF! -> #REF! | T27: =#REF! -> #REF! | U27: =#REF! -> #REF! | V27: =#REF! -> #REF! | W27: =#REF! -> #REF! | X27: =#REF! -> #REF! | Y27: =#REF! -> #REF! | Z27: =#REF! -> #REF! | ... AD27: =#REF! -> #REF! | AG27: 9 | AH27: =O27 -> #REF! | AI27: =P27 -> #REF! | AJ27: =Q27 -> #REF! | AL27: =#REF! -> #REF! | AM27: =#REF! -> #REF! | AN27: =#REF! -> #REF! | AO27: =#REF! -> #REF! | AP27: =#REF! -> #REF! | AQ27: =#REF! -> #REF! | AR27: =#REF! -> #REF! | AS27: =#REF! -> #REF! | ... AW27: =#REF! -> #REF!
S28: =#REF! -> #REF! | T28: =#REF! -> #REF! | U28: =#REF! -> #REF! | V28: =#REF! -> #REF! | W28: =#REF! -> #REF! | X28: =#REF! -> #REF! | Y28: =#REF! -> #REF! | Z28: =#REF! -> #REF! | ... AD28: =#REF! -> #REF! | AL28: =#REF! -> #REF! | AM28: =#REF! -> #REF! | AN28: =#REF! -> #REF! | AO28: =#REF! -> #REF! | AP28: =#REF! -> #REF! | AQ28: =#REF! -> #REF! | AR28: =#REF! -> #REF! | AS28: =#REF! -> #REF! | ... AW28: =#REF! -> #REF!
B29: 10 | C29: =VLOOKUP(B29,#REF!,2,0) -> #REF! | D29: =VLOOKUP(B29,#REF!,10,0) -> #REF! | F29: =VLOOKUP(B29,#REF!,15,0) -> #REF! | G29: =D29-F29 -> #REF! | I29: =VLOOKUP(B29,#REF!,11,0) -> #REF! | K29: =I29/SUM($I$11:$J$50) -> #REF! | N29: 10 | O29: =C29 -> #REF! | P29: =I29 -> #REF! | Q29: =K29 -> #REF! | S29: =#REF! -> #REF! | T29: =#REF! -> #REF! | U29: =#REF! -> #REF! | V29: =#REF! -> #REF! | W29: =#REF! -> #REF! | X29: =#REF! -> #REF! | Y29: =#REF! -> #REF! | Z29: =#REF! -> #REF! | ... AD29: =#REF! -> #REF! | AG29: 10 | AH29: =O29 -> #REF! | AI29: =P29 -> #REF! | AJ29: =Q29 -> #REF! | AL29: =#REF! -> #REF! | AM29: =#REF! -> #REF! | AN29: =#REF! -> #REF! | AO29: =#REF! -> #REF! | AP29: =#REF! -> #REF! | AQ29: =#REF! -> #REF! | AR29: =#REF! -> #REF! | AS29: =#REF! -> #REF! | ... AW29: =#REF! -> #REF!
S30: =#REF! -> #REF! | T30: =#REF! -> #REF! | U30: =#REF! -> #REF! | V30: =#REF! -> #REF! | W30: =#REF! -> #REF! | X30: =#REF! -> #REF! | Y30: =#REF! -> #REF! | Z30: =#REF! -> #REF! | ... AD30: =#REF! -> #REF! | AL30: =#REF! -> #REF! | AM30: =#REF! -> #REF! | AN30: =#REF! -> #REF! | AO30: =#REF! -> #REF! | AP30: =#REF! -> #REF! | AQ30: =#REF! -> #REF! | AR30: =#REF! -> #REF! | AS30: =#REF! -> #REF! | ... AW30: =#REF! -> #REF! | BA30: =S9 -> #REF! | BB30: =T9 -> #REF! | BC30: =U9 -> #REF! | BD30: =V9 -> #REF! | BE30: =W9 -> #REF! | BF30: =X9 -> #REF! | BG30: =Y9 -> #REF! | BH30: =Z9 -> #REF! | ... BL30: =AD9 -> #REF! | BM30: =AL9 -> #REF! | BN30: =AM9 -> #REF! | BO30: =AN9 -> #REF! | BP30: =AO9 -> #REF! | BQ30: =AP9 -> #REF! | BR30: =AQ9 -> #REF! | BS30: =AR9 -> #REF! | BT30: =AS9 -> #REF! | ... BX30: =AW9 -> #REF!
B31: 11 | C31: =VLOOKUP(B31,#REF!,2,0) -> #REF! | D31: =VLOOKUP(B31,#REF!,10,0) -> #REF! | F31: =VLOOKUP(B31,#REF!,15,0) -> #REF! | G31: =D31-F31 -> #REF! | I31: =VLOOKUP(B31,#REF!,11,0) -> #REF! | K31: =I31/SUM($I$11:$J$50) -> #REF! | N31: 11 | O31: =C31 -> #REF! | P31: =I31 -> #REF! | Q31: =K31 -> #REF! | S31: =#REF! -> #REF! | T31: =#REF! -> #REF! | U31: =#REF! -> #REF! | V31: =#REF! -> #REF! | W31: =#REF! -> #REF! | X31: =#REF! -> #REF! | Y31: =#REF! -> #REF! | Z31: =#REF! -> #REF! | ... AD31: =#REF! -> #REF! | AG31: 11 | AH31: =O31 -> #REF! | AI31: =P31 -> #REF! | AJ31: =Q31 -> #REF! | AL31: =#REF! -> #REF! | AM31: =#REF! -> #REF! | AN31: =#REF! -> #REF! | AO31: =#REF! -> #REF! | AP31: =#REF! -> #REF! | AQ31: =#REF! -> #REF! | AR31: =#REF! -> #REF! | AS31: =#REF! -> #REF! | ... AW31: =#REF! -> #REF!
S32: =#REF! -> #REF! | T32: =#REF! -> #REF! | U32: =#REF! -> #REF! | V32: =#REF! -> #REF! | W32: =#REF! -> #REF! | X32: =#REF! -> #REF! | Y32: =#REF! -> #REF! | Z32: =#REF! -> #REF! | ... AD32: =#REF! -> #REF! | AL32: =#REF! -> #REF! | AM32: =#REF! -> #REF! | AN32: =#REF! -> #REF! | AO32: =#REF! -> #REF! | AP32: =#REF! -> #REF! | AQ32: =#REF! -> #REF! | AR32: =#REF! -> #REF! | AS32: =#REF! -> #REF! | ... AW32: =#REF! -> #REF!
B33: 12 | C33: =VLOOKUP(B33,#REF!,2,0) -> #REF! | D33: =VLOOKUP(B33,#REF!,10,0) -> #REF! | F33: =VLOOKUP(B33,#REF!,15,0) -> #REF! | G33: =D33-F33 -> #REF! | I33: =VLOOKUP(B33,#REF!,11,0) -> #REF! | K33: =I33/SUM($I$11:$J$50) -> #REF! | N33: 12 | O33: =C33 -> #REF! | P33: =I33 -> #REF! | Q33: =K33 -> #REF! | S33: =#REF! -> #REF! | T33: =#REF! -> #REF! | U33: =#REF! -> #REF! | V33: =#REF! -> #REF! | W33: =#REF! -> #REF! | X33: =#REF! -> #REF! | Y33: =#REF! -> #REF! | Z33: =#REF! -> #REF! | ... AD33: =#REF! -> #REF! | AG33: 12 | AH33: =O33 -> #REF! | AI33: =P33 -> #REF! | AJ33: =Q33 -> #REF! | AL33: =#REF! -> #REF! | AM33: =#REF! -> #REF! | AN33: =#REF! -> #REF! | AO33: =#REF! -> #REF! | AP33: =#REF! -> #REF! | AQ33: =#REF! -> #REF! | AR33: =#REF! -> #REF! | AS33: =#REF! -> #REF! | ... AW33: =#REF! -> #REF!
S34: =#REF! -> #REF! | T34: =#REF! -> #REF! | U34: =#REF! -> #REF! | V34: =#REF! -> #REF! | W34: =#REF! -> #REF! | X34: =#REF! -> #REF! | Y34: =#REF! -> #REF! | Z34: =#REF! -> #REF! | ... AD34: =#REF! -> #REF! | AL34: =#REF! -> #REF! | AM34: =#REF! -> #REF! | AN34: =#REF! -> #REF! | AO34: =#REF! -> #REF! | AP34: =#REF! -> #REF! | AQ34: =#REF! -> #REF! | AR34: =#REF! -> #REF! | AS34: =#REF! -> #REF! | ... AW34: =#REF! -> #REF!
B35: 13 | C35: =VLOOKUP(B35,#REF!,2,0) -> #REF! | D35: =VLOOKUP(B35,#REF!,10,0) -> #REF! | F35: =VLOOKUP(B35,#REF!,15,0) -> #REF! | G35: =D35-F35 -> #REF! | I35: =VLOOKUP(B35,#REF!,11,0) -> #REF! | K35: =I35/SUM($I$11:$J$50) -> #REF! | N35: 13 | O35: =C35 -> #REF! | P35: =I35 -> #REF! | Q35: =K35 -> #REF! | S35: =#REF! -> #REF! | T35: =#REF! -> #REF! | U35: =#REF! -> #REF! | V35: =#REF! -> #REF! | W35: =#REF! -> #REF! | X35: =#REF! -> #REF! | Y35: =#REF! -> #REF! | Z35: =#REF! -> #REF! | ... AD35: =#REF! -> #REF! | AG35: 13 | AH35: =O35 -> #REF! | AI35: =P35 -> #REF! | AJ35: =Q35 -> #REF! | AL35: =#REF! -> #REF! | AM35: =#REF! -> #REF! | AN35: =#REF! -> #REF! | AO35: =#REF! -> #REF! | AP35: =#REF! -> #REF! | AQ35: =#REF! -> #REF! | AR35: =#REF! -> #REF! | AS35: =#REF! -> #REF! | ... AW35: =#REF! -> #REF! | AZ35: SAÍDAS | BA35: =S55 -> #REF! | BB35: =T55 -> #REF! | BC35: =U55 -> #REF! | BD35: =V55 -> #REF! | BE35: =W55 -> #REF! | BF35: =X55 -> #REF! | BG35: =Y55 -> #REF! | BH35: =Z55 -> #REF! | ... BL35: =AD55 -> #REF! | BM35: =AL55 -> #REF! | BN35: =AM55 -> #REF! | BO35: =AN55 -> #REF! | BP35: =AO55 -> #REF! | BQ35: =AP55 -> #REF! | BR35: =AQ55 -> #REF! | BS35: =AR55 -> #REF! | BT35: =AS55 -> #REF! | ... BX35: =AW55 -> #REF!
S36: =#REF! -> #REF! | T36: =#REF! -> #REF! | U36: =#REF! -> #REF! | V36: =#REF! -> #REF! | W36: =#REF! -> #REF! | X36: =#REF! -> #REF! | Y36: =#REF! -> #REF! | Z36: =#REF! -> #REF! | ... AD36: =#REF! -> #REF! | AL36: =#REF! -> #REF! | AM36: =#REF! -> #REF! | AN36: =#REF! -> #REF! | AO36: =#REF! -> #REF! | AP36: =#REF! -> #REF! | AQ36: =#REF! -> #REF! | AR36: =#REF! -> #REF! | AS36: =#REF! -> #REF! | ... AW36: =#REF! -> #REF!
B37: 14 | C37: =VLOOKUP(B37,#REF!,2,0) -> #REF! | D37: =VLOOKUP(B37,#REF!,10,0) -> #REF! | F37: =VLOOKUP(B37,#REF!,15,0) -> #REF! | G37: =D37-F37 -> #REF! | I37: =VLOOKUP(B37,#REF!,11,0) -> #REF! | K37: =I37/SUM($I$11:$J$50) -> #REF! | N37: 14 | O37: =C37 -> #REF! | P37: =I37 -> #REF! | Q37: =K37 -> #REF! | S37: =#REF! -> #REF! | T37: =#REF! -> #REF! | U37: =#REF! -> #REF! | V37: =#REF! -> #REF! | W37: =#REF! -> #REF! | X37: =#REF! -> #REF! | Y37: =#REF! -> #REF! | Z37: =#REF! -> #REF! | ... AD37: =#REF! -> #REF! | AG37: 14 | AH37: =O37 -> #REF! | AI37: =P37 -> #REF! | AJ37: =Q37 -> #REF! | AL37: =#REF! -> #REF! | AM37: =#REF! -> #REF! | AN37: =#REF! -> #REF! | AO37: =#REF! -> #REF! | AP37: =#REF! -> #REF! | AQ37: =#REF! -> #REF! | AR37: =#REF! -> #REF! | AS37: =#REF! -> #REF! | ... AW37: =#REF! -> #REF!
S38: =#REF! -> #REF! | T38: =#REF! -> #REF! | U38: =#REF! -> #REF! | V38: =#REF! -> #REF! | W38: =#REF! -> #REF! | X38: =#REF! -> #REF! | Y38: =#REF! -> #REF! | Z38: =#REF! -> #REF! | ... AD38: =#REF! -> #REF! | AL38: =#REF! -> #REF! | AM38: =#REF! -> #REF! | AN38: =#REF! -> #REF! | AO38: =#REF! -> #REF! | AP38: =#REF! -> #REF! | AQ38: =#REF! -> #REF! | AR38: =#REF! -> #REF! | AS38: =#REF! -> #REF! | ... AW38: =#REF! -> #REF!
B39: 15 | C39: =VLOOKUP(B39,#REF!,2,0) -> #REF! | D39: =VLOOKUP(B39,#REF!,10,0) -> #REF! | F39: =VLOOKUP(B39,#REF!,15,0) -> #REF! | G39: =D39-F39 -> #REF! | I39: =VLOOKUP(B39,#REF!,11,0) -> #REF! | K39: =I39/SUM($I$11:$J$50) -> #REF! | N39: 15 | O39: =C39 -> #REF! | P39: =I39 -> #REF! | Q39: =K39 -> #REF! | S39: =#REF! -> #REF! | T39: =#REF! -> #REF! | U39: =#REF! -> #REF! | V39: =#REF! -> #REF! | W39: =#REF! -> #REF! | X39: =#REF! -> #REF! | Y39: =#REF! -> #REF! | Z39: =#REF! -> #REF! | ... AD39: =#REF! -> #REF! | AG39: 15 | AH39: =O39 -> #REF! | AI39: =P39 -> #REF! | AJ39: =Q39 -> #REF! | AL39: =#REF! -> #REF! | AM39: =#REF! -> #REF! | AN39: =#REF! -> #REF! | AO39: =#REF! -> #REF! | AP39: =#REF! -> #REF! | AQ39: =#REF! -> #REF! | AR39: =#REF! -> #REF! | AS39: =#REF! -> #REF! | ... AW39: =#REF! -> #REF!
S40: =#REF! -> #REF! | T40: =#REF! -> #REF! | U40: =#REF! -> #REF! | V40: =#REF! -> #REF! | W40: =#REF! -> #REF! | X40: =#REF! -> #REF! | Y40: =#REF! -> #REF! | Z40: =#REF! -> #REF! | ... AD40: =#REF! -> #REF! | AL40: =#REF! -> #REF! | AM40: =#REF! -> #REF! | AN40: =#REF! -> #REF! | AO40: =#REF! -> #REF! | AP40: =#REF! -> #REF! | AQ40: =#REF! -> #REF! | AR40: =#REF! -> #REF! | AS40: =#REF! -> #REF! | ... AW40: =#REF! -> #REF!
B41: 16 | C41: =VLOOKUP(B41,#REF!,2,0) -> #REF! | D41: =VLOOKUP(B41,#REF!,10,0) -> #REF! | F41: =VLOOKUP(B41,#REF!,15,0) -> #REF! | G41: =D41-F41 -> #REF! | I41: =VLOOKUP(B41,#REF!,11,0) -> #REF! | K41: =I41/SUM($I$11:$J$50) -> #REF! | N41: 16 | O41: =C41 -> #REF! | P41: =I41 -> #REF! | Q41: =K41 -> #REF! | S41: =#REF! -> #REF! | T41: =#REF! -> #REF! | U41: =#REF! -> #REF! | V41: =#REF! -> #REF! | W41: =#REF! -> #REF! | X41: =#REF! -> #REF! | Y41: =#REF! -> #REF! | Z41: =#REF! -> #REF! | ... AD41: =#REF! -> #REF! | AG41: 16 | AH41: =O41 -> #REF! | AI41: =P41 -> #REF! | AJ41: =Q41 -> #REF! | AL41: =#REF! -> #REF! | AM41: =#REF! -> #REF! | AN41: =#REF! -> #REF! | AO41: =#REF! -> #REF! | AP41: =#REF! -> #REF! | AQ41: =#REF! -> #REF! | AR41: =#REF! -> #REF! | AS41: =#REF! -> #REF! | ... AW41: =#REF! -> #REF!
S42: =#REF! -> #REF! | T42: =#REF! -> #REF! | U42: =#REF! -> #REF! | V42: =#REF! -> #REF! | W42: =#REF! -> #REF! | X42: =#REF! -> #REF! | Y42: =#REF! -> #REF! | Z42: =#REF! -> #REF! | ... AD42: =#REF! -> #REF! | AL42: =#REF! -> #REF! | AM42: =#REF! -> #REF! | AN42: =#REF! -> #REF! | AO42: =#REF! -> #REF! | AP42: =#REF! -> #REF! | AQ42: =#REF! -> #REF! | AR42: =#REF! -> #REF! | AS42: =#REF! -> #REF! | ... AW42: =#REF! -> #REF!
B43: 17 | C43: =VLOOKUP(B43,#REF!,2,0) -> #REF! | D43: =VLOOKUP(B43,#REF!,10,0) -> #REF! | F43: =VLOOKUP(B43,#REF!,15,0) -> #REF! | G43: =D43-F43 -> #REF! | I43: =VLOOKUP(B43,#REF!,11,0) -> #REF! | K43: =I43/SUM($I$11:$J$50) -> #REF! | N43: 17 | O43: =C43 -> #REF! | P43: =I43 -> #REF! | Q43: =K43 -> #REF! | S43: =#REF! -> #REF! | T43: =#REF! -> #REF! | U43: =#REF! -> #REF! | V43: =#REF! -> #REF! | W43: =#REF! -> #REF! | X43: =#REF! -> #REF! | Y43: =#REF! -> #REF! | Z43: =#REF! -> #REF! | ... AD43: =#REF! -> #REF! | AG43: 17 | AH43: =O43 -> #REF! | AI43: =P43 -> #REF! | AJ43: =Q43 -> #REF! | AL43: =#REF! -> #REF! | AM43: =#REF! -> #REF! | AN43: =#REF! -> #REF! | AO43: =#REF! -> #REF! | AP43: =#REF! -> #REF! | AQ43: =#REF! -> #REF! | AR43: =#REF! -> #REF! | AS43: =#REF! -> #REF! | ... AW43: =#REF! -> #REF!
S44: =#REF! -> #REF! | T44: =#REF! -> #REF! | U44: =#REF! -> #REF! | V44: =#REF! -> #REF! | W44: =#REF! -> #REF! | X44: =#REF! -> #REF! | Y44: =#REF! -> #REF! | Z44: =#REF! -> #REF! | ... AD44: =#REF! -> #REF! | AL44: =#REF! -> #REF! | AM44: =#REF! -> #REF! | AN44: =#REF! -> #REF! | AO44: =#REF! -> #REF! | AP44: =#REF! -> #REF! | AQ44: =#REF! -> #REF! | AR44: =#REF! -> #REF! | AS44: =#REF! -> #REF! | ... AW44: =#REF! -> #REF!
B45: 18 | C45: =VLOOKUP(B45,#REF!,2,0) -> #REF! | D45: =VLOOKUP(B45,#REF!,10,0) -> #REF! | F45: =VLOOKUP(B45,#REF!,15,0) -> #REF! | G45: =D45-F45 -> #REF! | I45: =VLOOKUP(B45,#REF!,11,0) -> #REF! | K45: =I45/SUM($I$11:$J$50) -> #REF! | N45: 18 | O45: =C45 -> #REF! | P45: =I45 -> #REF! | Q45: =K45 -> #REF! | S45: =#REF! -> #REF! | T45: =#REF! -> #REF! | U45: =#REF! -> #REF! | V45: =#REF! -> #REF! | W45: =#REF! -> #REF! | X45: =#REF! -> #REF! | Y45: =#REF! -> #REF! | Z45: =#REF! -> #REF! | ... AD45: =#REF! -> #REF! | AG45: 18 | AH45: =O45 -> #REF! | AI45: =P45 -> #REF! | AJ45: =Q45 -> #REF! | AL45: =#REF! -> #REF! | AM45: =#REF! -> #REF! | AN45: =#REF! -> #REF! | AO45: =#REF! -> #REF! | AP45: =#REF! -> #REF! | AQ45: =#REF! -> #REF! | AR45: =#REF! -> #REF! | AS45: =#REF! -> #REF! | ... AW45: =#REF! -> #REF!
S46: =#REF! -> #REF! | T46: =#REF! -> #REF! | U46: =#REF! -> #REF! | V46: =#REF! -> #REF! | W46: =#REF! -> #REF! | X46: =#REF! -> #REF! | Y46: =#REF! -> #REF! | Z46: =#REF! -> #REF! | ... AD46: =#REF! -> #REF! | AL46: =#REF! -> #REF! | AM46: =#REF! -> #REF! | AN46: =#REF! -> #REF! | AO46: =#REF! -> #REF! | AP46: =#REF! -> #REF! | AQ46: =#REF! -> #REF! | AR46: =#REF! -> #REF! | AS46: =#REF! -> #REF! | ... AW46: =#REF! -> #REF! | AZ46: ACUMULADO | BA46: =S56 -> #REF! | BB46: =T56 -> #REF! | BC46: =U56 -> #REF! | BD46: =V56 -> #REF! | BE46: =W56 -> #REF! | BF46: =X56 -> #REF! | BG46: =Y56 -> #REF! | BH46: =Z56 -> #REF! | ... BL46: =AD56 -> #REF! | BM46: =AL56 -> #REF! | BN46: =AM56 -> #REF! | BO46: =AN56 -> #REF! | BP46: =AO56 -> #REF! | BQ46: =AP56 -> #REF! | BR46: =AQ56 -> #REF! | BS46: =AR56 -> #REF! | BT46: =AS56 -> #REF! | ... BX46: =AW56 -> #REF!
B47: 19 | C47: =VLOOKUP(B47,#REF!,2,0) -> #REF! | D47: =VLOOKUP(B47,#REF!,10,0) -> #REF! | F47: =VLOOKUP(B47,#REF!,15,0) -> #REF! | G47: =D47-F47 -> #REF! | I47: =VLOOKUP(B47,#REF!,11,0) -> #REF! | K47: =I47/SUM($I$11:$J$50) -> #REF! | N47: 19 | O47: =C47 -> #REF! | P47: =I47 -> #REF! | Q47: =K47 -> #REF! | S47: =#REF! -> #REF! | T47: =#REF! -> #REF! | U47: =#REF! -> #REF! | V47: =#REF! -> #REF! | W47: =#REF! -> #REF! | X47: =#REF! -> #REF! | Y47: =#REF! -> #REF! | Z47: =#REF! -> #REF! | ... AD47: =#REF! -> #REF! | AG47: 19 | AH47: =O47 -> #REF! | AI47: =P47 -> #REF! | AJ47: =Q47 -> #REF! | AL47: =#REF! -> #REF! | AM47: =#REF! -> #REF! | AN47: =#REF! -> #REF! | AO47: =#REF! -> #REF! | AP47: =#REF! -> #REF! | AQ47: =#REF! -> #REF! | AR47: =#REF! -> #REF! | AS47: =#REF! -> #REF! | ... AW47: =#REF! -> #REF!
S48: =#REF! -> #REF! | T48: =#REF! -> #REF! | U48: =#REF! -> #REF! | V48: =#REF! -> #REF! | W48: =#REF! -> #REF! | X48: =#REF! -> #REF! | Y48: =#REF! -> #REF! | Z48: =#REF! -> #REF! | ... AD48: =#REF! -> #REF! | AL48: =#REF! -> #REF! | AM48: =#REF! -> #REF! | AN48: =#REF! -> #REF! | AO48: =#REF! -> #REF! | AP48: =#REF! -> #REF! | AQ48: =#REF! -> #REF! | AR48: =#REF! -> #REF! | AS48: =#REF! -> #REF! | ... AW48: =#REF! -> #REF!
B49: 20 | C49: =VLOOKUP(B49,#REF!,2,0) -> #REF! | D49: =VLOOKUP(B49,#REF!,10,0) -> #REF! | F49: =VLOOKUP(B49,#REF!,15,0) -> #REF! | G49: =D49-F49 -> #REF! | I49: =VLOOKUP(B49,#REF!,11,0) -> #REF! | K49: =I49/SUM($I$11:$J$50) -> #REF! | N49: 20 | O49: =C49 -> #REF! | P49: =I49 -> #REF! | Q49: =K49 -> #REF! | S49: =#REF! -> #REF! | T49: =#REF! -> #REF! | U49: =#REF! -> #REF! | V49: =#REF! -> #REF! | W49: =#REF! -> #REF! | X49: =#REF! -> #REF! | Y49: =#REF! -> #REF! | Z49: =#REF! -> #REF! | ... AD49: =#REF! -> #REF! | AG49: 20 | AH49: =O49 -> #REF! | AI49: =P49 -> #REF! | AJ49: =Q49 -> #REF! | AL49: =#REF! -> #REF! | AM49: =#REF! -> #REF! | AN49: =#REF! -> #REF! | AO49: =#REF! -> #REF! | AP49: =#REF! -> #REF! | AQ49: =#REF! -> #REF! | AR49: =#REF! -> #REF! | AS49: =#REF! -> #REF! | ... AW49: =#REF! -> #REF!
S50: =#REF! -> #REF! | T50: =#REF! -> #REF! | U50: =#REF! -> #REF! | V50: =#REF! -> #REF! | W50: =#REF! -> #REF! | X50: =#REF! -> #REF! | Y50: =#REF! -> #REF! | Z50: =#REF! -> #REF! | ... AD50: =#REF! -> #REF! | AL50: =#REF! -> #REF! | AM50: =#REF! -> #REF! | AN50: =#REF! -> #REF! | AO50: =#REF! -> #REF! | AP50: =#REF! -> #REF! | AQ50: =#REF! -> #REF! | AR50: =#REF! -> #REF! | AS50: =#REF! -> #REF! | ... AW50: =#REF! -> #REF!
B52: CUSTO TOTAL DE CONSTRUÇÃO | I52: =SUM(D11:D30) -> #REF! | N52: AVANÇO FÍSICO PLANEJADO MENSAL | S52: =#REF! -> #REF! | T52: =#REF! -> #REF! | U52: =#REF! -> #REF! | V52: =#REF! -> #REF! | W52: =#REF! -> #REF! | X52: =#REF! -> #REF! | Y52: =#REF! -> #REF! | Z52: =#REF! -> #REF! | ... AD52: =#REF! -> #REF! | AG52: AVANÇO FÍSICO PLANEJADO MENSAL | AL52: =#REF! -> #REF! | AM52: =#REF! -> #REF! | AN52: =#REF! -> #REF! | AO52: =#REF! -> #REF! | AP52: =#REF! -> #REF! | AQ52: =#REF! -> #REF! | AR52: =#REF! -> #REF! | AS52: =#REF! -> #REF! | ... AW52: =#REF! -> #REF!
N53: AVANÇO FÍSICO PLANEJADO ACUMULADO | S53: =#REF! -> #REF! | T53: =#REF! -> #REF! | U53: =#REF! -> #REF! | V53: =#REF! -> #REF! | W53: =#REF! -> #REF! | X53: =#REF! -> #REF! | Y53: =#REF! -> #REF! | Z53: =#REF! -> #REF! | ... AD53: =#REF! -> #REF! | AG53: AVANÇO FÍSICO PLANEJADO ACUMULADO | AL53: =#REF! -> #REF! | AM53: =#REF! -> #REF! | AN53: =#REF! -> #REF! | AO53: =#REF! -> #REF! | AP53: =#REF! -> #REF! | AQ53: =#REF! -> #REF! | AR53: =#REF! -> #REF! | AS53: =#REF! -> #REF! | ... AW53: =#REF! -> #REF!
B55: CUSTO TOTAL COM BDI | G55: 0.06 | I55: =SUM(I11:I30) -> #REF! | N55: FÍSICO-FINANCEIRO MENSAL DE OBRA | S55: =#REF! -> #REF! | T55: =#REF! -> #REF! | U55: =#REF! -> #REF! | V55: =#REF! -> #REF! | W55: =#REF! -> #REF! | X55: =#REF! -> #REF! | Y55: =#REF! -> #REF! | Z55: =#REF! -> #REF! | ... AD55: =#REF! -> #REF! | AG55: FÍSICO-FINANCEIRO MENSAL DE OBRA | AL55: =#REF! -> #REF! | AM55: =#REF! -> #REF! | AN55: =#REF! -> #REF! | AO55: =#REF! -> #REF! | AP55: =#REF! -> #REF! | AQ55: =#REF! -> #REF! | AR55: =#REF! -> #REF! | AS55: =#REF! -> #REF! | ... AW55: =#REF! -> #REF!
N56: FÍSICO-FINANCEIRO ACUMULADO DE OBRA | S56: =#REF! -> #REF! | T56: =#REF! -> #REF! | U56: =#REF! -> #REF! | V56: =#REF! -> #REF! | W56: =#REF! -> #REF! | X56: =#REF! -> #REF! | Y56: =#REF! -> #REF! | Z56: =#REF! -> #REF! | ... AD56: =#REF! -> #REF! | AG56: FÍSICO-FINANCEIRO ACUMULADO DE OBRA | AL56: =#REF! -> #REF! | AM56: =#REF! -> #REF! | AN56: =#REF! -> #REF! | AO56: =#REF! -> #REF! | AP56: =#REF! -> #REF! | AQ56: =#REF! -> #REF! | AR56: =#REF! -> #REF! | AS56: =#REF! -> #REF! | ... AW56: =#REF! -> #REF!
